Workbook

Sheet Tableau de bord
A1: IAT — Tableau de bord CODIR · Pipeline clients & renouvellements
A2: Calculé automatiquement à partir des onglets Renouvellements et Pipeline · Situation au 13/10/2026 · Montants en FCFA
A4: Montant total facturé | B4: Total encaissé | C4: Reste à encaisser | D4: Taux d'encaissement | E4: Deals en attente
A5: =SUM(Pipeline!$G$5:$G$32) -> 299743360 | B5: =SUM(Pipeline!$H$5:$H$32) -> 295243360 | C5: =SUM(Pipeline!$I$5:$I$32) -> 4500000 | D5: =IF(SUM(Pipeline!$G$5:$G$32)=0,"",SUM(Pipeline!$H$5:$H$32)/SUM(Pipeline!$G$5:$G$32)) -> 0.98498716 | E5: =COUNTIF(Pipeline!$K$5:$K$32,"Attente*")+COUNTIF(Pipeline!$K$5:$K$32,"Offre*")+COUNTIF(Pipeline!$K$5:$K$32,"Prospection") -> 2
A7: 1. Renouvellements à sécuriser
A8: Montant récurrent annuel | B8: Échus non renouvelés | C8: Nb contrats échus | D8: Échéances sous 12 mois | E8: À relancer sous 90 j
A9: =SUM(Renouvellements!$E$5:$E$18) -> 143648024 | B9: =SUMIF(Renouvellements!$K$5:$K$18,"Échu*",Renouvellements!$E$5:$E$18) -> 28961849 | C9: =COUNTIF(Renouvellements!$K$5:$K$18,"Échu*") -> 2 | D9: =SUMIFS(Renouvellements!$E$5:$E$18,Renouvellements!$G$5:$G$18,">="&TODAY(),Renouvellements!$G$5:$G$18,"<="&EDATE(TODAY(),12)) -> 96686175 | E9: =COUNTIF(Renouvellements!$K$5:$K$18,"À relancer*") -> 0
A11: Client | B11: Contrat | C11: Dernière facturation | D11: Montant attendu | E11: Prochaine échéance | F11: Jours restants | G11: Alerte | H11: Statut du renouvellement
A12: =Renouvellements!B5 -> CNPS | B12: =Renouvellements!C5 -> Licences ManageEngine | C12: =IF(ISNUMBER(Renouvellements!D5),Renouvellements!D5,"N/A") -> 45698 | D12: =Renouvellements!E5 -> 21578849 | E12: =IF(ISNUMBER(Renouvellements!G5),Renouvellements!G5,"À confirmer") -> 46063 | F12: =IF(ISNUMBER(Renouvellements!H5),Renouvellements!H5,"") -> -251 | G12: =Renouvellements!K5 -> Échu - urgent | H12: =IF(Renouvellements!L5="","",Renouvellements!L5) -> Offre envoyée
A13: =Renouvellements!B6 -> NEURONES | B13: =Renouvellements!C6 -> Licence WithSecure | C13: =IF(ISNUMBER(Renouvellements!D6),Renouvellements!D6,"N/A") -> 45890 | D13: =Renouvellements!E6 -> 7383000 | E13: =IF(ISNUMBER(Renouvellements!G6),Renouvellements!G6,"À confirmer") -> 46255 | F13: =IF(ISNUMBER(Renouvellements!H6),Renouvellements!H6,"") -> -59 | G13: =Renouvellements!K6 -> Échu - urgent | H13: =IF(Renouvellements!L6="","",Renouvellements!L6) -> Attente cotation fournisseur
A14: =Renouvellements!B7 -> CNAM | B14: =Renouvellements!C7 -> Licences ManageEngine | C14: =IF(ISNUMBER(Renouvellements!D7),Renouvellements!D7,"N/A") -> 46080 | D14: =Renouvellements!E7 -> 66309707 | E14: =IF(ISNUMBER(Renouvellements!G7),Renouvellements!G7,"À confirmer") -> 46445 | F14: =IF(ISNUMBER(Renouvellements!H7),Renouvellements!H7,"") -> 131 | G14: =Renouvellements!K7 -> À venir | H14: =IF(Renouvellements!L7="","",Renouvellements!L7) -> Non démarré
A15: =Renouvellements!B8 -> FER | B15: =Renouvellements!C8 -> Licences ManageEngine | C15: =IF(ISNUMBER(Renouvellements!D8),Renouvellements!D8,"N/A") -> 46197 | D15: =Renouvellements!E8 -> 28766400 | E15: =IF(ISNUMBER(Renouvellements!G8),Renouvellements!G8,"À confirmer") -> 46562 | F15: =IF(ISNUMBER(Renouvellements!H8),Renouvellements!H8,"") -> 248 | G15: =Renouvellements!K8 -> À venir | H15: =IF(Renouvellements!L8="","",Renouvellements!L8) -> Non démarré
A16: =Renouvellements!B9 -> NSIA | B16: =Renouvellements!C9 -> Licences ManageEngine | C16: =IF(ISNUMBER(Renouvellements!D9),Renouvellements!D9,"N/A") -> 46283 | D16: =Renouvellements!E9 -> 1610068 | E16: =IF(ISNUMBER(Renouvellements!G9),Renouvellements!G9,"À confirmer") -> 46648 | F16: =IF(ISNUMBER(Renouvellements!H9),Renouvellements!H9,"") -> 334 | G16: =Renouvellements!K9 -> À venir | H16: =IF(Renouvellements!L9="","",Renouvellements!L9) -> Non démarré
A17: =Renouvellements!B10 -> CNAM | B17: =Renouvellements!C10 -> Contrat de maintenance ManageEngine | C17: =IF(ISNUMBER(Renouvellements!D10),Renouvellements!D10,"N/A") -> N/A | D17: =Renouvellements!E10 -> 18000000 | E17: =IF(ISNUMBER(Renouvellements!G10),Renouvellements!G10,"À confirmer") -> À confirmer | F17: =IF(ISNUMBER(Renouvellements!H10),Renouvellements!H10,"") | G17: =Renouvellements!K10 -> Date à confirmer | H17: =IF(Renouvellements!L10="","",Renouvellements!L10) -> Non démarré
A19: 2. Synthèse par exercice
A20: Exercice | B20: Nb deals | C20: Montant facturé | D20: Encaissé | E20: Solde à encaisser | F20: Taux d'encaissement | G20: Deals en attente | H20: Évolution facturé vs N-1
A21: 2024 | B21: =COUNTIF(Pipeline!$B$5:$B$32,A21) -> 2 | C21: =SUMIF(Pipeline!$B$5:$B$32,A21,Pipeline!$G$5:$G$32) -> 70802690 | D21: =SUMIF(Pipeline!$B$5:$B$32,A21,Pipeline!$H$5:$H$32) -> 70802690 | E21: =SUMIF(Pipeline!$B$5:$B$32,A21,Pipeline!$I$5:$I$32) -> 0 | F21: =IF(C21=0,"",D21/C21) -> 1 | G21: =COUNTIFS(Pipeline!$B$5:$B$32,A21,Pipeline!$K$5:$K$32,"Attente*")+COUNTIFS(Pipeline!$B$5:$B$32,A21,Pipeline!$K$5:$K$32,"Offre*")+COUNTIFS(Pipeline!$B$5:$B$32,A21,Pipeline!$K$5:$K$32,"Prospection") -> 0
A22: 2025 | B22: =COUNTIF(Pipeline!$B$5:$B$32,A22) -> 5 | C22: =SUMIF(Pipeline!$B$5:$B$32,A22,Pipeline!$G$5:$G$32) -> 114254495 | D22: =SUMIF(Pipeline!$B$5:$B$32,A22,Pipeline!$H$5:$H$32) -> 114254495 | E22: =SUMIF(Pipeline!$B$5:$B$32,A22,Pipeline!$I$5:$I$32) -> 0 | F22: =IF(C22=0,"",D22/C22) -> 1 | G22: =COUNTIFS(Pipeline!$B$5:$B$32,A22,Pipeline!$K$5:$K$32,"Attente*")+COUNTIFS(Pipeline!$B$5:$B$32,A22,Pipeline!$K$5:$K$32,"Offre*")+COUNTIFS(Pipeline!$B$5:$B$32,A22,Pipeline!$K$5:$K$32,"Prospection") -> 0 | H22: =IF(C21=0,"",C22/C21-1) -> 0.61370274
A23: 2026 | B23: =COUNTIF(Pipeline!$B$5:$B$32,A23) -> 6 | C23: =SUMIF(Pipeline!$B$5:$B$32,A23,Pipeline!$G$5:$G$32) -> 114686175 | D23: =SUMIF(Pipeline!$B$5:$B$32,A23,Pipeline!$H$5:$H$32) -> 110186175 | E23: =SUMIF(Pipeline!$B$5:$B$32,A23,Pipeline!$I$5:$I$32) -> 4500000 | F23: =IF(C23=0,"",D23/C23) -> 0.96076249 | G23: =COUNTIFS(Pipeline!$B$5:$B$32,A23,Pipeline!$K$5:$K$32,"Attente*")+COUNTIFS(Pipeline!$B$5:$B$32,A23,Pipeline!$K$5:$K$32,"Offre*")+COUNTIFS(Pipeline!$B$5:$B$32,A23,Pipeline!$K$5:$K$32,"Prospection") -> 2 | H23: =IF(C22=0,"",C23/C22-1) -> 0.0037782321
A24: TOTAL | B24: =SUM(B21:B23) -> 13 | C24: =SUM(C21:C23) -> 299743360 | D24: =SUM(D21:D23) -> 295243360 | E24: =SUM(E21:E23) -> 4500000 | F24: =IF(C24=0,"",D24/C24) -> 0.98498716 | G24: =SUM(G21:G23) -> 2
A26: 3. Historique par client — montant facturé (suivi des renouvellements)
A27: Client | B27: 2024 | C27: 2025 | D27: 2026 | E27: Total 2024-2026 | F27: Solde à encaisser | G27: Situation 2026
A28: CNAM | B28: =SUMIFS(Pipeline!$G$5:$G$32,Pipeline!$C$5:$C$32,$A28,Pipeline!$B$5:$B$32,2024) -> 69799690 | C28: =SUMIFS(Pipeline!$G$5:$G$32,Pipeline!$C$5:$C$32,$A28,Pipeline!$B$5:$B$32,2025) -> 84309706 | D28: =SUMIFS(Pipeline!$G$5:$G$32,Pipeline!$C$5:$C$32,$A28,Pipeline!$B$5:$B$32,2026) -> 84309707 | E28: =SUM(B28:D28) -> 238419103 | F28: =SUMIF(Pipeline!$C$5:$C$32,A28,Pipeline!$I$5:$I$32) -> 4500000 | G28: =IF(COUNTIFS(Pipeline!$C$5:$C$32,A28,Pipeline!$B$5:$B$32,2026,Pipeline!$K$5:$K$32,"Attente*")+COUNTIFS(Pipeline!$C$5:$C$32,A28,Pipeline!$B$5:$B$32,2026,Pipeline!$K$5:$K$32,"Offre*")>0,"En attente",IF(SUMIFS(Pipeline!$I$5:$I$32,Pipeline!$C$5:$C$32,A28,Pipeline!$B$5:$B$32,2026)>0,"Solde à encaisser",IF(D28>0,"Renouvelé","Non renouvelé"))) -> Solde à encaisser
A29: CNPS | B29: =SUMIFS(Pipeline!$G$5:$G$32,Pipeline!$C$5:$C$32,$A29,Pipeline!$B$5:$B$32,2024) -> 0 | C29: =SUMIFS(Pipeline!$G$5:$G$32,Pipeline!$C$5:$C$32,$A29,Pipeline!$B$5:$B$32,2025) -> 21578849 | D29: =SUMIFS(Pipeline!$G$5:$G$32,Pipeline!$C$5:$C$32,$A29,Pipeline!$B$5:$B$32,2026) -> 0 | E29: =SUM(B29:D29) -> 21578849 | F29: =SUMIF(Pipeline!$C$5:$C$32,A29,Pipeline!$I$5:$I$32) -> 0 | G29: =IF(COUNTIFS(Pipeline!$C$5:$C$32,A29,Pipeline!$B$5:$B$32,2026,Pipeline!$K$5:$K$32,"Attente*")+COUNTIFS(Pipeline!$C$5:$C$32,A29,Pipeline!$B$5:$B$32,2026,Pipeline!$K$5:$K$32,"Offre*")>0,"En attente",IF(SUMIFS(Pipeline!$I$5:$I$32,Pipeline!$C$5:$C$32,A29,Pipeline!$B$5:$B$32,2026)>0,"Solde à encaisser",IF(D29>0,"Renouvelé","Non renouvelé"))) -> En attente
A30: FER | B30: =SUMIFS(Pipeline!$G$5:$G$32,Pipeline!$C$5:$C$32,$A30,Pipeline!$B$5:$B$32,2024) -> 0 | C30: =SUMIFS(Pipeline!$G$5:$G$32,Pipeline!$C$5:$C$32,$A30,Pipeline!$B$5:$B$32,2025) -> 0 | D30: =SUMIFS(Pipeline!$G$5:$G$32,Pipeline!$C$5:$C$32,$A30,Pipeline!$B$5:$B$32,2026) -> 28766400 | E30: =SUM(B30:D30) -> 28766400 | F30: =SUMIF(Pipeline!$C$5:$C$32,A30,Pipeline!$I$5:$I$32) -> 0 | G30: =IF(COUNTIFS(Pipeline!$C$5:$C$32,A30,Pipeline!$B$5:$B$32,2026,Pipeline!$K$5:$K$32,"Attente*")+COUNTIFS(Pipeline!$C$5:$C$32,A30,Pipeline!$B$5:$B$32,2026,Pipeline!$K$5:$K$32,"Offre*")>0,"En attente",IF(SUMIFS(Pipeline!$I$5:$I$32,Pipeline!$C$5:$C$32,A30,Pipeline!$B$5:$B$32,2026)>0,"Solde à encaisser",IF(D30>0,"Renouvelé","Non renouvelé"))) -> Renouvelé
A31: NEURONE | B31: =SUMIFS(Pipeline!$G$5:$G$32,Pipeline!$C$5:$C$32,$A31,Pipeline!$B$5:$B$32,2024) -> 0 | C31: =SUMIFS(Pipeline!$G$5:$G$32,Pipeline!$C$5:$C$32,$A31,Pipeline!$B$5:$B$32,2025) -> 7383000 | D31: =SUMIFS(Pipeline!$G$5:$G$32,Pipeline!$C$5:$C$32,$A31,Pipeline!$B$5:$B$32,2026) -> 0 | E31: =SUM(B31:D31) -> 7383000 | F31: =SUMIF(Pipeline!$C$5:$C$32,A31,Pipeline!$I$5:$I$32) -> 0 | G31: =IF(COUNTIFS(Pipeline!$C$5:$C$32,A31,Pipeline!$B$5:$B$32,2026,Pipeline!$K$5:$K$32,"Attente*")+COUNTIFS(Pipeline!$C$5:$C$32,A31,Pipeline!$B$5:$B$32,2026,Pipeline!$K$5:$K$32,"Offre*")>0,"En attente",IF(SUMIFS(Pipeline!$I$5:$I$32,Pipeline!$C$5:$C$32,A31,Pipeline!$B$5:$B$32,2026)>0,"Solde à encaisser",IF(D31>0,"Renouvelé","Non renouvelé"))) -> En attente
A32: NSIA | B32: =SUMIFS(Pipeline!$G$5:$G$32,Pipeline!$C$5:$C$32,$A32,Pipeline!$B$5:$B$32,2024) -> 1003000 | C32: =SUMIFS(Pipeline!$G$5:$G$32,Pipeline!$C$5:$C$32,$A32,Pipeline!$B$5:$B$32,2025) -> 982940 | D32: =SUMIFS(Pipeline!$G$5:$G$32,Pipeline!$C$5:$C$32,$A32,Pipeline!$B$5:$B$32,2026) -> 1610068 | E32: =SUM(B32:D32) -> 3596008 | F32: =SUMIF(Pipeline!$C$5:$C$32,A32,Pipeline!$I$5:$I$32) -> 0 | G32: =IF(COUNTIFS(Pipeline!$C$5:$C$32,A32,Pipeline!$B$5:$B$32,2026,Pipeline!$K$5:$K$32,"Attente*")+COUNTIFS(Pipeline!$C$5:$C$32,A32,Pipeline!$B$5:$B$32,2026,Pipeline!$K$5:$K$32,"Offre*")>0,"En attente",IF(SUMIFS(Pipeline!$I$5:$I$32,Pipeline!$C$5:$C$32,A32,Pipeline!$B$5:$B$32,2026)>0,"Solde à encaisser",IF(D32>0,"Renouvelé","Non renouvelé"))) -> Renouvelé
A33: TOTAL | B33: =SUM(B28:B32) -> 70802690 | C33: =SUM(C28:C32) -> 114254495 | D33: =SUM(D28:D32) -> 114686175 | E33: =SUM(E28:E32) -> 299743360 | F33: =SUM(F28:F32) -> 4500000
A35: 4. Répartition par étape du pipeline
A36: Étape | B36: Nb deals | C36: Montant | D36: Solde à encaisser
A37: =Listes!A2 -> Prospection | B37: =COUNTIF(Pipeline!$K$5:$K$32,A37) -> 0 | C37: =SUMIF(Pipeline!$K$5:$K$32,A37,Pipeline!$G$5:$G$32) -> 0 | D37: =SUMIF(Pipeline!$K$5:$K$32,A37,Pipeline!$I$5:$I$32) -> 0
A38: =Listes!A3 -> Attente cotation fournisseur | B38: =COUNTIF(Pipeline!$K$5:$K$32,A38) -> 1 | C38: =SUMIF(Pipeline!$K$5:$K$32,A38,Pipeline!$G$5:$G$32) -> 0 | D38: =SUMIF(Pipeline!$K$5:$K$32,A38,Pipeline!$I$5:$I$32) -> 0
A39: =Listes!A4 -> Offre envoyée - attente client | B39: =COUNTIF(Pipeline!$K$5:$K$32,A39) -> 1 | C39: =SUMIF(Pipeline!$K$5:$K$32,A39,Pipeline!$G$5:$G$32) -> 0 | D39: =SUMIF(Pipeline!$K$5:$K$32,A39,Pipeline!$I$5:$I$32) -> 0
A40: =Listes!A5 -> Facturé - non encaissé | B40: =COUNTIF(Pipeline!$K$5:$K$32,A40) -> 0 | C40: =SUMIF(Pipeline!$K$5:$K$32,A40,Pipeline!$G$5:$G$32) -> 0 | D40: =SUMIF(Pipeline!$K$5:$K$32,A40,Pipeline!$I$5:$I$32) -> 0
A41: =Listes!A6 -> Encaissement partiel | B41: =COUNTIF(Pipeline!$K$5:$K$32,A41) -> 1 | C41: =SUMIF(Pipeline!$K$5:$K$32,A41,Pipeline!$G$5:$G$32) -> 18000000 | D41: =SUMIF(Pipeline!$K$5:$K$32,A41,Pipeline!$I$5:$I$32) -> 4500000
A42: =Listes!A7 -> Soldé | B42: =COUNTIF(Pipeline!$K$5:$K$32,A42) -> 10 | C42: =SUMIF(Pipeline!$K$5:$K$32,A42,Pipeline!$G$5:$G$32) -> 281743360 | D42: =SUMIF(Pipeline!$K$5:$K$32,A42,Pipeline!$I$5:$I$32) -> 0
A43: =Listes!A8 -> Perdu | B43: =COUNTIF(Pipeline!$K$5:$K$32,A43) -> 0 | C43: =SUMIF(Pipeline!$K$5:$K$32,A43,Pipeline!$G$5:$G$32) -> 0 | D43: =SUMIF(Pipeline!$K$5:$K$32,A43,Pipeline!$I$5:$I$32) -> 0

Sheet Renouvellements
A1: IAT — Calendrier et suivi des relances de renouvellement
A2: Contrats récurrents (licences et maintenance). Prochaine échéance = dernière facturation + 12 mois. Fond jaune = à renseigner (statut, porteur, relances). Texte bleu = données du point deals. Colonnes grises = calculées.
A4: N° | B4: Client | C4: Contrat / produit | D4: Dernière facturation | E4: Dernier montant facturé | F4: Historique facturé | G4: Prochaine échéance | H4: Jours restants | I4: Relance J-90 | J4: Relance J-30 | K4: Alerte | L4: Statut du renouvellement | M4: Porteur | N4: Date dernière relance | O4: Prochaine action | P4: Commentaire
A5: 1 | B5: CNPS | C5: Licences ManageEngine | D5: 45698 | E5: 21578849 | F5: 2025 : 21,6 M | G5: =IF(ISNUMBER(D5),EDATE(D5,12),"") -> 46063 | H5: =IF(ISNUMBER(G5),G5-TODAY(),"") -> -251 | I5: =IF(ISNUMBER(G5),G5-90,"") -> 45973 | J5: =IF(ISNUMBER(G5),G5-30,"") -> 46033 | K5: =IF(B5="","",IF(L5="Renouvelé","Renouvelé",IF(L5="Perdu","Perdu",IF(NOT(ISNUMBER(G5)),"Date à confirmer",IF(G5<TODAY(),"Échu - urgent",IF(G5-TODAY()<=90,"À relancer (≤ 90 j)","À venir")))))) -> Échu - urgent | L5: Offre envoyée | O5: Relance commerciale + rendez-vous avec la DSI CNPS pour obtenir la décision | P5: Offre 2026 en attente de retour CNPS. Échéance dépassée.
A6: 2 | B6: NEURONES | C6: Licence WithSecure | D6: 45890 | E6: 7383000 | F6: 2025 : 7,4 M | G6: =IF(ISNUMBER(D6),EDATE(D6,12),"") -> 46255 | H6: =IF(ISNUMBER(G6),G6-TODAY(),"") -> -59 | I6: =IF(ISNUMBER(G6),G6-90,"") -> 46165 | J6: =IF(ISNUMBER(G6),G6-30,"") -> 46225 | K6: =IF(B6="","",IF(L6="Renouvelé","Renouvelé",IF(L6="Perdu","Perdu",IF(NOT(ISNUMBER(G6)),"Date à confirmer",IF(G6<TODAY(),"Échu - urgent",IF(G6-TODAY()<=90,"À relancer (≤ 90 j)","À venir")))))) -> Échu - urgent | L6: Attente cotation fournisseur | O6: Relancer le fournisseur pour la cotation, puis émettre l'offre | P6: Blocage côté fournisseur. Échéance dépassée.
A7: 3 | B7: CNAM | C7: Licences ManageEngine | D7: 46080 | E7: 66309707 | F7: 2024 : 69,8 M · 2025 : 66,3 M · 2026 : 66,3 M | G7: =IF(ISNUMBER(D7),EDATE(D7,12),"") -> 46445 | H7: =IF(ISNUMBER(G7),G7-TODAY(),"") -> 131 | I7: =IF(ISNUMBER(G7),G7-90,"") -> 46355 | J7: =IF(ISNUMBER(G7),G7-30,"") -> 46415 | K7: =IF(B7="","",IF(L7="Renouvelé","Renouvelé",IF(L7="Perdu","Perdu",IF(NOT(ISNUMBER(G7)),"Date à confirmer",IF(G7<TODAY(),"Échu - urgent",IF(G7-TODAY()<=90,"À relancer (≤ 90 j)","À venir")))))) -> À venir | L7: Non démarré | O7: Préparer l'offre de renouvellement 2027 avant la relance J-90 | P7: Premier contrat : 46 % du montant récurrent annuel
A8: 4 | B8: FER | C8: Licences ManageEngine | D8: 46197 | E8: 28766400 | F8: 2026 : 28,8 M (nouveau client) | G8: =IF(ISNUMBER(D8),EDATE(D8,12),"") -> 46562 | H8: =IF(ISNUMBER(G8),G8-TODAY(),"") -> 248 | I8: =IF(ISNUMBER(G8),G8-90,"") -> 46472 | J8: =IF(ISNUMBER(G8),G8-30,"") -> 46532 | K8: =IF(B8="","",IF(L8="Renouvelé","Renouvelé",IF(L8="Perdu","Perdu",IF(NOT(ISNUMBER(G8)),"Date à confirmer",IF(G8<TODAY(),"Échu - urgent",IF(G8-TODAY()<=90,"À relancer (≤ 90 j)","À venir")))))) -> À venir | L8: Non démarré | O8: Point de satisfaction client avant la relance J-90
A9: 5 | B9: NSIA | C9: Licences ManageEngine | D9: 46283 | E9: 1610068 | F9: 2024 : 1,0 M · 2025 : 1,0 M · 2026 : 1,6 M | G9: =IF(ISNUMBER(D9),EDATE(D9,12),"") -> 46648 | H9: =IF(ISNUMBER(G9),G9-TODAY(),"") -> 334 | I9: =IF(ISNUMBER(G9),G9-90,"") -> 46558 | J9: =IF(ISNUMBER(G9),G9-30,"") -> 46618 | K9: =IF(B9="","",IF(L9="Renouvelé","Renouvelé",IF(L9="Perdu","Perdu",IF(NOT(ISNUMBER(G9)),"Date à confirmer",IF(G9<TODAY(),"Échu - urgent",IF(G9-TODAY()<=90,"À relancer (≤ 90 j)","À venir")))))) -> À venir | L9: Non démarré | P9: Renouvelle chaque année en septembre
A10: 6 | B10: CNAM | C10: Contrat de maintenance ManageEngine | D10: N/A | E10: 18000000 | F10: 2025 : 18 M · 2026 : 18 M | H10: =IF(ISNUMBER(G10),G10-TODAY(),"") | I10: =IF(ISNUMBER(G10),G10-90,"") | J10: =IF(ISNUMBER(G10),G10-30,"") | K10: =IF(B10="","",IF(L10="Renouvelé","Renouvelé",IF(L10="Perdu","Perdu",IF(NOT(ISNUMBER(G10)),"Date à confirmer",IF(G10<TODAY(),"Échu - urgent",IF(G10-TODAY()<=90,"À relancer (≤ 90 j)","À venir")))))) -> Date à confirmer | L10: Non démarré | O10: Renseigner la date de facturation / d'échéance du contrat | P10: Date de facturation « N/A » dans le point deals : échéance à saisir en colonne G. Solde 2026 de 4,5 M encore à encaisser.
A11: =IF(B11="","",ROW()-4) | G11: =IF(ISNUMBER(D11),EDATE(D11,12),"") | H11: =IF(ISNUMBER(G11),G11-TODAY(),"") | I11: =IF(ISNUMBER(G11),G11-90,"") | J11: =IF(ISNUMBER(G11),G11-30,"") | K11: =IF(B11="","",IF(L11="Renouvelé","Renouvelé",IF(L11="Perdu","Perdu",IF(NOT(ISNUMBER(G11)),"Date à confirmer",IF(G11<TODAY(),"Échu - urgent",IF(G11-TODAY()<=90,"À relancer (≤ 90 j)","À venir"))))))
A12: =IF(B12="","",ROW()-4) | G12: =IF(ISNUMBER(D12),EDATE(D12,12),"") | H12: =IF(ISNUMBER(G12),G12-TODAY(),"") | I12: =IF(ISNUMBER(G12),G12-90,"") | J12: =IF(ISNUMBER(G12),G12-30,"") | K12: =IF(B12="","",IF(L12="Renouvelé","Renouvelé",IF(L12="Perdu","Perdu",IF(NOT(ISNUMBER(G12)),"Date à confirmer",IF(G12<TODAY(),"Échu - urgent",IF(G12-TODAY()<=90,"À relancer (≤ 90 j)","À venir"))))))
A13: =IF(B13="","",ROW()-4) | G13: =IF(ISNUMBER(D13),EDATE(D13,12),"") | H13: =IF(ISNUMBER(G13),G13-TODAY(),"") | I13: =IF(ISNUMBER(G13),G13-90,"") | J13: =IF(ISNUMBER(G13),G13-30,"") | K13: =IF(B13="","",IF(L13="Renouvelé","Renouvelé",IF(L13="Perdu","Perdu",IF(NOT(ISNUMBER(G13)),"Date à confirmer",IF(G13<TODAY(),"Échu - urgent",IF(G13-TODAY()<=90,"À relancer (≤ 90 j)","À venir"))))))
A14: =IF(B14="","",ROW()-4) | G14: =IF(ISNUMBER(D14),EDATE(D14,12),"") | H14: =IF(ISNUMBER(G14),G14-TODAY(),"") | I14: =IF(ISNUMBER(G14),G14-90,"") | J14: =IF(ISNUMBER(G14),G14-30,"") | K14: =IF(B14="","",IF(L14="Renouvelé","Renouvelé",IF(L14="Perdu","Perdu",IF(NOT(ISNUMBER(G14)),"Date à confirmer",IF(G14<TODAY(),"Échu - urgent",IF(G14-TODAY()<=90,"À relancer (≤ 90 j)","À venir"))))))
A15: =IF(B15="","",ROW()-4) | G15: =IF(ISNUMBER(D15),EDATE(D15,12),"") | H15: =IF(ISNUMBER(G15),G15-TODAY(),"") | I15: =IF(ISNUMBER(G15),G15-90,"") | J15: =IF(ISNUMBER(G15),G15-30,"") | K15: =IF(B15="","",IF(L15="Renouvelé","Renouvelé",IF(L15="Perdu","Perdu",IF(NOT(ISNUMBER(G15)),"Date à confirmer",IF(G15<TODAY(),"Échu - urgent",IF(G15-TODAY()<=90,"À relancer (≤ 90 j)","À venir"))))))
A16: =IF(B16="","",ROW()-4) | G16: =IF(ISNUMBER(D16),EDATE(D16,12),"") | H16: =IF(ISNUMBER(G16),G16-TODAY(),"") | I16: =IF(ISNUMBER(G16),G16-90,"") | J16: =IF(ISNUMBER(G16),G16-30,"") | K16: =IF(B16="","",IF(L16="Renouvelé","Renouvelé",IF(L16="Perdu","Perdu",IF(NOT(ISNUMBER(G16)),"Date à confirmer",IF(G16<TODAY(),"Échu - urgent",IF(G16-TODAY()<=90,"À relancer (≤ 90 j)","À venir"))))))
A17: =IF(B17="","",ROW()-4) | G17: =IF(ISNUMBER(D17),EDATE(D17,12),"") | H17: =IF(ISNUMBER(G17),G17-TODAY(),"") | I17: =IF(ISNUMBER(G17),G17-90,"") | J17: =IF(ISNUMBER(G17),G17-30,"") | K17: =IF(B17="","",IF(L17="Renouvelé","Renouvelé",IF(L17="Perdu","Perdu",IF(NOT(ISNUMBER(G17)),"Date à confirmer",IF(G17<TODAY(),"Échu - urgent",IF(G17-TODAY()<=90,"À relancer (≤ 90 j)","À venir"))))))
A18: =IF(B18="","",ROW()-4) | G18: =IF(ISNUMBER(D18),EDATE(D18,12),"") | H18: =IF(ISNUMBER(G18),G18-TODAY(),"") | I18: =IF(ISNUMBER(G18),G18-90,"") | J18: =IF(ISNUMBER(G18),G18-30,"") | K18: =IF(B18="","",IF(L18="Renouvelé","Renouvelé",IF(L18="Perdu","Perdu",IF(NOT(ISNUMBER(G18)),"Date à confirmer",IF(G18<TODAY(),"Échu - urgent",IF(G18-TODAY()<=90,"À relancer (≤ 90 j)","À venir"))))))
A19: TOTAL | E19: =SUM(E5:E18) -> 143648024 | F19: Montant récurrent annuel (base dernière facturation)

Sheet Pipeline
A1: IAT — Pipeline des deals clients 2024 · 2025 · 2026
A2: Source : POINTS_DEALS_IAT.xlsx (onglets 2024, 2025, 2026), version du 13/10/2026 · Montants en FCFA · Saisie : texte bleu = données issues du fichier source ; fond jaune = à renseigner pendant le suivi ; colonnes grises = calculées
A4: N° | B4: Exercice | C4: Client | D4: Raison sociale (source) | E4: Deal / objet | F4: Date de facturation | G4: Montant du deal | H4: Montant encaissé | I4: Solde à encaisser | J4: Taux d'encaissement | K4: Étape pipeline | L4: Jours depuis facturation (si solde) | M4: Prochaine action | N4: Porteur | O4: Échéance | P4: Date dernière relance | Q4: Commentaire
A5: 1 | B5: 2024 | C5: NSIA | D5: NSIA ASSURANCES | E5: Achat de licences ManageEngine | F5: 45560 | G5: 1003000 | H5: 1003000 | I5: =IF(N(G5)=0,"",G5-H5) -> 0 | J5: =IF(N(G5)=0,"",H5/G5) -> 1 | K5: Soldé | L5: =IF(AND(ISNUMBER(F5),N(I5)>0),TODAY()-F5,"")
A6: 2 | B6: 2024 | C6: CNAM | D6: CNAM | E6: Déploiement de licences ManageEngine | F6: 45595 | G6: 69799690 | H6: 69799690 | I6: =IF(N(G6)=0,"",G6-H6) -> 0 | J6: =IF(N(G6)=0,"",H6/G6) -> 1 | K6: Soldé | L6: =IF(AND(ISNUMBER(F6),N(I6)>0),TODAY()-F6,"") | Q6: Encaissé le 05/02/2025 (chèque 5770692)
A7: 3 | B7: 2025 | C7: CNPS | D7: CNPS | E7: Achat de licences ManageEngine | F7: 45698 | G7: 21578849 | H7: 21578849 | I7: =IF(N(G7)=0,"",G7-H7) -> 0 | J7: =IF(N(G7)=0,"",H7/G7) -> 1 | K7: Soldé | L7: =IF(AND(ISNUMBER(F7),N(I7)>0),TODAY()-F7,"") | Q7: Encaissé le 18/03/2025
A8: 4 | B8: 2025 | C8: NEURONE | D8: NEURONE | E8: Achat de licence WithSecure | F8: 45890 | G8: 7383000 | H8: 7383000 | I8: =IF(N(G8)=0,"",G8-H8) -> 0 | J8: =IF(N(G8)=0,"",H8/G8) -> 1 | K8: Soldé | L8: =IF(AND(ISNUMBER(F8),N(I8)>0),TODAY()-F8,"") | Q8: Encaissé en 3 fois (27/08, 14/11, 02/12/2025)
A9: 5 | B9: 2025 | C9: CNAM | D9: CNAM | E9: Achat de licences ManageEngine | F9: 45898 | G9: 66309706 | H9: 66309706 | I9: =IF(N(G9)=0,"",G9-H9) -> 0 | J9: =IF(N(G9)=0,"",H9/G9) -> 1 | K9: Soldé | L9: =IF(AND(ISNUMBER(F9),N(I9)>0),TODAY()-F9,"") | Q9: Encaissé le 01/12/2025
A10: 6 | B10: 2025 | C10: CNAM | D10: CNAM | E10: Contrat de maintenance licences ManageEngine | F10: N/A | G10: 18000000 | H10: 18000000 | I10: =IF(N(G10)=0,"",G10-H10) -> 0 | J10: =IF(N(G10)=0,"",H10/G10) -> 1 | K10: Soldé | L10: =IF(AND(ISNUMBER(F10),N(I10)>0),TODAY()-F10,"") | Q10: Date de facturation non renseignée (N/A). Encaissé en déc. 2025 (9 M + 4,5 M + 4,5 M)
A11: 7 | B11: 2025 | C11: NSIA | D11: NSIA | E11: Achat de licences ManageEngine | F11: 45905 | G11: 982940 | H11: 982940 | I11: =IF(N(G11)=0,"",G11-H11) -> 0 | J11: =IF(N(G11)=0,"",H11/G11) -> 1 | K11: Soldé | L11: =IF(AND(ISNUMBER(F11),N(I11)>0),TODAY()-F11,"") | Q11: Encaissé le 24/09/2025
A12: 8 | B12: 2026 | C12: CNAM | D12: CNAM | E12: Renouvellement licences ManageEngine | F12: 46080 | G12: 66309707 | H12: 66309707 | I12: =IF(N(G12)=0,"",G12-H12) -> 0 | J12: =IF(N(G12)=0,"",H12/G12) -> 1 | K12: Soldé | L12: =IF(AND(ISNUMBER(F12),N(I12)>0),TODAY()-F12,"")
A13: 9 | B13: 2026 | C13: CNAM | D13: CNAM | E13: Contrat de maintenance licences ManageEngine | F13: N/A | G13: 18000000 | H13: 13500000 | I13: =IF(N(G13)=0,"",G13-H13) -> 4500000 | J13: =IF(N(G13)=0,"",H13/G13) -> 0.75 | K13: Encaissement partiel | L13: =IF(AND(ISNUMBER(F13),N(I13)>0),TODAY()-F13,"") | M13: Relancer la direction financière CNAM pour le solde (facture jointe) | O13: 46357 | Q13: Facturation trimestrielle de 4,5M
A14: 10 | B14: 2026 | C14: FER | D14: FER | E14: Renouvellement licences ManageEngine | F14: 46197 | G14: 28766400 | H14: 28766400 | I14: =IF(N(G14)=0,"",G14-H14) -> 0 | J14: =IF(N(G14)=0,"",H14/G14) -> 1 | K14: Soldé | L14: =IF(AND(ISNUMBER(F14),N(I14)>0),TODAY()-F14,"") | Q14: Nouveau client 2026
A15: 11 | B15: 2026 | C15: NSIA | D15: NSIA ASSURANCES VIE | E15: Renouvellement licences ManageEngine | F15: 46283 | G15: 1610068 | H15: 1610068 | I15: =IF(N(G15)=0,"",G15-H15) -> 0 | J15: =IF(N(G15)=0,"",H15/G15) -> 1 | K15: Soldé | L15: =IF(AND(ISNUMBER(F15),N(I15)>0),TODAY()-F15,"")
A16: 12 | B16: 2026 | C16: CNPS | D16: CNPS | E16: Renouvellement licences ManageEngine | H16: 0 | I16: =IF(N(G16)=0,"",G16-H16) | J16: =IF(N(G16)=0,"",H16/G16) | K16: Offre envoyée - attente client | L16: =IF(AND(ISNUMBER(F16),N(I16)>0),TODAY()-F16,"") | M16: Relance commerciale pour obtenir la décision CNPS | O16: 46318 | Q16: Montant non chiffré. 2025 : 21 578 849 facturé le 10/02/2025
A17: 13 | B17: 2026 | C17: NEURONE | D17: NEURONE | E17: Nouvelle offre (en attente cotation) | H17: 0 | I17: =IF(N(G17)=0,"",G17-H17) | J17: =IF(N(G17)=0,"",H17/G17) | K17: Attente cotation fournisseur | L17: =IF(AND(ISNUMBER(F17),N(I17)>0),TODAY()-F17,"") | M17: Relancer le fournisseur, puis émettre l'offre client | O17: 46309 | Q17: Montant non chiffré. 2025 : 7 383 000 (licence WithSecure)
A18: =IF(C18="","",ROW()-4) | I18: =IF(N(G18)=0,"",G18-H18) | J18: =IF(N(G18)=0,"",H18/G18) | L18: =IF(AND(ISNUMBER(F18),N(I18)>0),TODAY()-F18,"")
A19: =IF(C19="","",ROW()-4) | I19: =IF(N(G19)=0,"",G19-H19) | J19: =IF(N(G19)=0,"",H19/G19) | L19: =IF(AND(ISNUMBER(F19),N(I19)>0),TODAY()-F19,"")
A20: =IF(C20="","",ROW()-4) | I20: =IF(N(G20)=0,"",G20-H20) | J20: =IF(N(G20)=0,"",H20/G20) | L20: =IF(AND(ISNUMBER(F20),N(I20)>0),TODAY()-F20,"")
A21: =IF(C21="","",ROW()-4) | I21: =IF(N(G21)=0,"",G21-H21) | J21: =IF(N(G21)=0,"",H21/G21) | L21: =IF(AND(ISNUMBER(F21),N(I21)>0),TODAY()-F21,"")
A22: =IF(C22="","",ROW()-4) | I22: =IF(N(G22)=0,"",G22-H22) | J22: =IF(N(G22)=0,"",H22/G22) | L22: =IF(AND(ISNUMBER(F22),N(I22)>0),TODAY()-F22,"")
A23: =IF(C23="","",ROW()-4) | I23: =IF(N(G23)=0,"",G23-H23) | J23: =IF(N(G23)=0,"",H23/G23) | L23: =IF(AND(ISNUMBER(F23),N(I23)>0),TODAY()-F23,"")
A24: =IF(C24="","",ROW()-4) | I24: =IF(N(G24)=0,"",G24-H24) | J24: =IF(N(G24)=0,"",H24/G24) | L24: =IF(AND(ISNUMBER(F24),N(I24)>0),TODAY()-F24,"")
A25: =IF(C25="","",ROW()-4) | I25: =IF(N(G25)=0,"",G25-H25) | J25: =IF(N(G25)=0,"",H25/G25) | L25: =IF(AND(ISNUMBER(F25),N(I25)>0),TODAY()-F25,"")
A26: =IF(C26="","",ROW()-4) | I26: =IF(N(G26)=0,"",G26-H26) | J26: =IF(N(G26)=0,"",H26/G26) | L26: =IF(AND(ISNUMBER(F26),N(I26)>0),TODAY()-F26,"")
A27: =IF(C27="","",ROW()-4) | I27: =IF(N(G27)=0,"",G27-H27) | J27: =IF(N(G27)=0,"",H27/G27) | L27: =IF(AND(ISNUMBER(F27),N(I27)>0),TODAY()-F27,"")
A28: =IF(C28="","",ROW()-4) | I28: =IF(N(G28)=0,"",G28-H28) | J28: =IF(N(G28)=0,"",H28/G28) | L28: =IF(AND(ISNUMBER(F28),N(I28)>0),TODAY()-F28,"")
A29: =IF(C29="","",ROW()-4) | I29: =IF(N(G29)=0,"",G29-H29) | J29: =IF(N(G29)=0,"",H29/G29) | L29: =IF(AND(ISNUMBER(F29),N(I29)>0),TODAY()-F29,"")
... A32: =IF(C32="","",ROW()-4) | I32: =IF(N(G32)=0,"",G32-H32) | J32: =IF(N(G32)=0,"",H32/G32) | L32: =IF(AND(ISNUMBER(F32),N(I32)>0),TODAY()-F32,"")

Sheet CNPS
A2: Abidjan le 10 Février 2025
B7: CNPS
B8: Abidijan-Plateau
B9: 01 BP 317Abidjan 01
B10: NCC: 5000810F
B11: Tél: 27 20 25 10 00
A15: Objet: Renouvellement des licences ManageEngine
A17: DESIGNATION | B17: MONTANT
A18: ManageEngine ADAudit Plus Professional Edition - Subscription Model
A19: Annual Subscription fee for 3 Domain Controllers | B19: 1130251
A20: Annual subscription fee for 25 Windows Servers | B20: 1000475
A21: Annual Subscription Fee for 2000 Workstations | B21: 2756598
A22: Annual subscription fee for 25 File Servers | B22: 2917668
A23: Total partiel ADAudit | B23: 7804992
A24: ManageEngine Recovery Manager Plus - Subscription Model
A25: Annual subscription fee for 2000 User Objects | B25: 1974258
A26: ManageEngine ADSelfService Plus Professional Edition
A27: Annual Maintenance and Support Fee for 2000 Domain Users | B27: 1770000
A28: ManageEngine ADManager Plus Professional Edition - Perpetual Model
A29: Single Installation License fee for 1 Domain (Unrestricted Objects) with 5help desk Technicians(Total of 35 technicians) | B29: 1150500
A30: Annual Maintenance and Support fee for 1 Domain (Unrestricted Objects) with 35 help desk Technicians | B30: 4277099
A31: TOTAL LICENCES HT | B31: 16976849
A32: Service Professionnel
A33: Intégration et mises à jour (4 jours) | B33: 1770000
A34: Formation (Forfait-8 jours) | B34: 2832000
A36: TOTAL GENERAL HT | B36: 21578849
A37: TVA 18% | B37: -
A38: TOTAL TTC | B38: 21578849
A40: Arrêtée la présente Facture à la somme de: Vingt Un Millions Cinq Cent Soixante Dix Huit Mille Huit Cent Quarante Neuf FCFA
B44: La Direction

Sheet NEURONES
C2: Abidjan le 21 Août 2025
C5: A Monsieur ZIEGA Behi Claude
C6: NEURONNES TECHNOLOGIES
C7: Angré 8ème tranche Abidjan
C8: Tél:27 22 42 90 90
C9: Cél: 07 88 88 61 61
C10: bziega@neuronestech.com
A13: Objet: Facture définitive
A14: Réf | B14: Désignation | C14: P Unitaire | D14: Qtité | E14: PT HT
B15: Offre Eléments EPP+EDR Premium 1 an
A16: FCEDSU1NVXCQQ | B16: WithSecure Elements EDR and EPP for Computers Premium, Partner Managed Upgrade for 1 year (100-499), | C16: 11400 | D16: 400 | E16: 4 560 000 CFA
A17: FCPSSN1NVXDIN | B17: WithSecure Support, Premium License (competitive upgrade and new) for 1 year (500-999), International | C17: 1800 | D17: 400 | E17: 720 000 CFA
B18: En Option_WithSecure Elevate 1an
A19: FCZVSN1NVXAQQ | B19: WithSecure Elevate Package (2/1), Partner Managed for 1 year | C19: 2103000 | D19: 1 | E19: 2 103 000 CFA
C21: Montant Total HT | E21: 7 383 000 CFA
C22: TVA 18% | E22: -
C23: Acompte reçue le 22/08/2025 | E23: -3 691 500 CFA
C24: Solde Restant à payer | E24: 3 691 500 CFA
B25: wxxw
A26: Arrêtée la présente facture à la somme de:
A27: Trois Millions Six Cent Quatre Vingt Onze Mille Cinq Cent FCFA
D30: Comptabilité

Sheet CNAM
A1: FACTURE DE VENTE N° 2401345J26000000002
B3: ÉMETTEUR | C3: CLIENT
B4: Raison sociale : INFINITY AFRICA TECHNOLOGY (SAS – capital 10 000 000 FCFA) | C4: Nom : CAISSE NAT D'ASSURANCE MALADIE (CNAM)
B5: NCC : 2401345J | C5: NCC : 1504753F
B6: RCCM : CI-ABJ-03-2024-B16-00056 | C6: Régime d'imposition : RS employeur
B7: Régime d'imposition : Microentreprise | C7: Adresse : facturesfne@ipscnam.ci
B8: Centre des impôts : 807 Impôts de Cocody
B9: Références bancaires : Ecobank CI059 01056 122000640001 47 | C9: Date et heure : 27/02/2026 10:55:01
B10: Téléphone : 27 22 22 34 64 | C10: Mode de paiement : Chèque
B11: Email : technology@infinity-africa.com | C11: Type : Facture normalisée électronique (FNE)
A13: N° | B13: Désignation | C13: P.U HT (FCFA) | D13: Qté | E13: Taxes | F13: Rem. (%) | G13: Montant HT (FCFA)
A14: 1 | B14: ManageEngine ADManager Plus Professional Edition - Perpetual Licensing Model Single Installation License fee for additional 5 help desk Technicians (total of 1 domain and 10 tech) | C14: 9177101 | D14: 1 | E14: TVAD (0) | F14: 0 | G14: =C14*D14*(1-F14) -> 9177101
A15: 2 | B15: Annual Maintenance and Support fee for 1 Domain (Unrestricted Objects) with 10 help desk Technicians | C15: 4350685 | D15: 1 | E15: TVAD (0) | F15: 0 | G15: =C15*D15*(1-F15) -> 4350685
A16: 3 | B16: ManageEngine Service Desk Plus Enterprise Edition - Perpetual Model Single Installation License fee for additional 15 technicians (Total of 30 Technicians (1000 nodes)) | C16: 22761646 | D16: 1 | E16: TVAD (0) | F16: 0 | G16: =C16*D16*(1-F16) -> 22761646
A17: 4 | B17: Annual Maintenance and Support fee for 30 Technicians (1000 nodes) | C17: 13936063 | D17: 1 | E17: TVAD (0) | F17: 0 | G17: =C17*D17*(1-F17) -> 13936063
A18: 5 | B18: ManageEngine Endpoint Central UEM Edition Perpetual Licensing Model Annual Maintenance and Support Fee for ManageEngine Endpoint Central UEM Edition for 500 endpoints and Single User License | C18: 5963842 | D18: 1 | E18: TVAD (0) | F18: 0 | G18: =C18*D18*(1-F18) -> 5963842
A19: 6 | B19: Single Installation License fee for Additional 5 Users (Total of 15) | C19: 4453628 | D19: 1 | E19: TVAD (0) | F19: 0 | G19: =C19*D19*(1-F19) -> 4453628
A20: 7 | B20: Annual Maintenance and Support fee for 15 Users | C20: 3979359 | D20: 1 | E20: TVAD (0) | F20: 0 | G20: =C20*D20*(1-F20) -> 3979359
A21: 8 | B21: Annual Maintenance and Support Fee for ManageEngine Endpoint Central UEM Edition Endpoint Security for 200 Workstations | C21: 3442178 | D21: 1 | E21: TVAD (0) | F21: 0 | G21: =C21*D21*(1-F21) -> 3442178
A22: 9 | B22: Annual Maintenance and Support Fee for ManageEngine Endpoint Central UEM Edition for Multi-Language Pack License | C22: 1735190 | D22: 1 | E22: TVAD (0) | F22: 0 | G22: =C22*D22*(1-F22) -> 1735190
D24: TOTAL HT | G24: =SUM(G14:G22) -> 69799692
D25: REMISE | G25: =ROUND(G24*C32,0) -> 3489985
D26: TOTAL HT APRÈS REMISE | G26: =G24-G25 -> 66309707
D27: TVA (exonération légale – 0 %) | G27: 0
D28: TOTAL TTC | G28: =G26+G27 -> 66309707
D29: AUTRES TAXES | G29: 0
D30: TOTAL À PAYER | G30: =G28+G29 -> 66309707
B32: Taux de remise globale appliqué | C32: 0.05
A34: Résumé : TVA exonération légale – Pas de TVA sur HT (taux 0 %, code D). Activités : Conseil, Stratégie, Ingénierie informatique, FinTech, Cybersécurité, Blockchain, Développement Web & Mobile, IA.
A35: Source : facture PDF IAT n° 2401345J26000000002 du 27/02/2026 (chiffres en bleu = saisies de la facture).

Sheet FER
A1: FACTURE DE VENTE N° 2401345J26000000003
A3: ÉMETTEUR | C3: CLIENT
A4: Raison sociale : INFINITY AFRICA TECHNOLOGY (SAS – capital 10 000 000 FCFA) | C4: Nom : FONDS D'ENTRETIEN ROUTIER (FER)
A5: NCC : 2401345J | C5: NCC : 0304966P
A6: RCCM : CI-ABJ-03-2024-B16-00056 | C6: Régime d'imposition : RNI
A7: Régime d'imposition : Microentreprise | C7: Adresse : atta.eblin@fer-ci.org
A8: Centre des impôts : 807 Impôts de Cocody
A9: Références bancaires : Ecobank CI059 01056 122000640001 47 | C9: Date et heure : 24/06/2026 09:00:26
A10: Téléphone : 27 22 22 34 64 | C10: Mode de paiement : Chèque
A11: Email : technology@infinity-africa.com | C11: Type : Facture normalisée électronique (FNE)
A13: Réf | B13: Désignation | C13: P.U HT (FCFA) | D13: Qté | E13: Taxes | F13: Rem. (%) | G13: Montant HT (FCFA)
B14: RENOUVELLEMENT DES LICENCES MANAGE ENGINE ISM, ITOM ET PAM POUR LE COMPTE DU FER SIEGE | C14: 28766400 | D14: 1 | E14: TVAD (0) | F14: 0 | G14: 28766400
D16: TOTAL HT | G16: 28766400
D17: TVA (exonération légale – 0 %) | G17: 0
D18: TOTAL TTC | G18: 28766400
D19: AUTRES TAXES | G19: 0
D20: TOTAL À PAYER | G20: 28766400
A22: Résumé : TVA exonération légale – Pas de TVA sur HT (taux 0 %, code D). Activités : Conseil, Stratégie, Ingénierie informatique, FinTech, Cybersécurité, Blockchain, Développement Web & Mobile, IA.
A23: Source : facture PDF IAT n° 2401345J26000000003 du 24/06/2026 (chiffres en bleu = saisies de la facture).
C26: La Comptabilité

Sheet NSIA VIE
A1: FACTURE DE VENTE N° 2401345J26000000008
A3: ÉMETTEUR | C3: CLIENT
A4: Raison sociale : INFINITY AFRICA TECHNOLOGY (SAS – capital 10 000 000 FCFA) | C4: Nom : NSIA VIE ASSURANCES
A5: NCC : 2401345J | C5: NCC : 8805053A
A6: RCCM : CI-ABJ-03-2024-B16-00056 | C6: Régime d'imposition : RNI
A7: Régime d'imposition : Microentreprise | C7: Adresse : silvere.kacou@nsiaassurances.com
A8: Centre des impôts : 807 Impôts de Cocody
A9: Références bancaires : Ecobank CI059 01056 122000640001 47 | C9: Date et heure : 18/09/2026 16:56:08
A10: Téléphone : 27 22 22 34 64 | C10: Mode de paiement : Chèque
A11: Email : technology@infinity-africa.com | C11: Type : Facture normalisée électronique (FNE)
A13: Réf | B13: Désignation | C13: P.U HT (FCFA) | D13: Qté | E13: Taxes | F13: Rem. (%) | G13: Montant HT (FCFA)
A14: ManageEngine ServiceDesk Plus Multi-Language Professional Edition - Subscription Model | B14: Annual Subscription fee for 4 Technicians (250 IT Assets) (Start 01/10/26 End 01/10/27) | C14: 1610068 | D14: 1 | E14: TVAD (0) | F14: 0 | G14: 1610068
D16: TOTAL HT | G16: 1610068
D17: TVA (exonération légale – 0 %) | G17: 0
D18: TOTAL TTC | G18: 1610068
D19: AUTRES TAXES | G19: 0
D20: TOTAL À PAYER | G20: 1610068
A22: Résumé : TVA exonération légale – Pas de TVA sur HT (taux 0 %, code D). Activités : Conseil, Stratégie, Ingénierie informatique, FinTech, Cybersécurité, Blockchain, Développement Web & Mobile, IA.
A23: Source : facture PDF IAT n° 2401345J26000000008 du 18/09/2026 (chiffres en bleu = saisies de la facture).
C27: La Comptabilité

Sheet Listes
A1: Étapes du pipeline | C1: Statuts de renouvellement | E1: Ajoutez ou renommez les étapes ici : la liste déroulante de l'onglet Pipeline se met à jour.
A2: Prospection | C2: Non démarré
A3: Attente cotation fournisseur | C3: Attente cotation fournisseur
A4: Offre envoyée - attente client | C4: Offre envoyée
A5: Facturé - non encaissé | C5: Accord client
A6: Encaissement partiel | C6: Renouvelé
A7: Soldé | C7: Perdu
A8: Perdu
