Workbook

Sheet Synthèse
B2: IAT — Synthèse du pipeline
B3: Vue consolidée | Montants en FCFA | Tous les chiffres sont calculés depuis les autres onglets
B4: Mise à jour : 15/10/2026 (facturation : point comptable du 13/10/2026) · Cliquer sur un nom d’onglet pour ouvrir le détail
B6: INDICATEURS CLÉS DU PIPELINE
B7: Nombre d’affaires dans le pipeline | C7: =COUNTA('Pipeline global'!$D$9:$D$50) -> 37
B8: Montant total du pipeline | C8: =SUM('Pipeline global'!$L$9:$L$50) -> 453330882
B9: Montant pondéré (Montant × Closing) | C9: =SUM('Pipeline global'!$M$9:$M$50) -> 171217175
B10: Commission totale | C10: =SUM('Pipeline global'!$N$9:$N$50) -> 39000000
B11: % Rentabilité (Commission / Montant) | C11: =IFERROR(C10/C8,"") -> 0.086029877
B12: Montant gagné (M6) | C12: =SUMIFS('Pipeline global'!$L$9:$L$50,'Pipeline global'!$J$9:$J$50,"M6 – Gagné") -> 114686175
B13: Offres remises ou en signature (M4 + M5) | C13: =SUMIFS('Pipeline global'!$L$9:$L$50,'Pipeline global'!$J$9:$J$50,"M4 – Offre remise")+SUMIFS('Pipeline global'!$L$9:$L$50,'Pipeline global'!$J$9:$J$50,"M5 – Négociation / signature") -> 186335000
B14: Affaires encore à qualifier (M0) | C14: =COUNTIFS('Pipeline global'!$J$9:$J$50,"M0 – À qualifier") -> 18
B15: Affaires prioritaires (P1) | C15: =COUNTIFS('Pipeline global'!$P$9:$P$50,"P1") -> 10
B16: Actions du plan non terminées | C16: =COUNTIFS('Plan d’actions'!$C$9:$C$51,"<>",'Plan d’actions'!$H$9:$H$51,"<>Fait") -> 38
B18: FACTURATION, ENCAISSEMENTS ET RENOUVELLEMENTS (point comptable du 13/10/2026)
B19: Montant total facturé 2024-2026 | C19: =CNAM!G45+CNPS!G45+FER!G38+NSIA!G48+'Orange Business'!G37+NEURONES!G39 -> 299743360
B20: Total encaissé | C20: =CNAM!L45+CNPS!L45+FER!L38+NSIA!L48+'Orange Business'!L37+NEURONES!L39 -> 295243360
B21: Reste à encaisser | C21: =CNAM!M45+CNPS!M45+FER!M38+NSIA!M48+'Orange Business'!M37+NEURONES!M39 -> 4500000
B22: Taux d’encaissement | C22: =IFERROR(C20/C19,"") -> 0.98498716
B23: Montant récurrent annuel (base dernière facturation) | C23: =Renouvellements!F21 -> 143648024
B24: Renouvellements échus non renouvelés (montant) | C24: =SUMPRODUCT((LEFT(Renouvellements!$L$9:$L$20,4)="Échu")*Renouvellements!$F$9:$F$20) -> 28961849
B25: Nombre de contrats échus | C25: =SUMPRODUCT(--(LEFT(Renouvellements!$L$9:$L$20,4)="Échu")) -> 2
B26: Contrats à relancer sous 90 jours | C26: =SUMPRODUCT(--(LEFT(Renouvellements!$L$9:$L$20,10)="À relancer")) -> 0
B27: → Renouvellements
B29: CONTACTS (base clients CI + dirigeants identifiés)
B30: Contacts au total (onglet Contacts) | C30: =COUNTA(Contacts!$C$9:$C$428) -> 420
B31: Contacts rattachés au pipeline, aux clients ou aux cibles | C31: =SUMPRODUCT(--(Contacts!$J$9:$J$428<>"")) -> 210
B32: Contacts « Direction SI / digital » | C32: =COUNTIF(Contacts!$G$9:$G$428,"Direction SI / digital") -> 51
B33: Coordonnées à vérifier (numéros à 8 chiffres) | C33: =COUNTIF(Contacts!$K$9:$K$428,"Coordonnées à vérifier") -> 122
B34: RDV obtenus | C34: =COUNTIF(Contacts!$K$9:$K$428,"RDV obtenu") -> 0
B35: Dirigeants identifiés (recherche du 15/10/2026) | C35: =COUNTIF(Contacts!$N$9:$N$428,"Recherche dirigeants (web + LinkedIn, 15/10/2026)") -> 18
B36: → Contacts
B38: PAR TYPE DE COMPTE
B39: Type de compte | C39: Nb d’affaires | D39: Montant | E39: Montant pondéré | F39: Commission | G39: % Rentabilité | H39: Détail
B40: Client existant | C40: =COUNTIFS('Pipeline global'!$C$9:$C$50,B40) -> 12 | D40: =SUMIFS('Pipeline global'!$L$9:$L$50,'Pipeline global'!$C$9:$C$50,B40) -> 345330882 | E40: =SUMIFS('Pipeline global'!$M$9:$M$50,'Pipeline global'!$C$9:$C$50,B40) -> 171217175 | F40: =SUMIFS('Pipeline global'!$N$9:$N$50,'Pipeline global'!$C$9:$C$50,B40) -> 39000000 | G40: =IFERROR(F40/D40,"") -> 0.11293516 | H40: → Pipeline global
B41: Prospect | C41: =COUNTIFS('Pipeline global'!$C$9:$C$50,B41) -> 23 | D41: =SUMIFS('Pipeline global'!$L$9:$L$50,'Pipeline global'!$C$9:$C$50,B41) -> 108000000 | E41: =SUMIFS('Pipeline global'!$M$9:$M$50,'Pipeline global'!$C$9:$C$50,B41) -> 0 | F41: =SUMIFS('Pipeline global'!$N$9:$N$50,'Pipeline global'!$C$9:$C$50,B41) -> 0 | G41: =IFERROR(F41/D41,"") -> 0 | H41: → Solutions & prospects
B42: Appel d’offres | C42: =COUNTIFS('Pipeline global'!$C$9:$C$50,B42) -> 1 | D42: =SUMIFS('Pipeline global'!$L$9:$L$50,'Pipeline global'!$C$9:$C$50,B42) -> 0 | E42: =SUMIFS('Pipeline global'!$M$9:$M$50,'Pipeline global'!$C$9:$C$50,B42) -> 0 | F42: =SUMIFS('Pipeline global'!$N$9:$N$50,'Pipeline global'!$C$9:$C$50,B42) -> 0 | G42: =IFERROR(F42/D42,"") | H42: → Appels d’offres
B43: Partenaire / apporteur | C43: =COUNTIFS('Pipeline global'!$C$9:$C$50,B43) -> 1 | D43: =SUMIFS('Pipeline global'!$L$9:$L$50,'Pipeline global'!$C$9:$C$50,B43) -> 0 | E43: =SUMIFS('Pipeline global'!$M$9:$M$50,'Pipeline global'!$C$9:$C$50,B43) -> 0 | F43: =SUMIFS('Pipeline global'!$N$9:$N$50,'Pipeline global'!$C$9:$C$50,B43) -> 0 | G43: =IFERROR(F43/D43,"") | H43: → NEURONES
B44: TOTAL | C44: =SUM(C40:C43) -> 37 | D44: =SUM(D40:D43) -> 453330882 | E44: =SUM(E40:E43) -> 171217175 | F44: =SUM(F40:F43) -> 39000000 | G44: =IFERROR(F44/D44,"") -> 0.086029877
B46: COMPTES EXISTANTS — HISTORIQUE FACTURÉ (détail dans chaque onglet client)
B47: Client | C47: État de santé | D47: Facturé 2024 | E47: Facturé 2025 | F47: Facturé 2026 | G47: Solde à encaisser | H47: Offres en cours | I47: Fiche
B48: CNAM | C48: =IF(CNAM!C14="","À renseigner",CNAM!C14) -> Bon | D48: =SUMIFS(CNAM!$G$38:$G$44,CNAM!$E$38:$E$44,2024) -> 69799690 | E48: =SUMIFS(CNAM!$G$38:$G$44,CNAM!$E$38:$E$44,2025) -> 84309706 | F48: =SUMIFS(CNAM!$G$38:$G$44,CNAM!$E$38:$E$44,2026) -> 84309707 | G48: =CNAM!M45 -> 4500000 | H48: =CNAM!G54 -> 66309707 | I48: → CNAM
B49: CNPS | C49: =IF(CNPS!C15="","À renseigner",CNPS!C15) -> À renseigner | D49: =SUMIFS(CNPS!$G$41:$G$44,CNPS!$E$41:$E$44,2024) -> 0 | E49: =SUMIFS(CNPS!$G$41:$G$44,CNPS!$E$41:$E$44,2025) -> 21578849 | F49: =SUMIFS(CNPS!$G$41:$G$44,CNPS!$E$41:$E$44,2026) -> 0 | G49: =CNPS!M45 -> 0 | H49: =CNPS!G54 -> 81700000 | I49: → CNPS
B50: FER | C50: =IF(FER!C14="","À renseigner",FER!C14) -> À renseigner | D50: =SUMIFS(FER!$G$34:$G$37,FER!$E$34:$E$37,2024) -> 0 | E50: =SUMIFS(FER!$G$34:$G$37,FER!$E$34:$E$37,2025) -> 0 | F50: =SUMIFS(FER!$G$34:$G$37,FER!$E$34:$E$37,2026) -> 28766400 | G50: =FER!M38 -> 0 | H50: =FER!G47 -> 4500000 | I50: → FER
B51: NSIA | C51: =IF(NSIA!C15="","À renseigner",NSIA!C15) -> À renseigner | D51: =SUMIFS(NSIA!$G$43:$G$47,NSIA!$E$43:$E$47,2024) -> 1003000 | E51: =SUMIFS(NSIA!$G$43:$G$47,NSIA!$E$43:$E$47,2025) -> 982940 | F51: =SUMIFS(NSIA!$G$43:$G$47,NSIA!$E$43:$E$47,2026) -> 1610068 | G51: =NSIA!M48 -> 0 | H51: =NSIA!G57 -> 0 | I51: → NSIA
B52: Orange Business | C52: =IF('Orange Business'!C14="","À renseigner",'Orange Business'!C14) -> À surveiller | D52: =SUMIFS('Orange Business'!$G$33:$G$36,'Orange Business'!$E$33:$E$36,2024) -> 0 | E52: =SUMIFS('Orange Business'!$G$33:$G$36,'Orange Business'!$E$33:$E$36,2025) -> 0 | F52: =SUMIFS('Orange Business'!$G$33:$G$36,'Orange Business'!$E$33:$E$36,2026) -> 0 | G52: ='Orange Business'!M37 -> 0 | H52: ='Orange Business'!G46 -> 64135000 | I52: → Orange Business
B53: NEURONES | C53: =IF(NEURONES!C14="","À renseigner",NEURONES!C14) -> À renseigner | D53: =SUMIFS(NEURONES!$G$35:$G$38,NEURONES!$E$35:$E$38,2024) -> 0 | E53: =SUMIFS(NEURONES!$G$35:$G$38,NEURONES!$E$35:$E$38,2025) -> 7383000 | F53: =SUMIFS(NEURONES!$G$35:$G$38,NEURONES!$E$35:$E$38,2026) -> 0 | G53: =NEURONES!M39 -> 0 | H53: =NEURONES!G48 -> 0 | I53: → NEURONES
B54: TOTAL | D54: =SUM(D48:D53) -> 70802690 | E54: =SUM(E48:E53) -> 114254495 | F54: =SUM(F48:F53) -> 114686175 | G54: =SUM(G48:G53) -> 4500000 | H54: =SUM(H48:H53) -> 216644707
B56: PAR ÉTAPE
B57: Étape | C57: Nb d’affaires | D57: Montant | E57: Montant pondéré
B58: M0 – À qualifier | C58: =COUNTIFS('Pipeline global'!$J$9:$J$50,B58) -> 18 | D58: =SUMIFS('Pipeline global'!$L$9:$L$50,'Pipeline global'!$J$9:$J$50,B58) -> 0 | E58: =SUMIFS('Pipeline global'!$M$9:$M$50,'Pipeline global'!$J$9:$J$50,B58) -> 0
B59: M1 – Besoin identifié | C59: =COUNTIFS('Pipeline global'!$J$9:$J$50,B59) -> 4 | D59: =SUMIFS('Pipeline global'!$L$9:$L$50,'Pipeline global'!$J$9:$J$50,B59) -> 0 | E59: =SUMIFS('Pipeline global'!$M$9:$M$50,'Pipeline global'!$J$9:$J$50,B59) -> 0
B60: M2 – Cadrage / découverte | C60: =COUNTIFS('Pipeline global'!$J$9:$J$50,B60) -> 0 | D60: =SUMIFS('Pipeline global'!$L$9:$L$50,'Pipeline global'!$J$9:$J$50,B60) -> 0 | E60: =SUMIFS('Pipeline global'!$M$9:$M$50,'Pipeline global'!$J$9:$J$50,B60) -> 0
B61: M3 – Offre en préparation | C61: =COUNTIFS('Pipeline global'!$J$9:$J$50,B61) -> 3 | D61: =SUMIFS('Pipeline global'!$L$9:$L$50,'Pipeline global'!$J$9:$J$50,B61) -> 138309707 | E61: =SUMIFS('Pipeline global'!$M$9:$M$50,'Pipeline global'!$J$9:$J$50,B61) -> 0
B62: M4 – Offre remise | C62: =COUNTIFS('Pipeline global'!$J$9:$J$50,B62) -> 1 | D62: =SUMIFS('Pipeline global'!$L$9:$L$50,'Pipeline global'!$J$9:$J$50,B62) -> 59000000 | E62: =SUMIFS('Pipeline global'!$M$9:$M$50,'Pipeline global'!$J$9:$J$50,B62) -> 0
B63: M5 – Négociation / signature | C63: =COUNTIFS('Pipeline global'!$J$9:$J$50,B63) -> 5 | D63: =SUMIFS('Pipeline global'!$L$9:$L$50,'Pipeline global'!$J$9:$J$50,B63) -> 127335000 | E63: =SUMIFS('Pipeline global'!$M$9:$M$50,'Pipeline global'!$J$9:$J$50,B63) -> 42531000
B64: M6 – Gagné | C64: =COUNTIFS('Pipeline global'!$J$9:$J$50,B64) -> 5 | D64: =SUMIFS('Pipeline global'!$L$9:$L$50,'Pipeline global'!$J$9:$J$50,B64) -> 114686175 | E64: =SUMIFS('Pipeline global'!$M$9:$M$50,'Pipeline global'!$J$9:$J$50,B64) -> 114686175
B65: Perdu | C65: =COUNTIFS('Pipeline global'!$J$9:$J$50,B65) -> 0 | D65: =SUMIFS('Pipeline global'!$L$9:$L$50,'Pipeline global'!$J$9:$J$50,B65) -> 0 | E65: =SUMIFS('Pipeline global'!$M$9:$M$50,'Pipeline global'!$J$9:$J$50,B65) -> 0
B66: Clôturé / en cessation | C66: =COUNTIFS('Pipeline global'!$J$9:$J$50,B66) -> 1 | D66: =SUMIFS('Pipeline global'!$L$9:$L$50,'Pipeline global'!$J$9:$J$50,B66) -> 14000000 | E66: =SUMIFS('Pipeline global'!$M$9:$M$50,'Pipeline global'!$J$9:$J$50,B66) -> 14000000
B67: TOTAL | C67: =SUM(C58:C66) -> 37 | D67: =SUM(D58:D66) -> 453330882 | E67: =SUM(E58:E66) -> 171217175
B69: PAR RESPONSABLE (y compris affaires où IAT n’est pas lead)
B70: Lead | C70: Nb d’affaires | D70: Montant | E70: Montant pondéré | F70: Affaires P1
B71: Commercial IAT | C71: =COUNTIFS('Pipeline global'!$H$9:$H$50,B71) -> 23 | D71: =SUMIFS('Pipeline global'!$L$9:$L$50,'Pipeline global'!$H$9:$H$50,B71) -> 267195882 | E71: =SUMIFS('Pipeline global'!$M$9:$M$50,'Pipeline global'!$H$9:$H$50,B71) -> 118736175 | F71: =COUNTIFS('Pipeline global'!$H$9:$H$50,B71,'Pipeline global'!$P$9:$P$50,"P1") -> 5
B72: Maoula | C72: =COUNTIFS('Pipeline global'!$H$9:$H$50,B72) -> 1 | D72: =SUMIFS('Pipeline global'!$L$9:$L$50,'Pipeline global'!$H$9:$H$50,B72) -> 0 | E72: =SUMIFS('Pipeline global'!$M$9:$M$50,'Pipeline global'!$H$9:$H$50,B72) -> 0 | F72: =COUNTIFS('Pipeline global'!$H$9:$H$50,B72,'Pipeline global'!$P$9:$P$50,"P1") -> 0
B73: Direction générale | C73: =COUNTIFS('Pipeline global'!$H$9:$H$50,B73) -> 2 | D73: =SUMIFS('Pipeline global'!$L$9:$L$50,'Pipeline global'!$H$9:$H$50,B73) -> 0 | E73: =SUMIFS('Pipeline global'!$M$9:$M$50,'Pipeline global'!$H$9:$H$50,B73) -> 0 | F73: =COUNTIFS('Pipeline global'!$H$9:$H$50,B73,'Pipeline global'!$P$9:$P$50,"P1") -> 0
B74: À confirmer | C74: =COUNTIFS('Pipeline global'!$H$9:$H$50,B74) -> 11 | D74: =SUMIFS('Pipeline global'!$L$9:$L$50,'Pipeline global'!$H$9:$H$50,B74) -> 186135000 | E74: =SUMIFS('Pipeline global'!$M$9:$M$50,'Pipeline global'!$H$9:$H$50,B74) -> 52481000 | F74: =COUNTIFS('Pipeline global'!$H$9:$H$50,B74,'Pipeline global'!$P$9:$P$50,"P1") -> 5
B75: TOTAL | C75: =SUM(C71:C74) -> 37 | D75: =SUM(D71:D74) -> 453330882 | E75: =SUM(E71:E74) -> 171217175 | F75: =SUM(F71:F74) -> 10
B77: ONGLETS DU CLASSEUR
B78: → Pipeline global | C78: Toutes les affaires (une ligne par affaire), avec type de compte, lead, étape, priorité
B79: → Renouvellements | C79: Calendrier des échéances et des relances J-90 / J-30 des contrats récurrents
B80: → CNAM | C80: Fiche compte : vendu, offres en cours, stratégie
B81: → CNPS | C81: Fiche compte
B82: → FER | C82: Fiche compte
B83: → Orange Business | C83: Fiche compte + tous les deals transmis (gagnés / soumis / perdus)
B84: → NSIA | C84: Fiche compte
B85: → NEURONES | C85: Fiche partenaire revendeur
B86: → Appels d’offres | C86: Suivi des AO et de la veille
B87: → Solutions & prospects | C87: Stratégie par produit + prospects par solution (Credolab, Wari+, ManageEngine…)
B88: → Plan d’actions | C88: Check-list des actions décidées le 13/10/2026
B89: → Contacts | C89: Base clients CI : contacts profilés et rattachés au pipeline

Sheet Pipeline global
B2: IAT — Pipeline global
B3: Groupe IAG — Suivi AEC | Montants et commissions en FCFA | Toutes les affaires, y compris celles dont IAT n’est pas lead
B4: % Rentabilité = Commission / Montant · Montant pondéré = Montant × Closing · Jaune pâle = à compléter · Vert = repris d’une fiche client
B5: ← Retour à la synthèse
B7: AFFAIRES IAT
B8: N° | C8: Type de compte | D8: Entreprise / Projet | E8: Nature de l’affaire | F8: Solution / partenaire | G8: Origine (domaine) | H8: Lead | I8: Récurrent / ponctuel | J8: Étape | K8: Closing | L8: Montant (FCFA) | M8: Montant pondéré | N8: Commission (FCFA) | O8: % Rentabilité | P8: Priorité | Q8: Prochaine étape | R8: Échéance | S8: Commentaires | T8: Service IAT proposé | U8: Fiche détaillée | V8: Contact clé (base clients CI)
B9: 1 | C9: Client existant | D9: MD Participations | E9: Mise en place d'un ERP Groupe | F9: Odoo Community — périmètre et état de mobilisation à confirmer | G9: Approche directe (à valider) | H9: À confirmer | J9: Clôturé / en cessation | K9: 1 | L9: 14000000 | M9: =IF(OR(L9="",K9=""),"",L9*K9) -> 14000000 | O9: =IF(OR(L9="",N9=""),"",IFERROR(N9/L9,"")) | Q9: préavis en cours - établir contradictoirement la réalité de la mobilisation | S9: Affaire en cessation - cloture acté | T9: Intégration ERP et transformation des processus
B10: 2 | C10: Client existant | D10: Orange Burkina (via Orange Business) | E10: Migration Microsoft Exchange | F10: Microsoft Exchange / Microsoft 365 — via OC²S | G10: Consultation via partenaire (OC²S) | H10: À confirmer | I10: Ponctuel | J10: M5 – Négociation / signature | K10: =IF('Orange Business'!H42="","",'Orange Business'!H42) -> 0.6 | L10: =IF('Orange Business'!G42="","",'Orange Business'!G42) -> 41135000 | M10: =IF(OR(L10="",K10=""),"",L10*K10) -> 24681000 | O10: =IF(OR(L10="",N10=""),"",IFERROR(N10/L10,"")) | P10: P1 | Q10: Fixer une date de décision avec Judicaël KOUTOU (échéance actuellement non renseignée) · Identifier le décideur final côté Orange Burkina · Préparer une position de repli tarifaire avant concession | S10: Négociation en cours | M5/M6 - Négociation post-remise d'offre (à valider) | Offre remise depuis plus de 2 mois : nécessite une relance structurée. | T10: Migration de messagerie et environnement collaboratif | U10: → Orange Business
B11: 3 | C11: Client existant | D11: Orange Liberia (via Orange Business) | E11: Audit des assets SAM (Software Asset Management) | F11: Outils SAM à confirmer — expertise / mobilisation via OC²S | G11: Consultation via partenaire (OC²S) | H11: À confirmer | I11: Ponctuel | J11: M5 – Négociation / signature | K11: =IF('Orange Business'!H43="","",'Orange Business'!H43) -> 0.6 | L11: =IF('Orange Business'!G43="","",'Orange Business'!G43) -> 23000000 | M11: =IF(OR(L11="",K11=""),"",L11*K11) -> 13800000 | O11: =IF(OR(L11="",N11=""),"",IFERROR(N11/L11,"")) | P11: P1 | Q11: Fixer une date de décision · Clarifier les contraintes locales (Liberia : logistique, fiscalité, langue de restitution) · Sécuriser la disponibilité de l'auditeur SAM sur la fenêtre d'intervention | S11: Négociation en cours | M5/M6 - Négociation post-remise d'offre (à valider) | Affaire jumelle du dossier Orange Burkina : à traiter dans une même séquence de relance OC²S. | T11: Audit Software Asset Management (SAM) | U11: → Orange Business
B12: 4 | C12: Prospect | D12: KAYDAN | E12: À COMPLÉTER — intitulé de l'affaire à préciser | F12: Odoo CRM / modules de gestion — à valider après découverte | G12: A Valider | H12: Commercial IAT | J12: M0 – À qualifier | M12: =IF(OR(L12="",K12=""),"",L12*K12) | O12: =IF(OR(L12="",N12=""),"",IFERROR(N12/L12,"")) | P12: P2 | S12: Non qualifié — seul le contact est renseigné | M0 - À qualifier | Décision attendue : qualifier ou sortir du portefeuille. | T12: CRM, gestion commerciale et digitalisation immobilière — à qualifier
B13: 5 | C13: Client existant | D13: CNAM | E13: Renouvellement licences ManageEngine 2026 | F13: ManageEngine — modules et licences exacts à confirmer | G13: ManageEngine | H13: Commercial IAT | I13: Récurrent | J13: M6 – Gagné | K13: 1 | L13: =IF(CNAM!G41="","",CNAM!G41) -> 66309707 | M13: =IF(OR(L13="",K13=""),"",L13*K13) -> 66309707 | N13: =IF(CNAM!I41="","",CNAM!I41) -> 33000000 | O13: =IF(OR(L13="",N13=""),"",IFERROR(N13/L13,"")) -> 0.49766469 | P13: P3 | Q13: — | S13: Facturé le 27/02/2026 et soldé (compta). Historique : 69,8 M (2024) · 66,3 M (2025) · 66,3 M (2026). | T13: Support et gestion des services IT / licences | U13: → CNAM | V13: Direction : DG : Karim Bamba (confirmé) · DGA : Ahmed Tidiane Diomandé (confirmé)
B14: 6 | C14: Client existant | D14: CNAM | E14: Contrat de maintenance ManageEngine 2026 | F14: ManageEngine — modules et licences exacts à confirmer | G14: ManageEngine | H14: Commercial IAT | I14: Récurrent | J14: M6 – Gagné | K14: 1 | L14: =IF(CNAM!G42="","",CNAM!G42) -> 18000000 | M14: =IF(OR(L14="",K14=""),"",L14*K14) -> 18000000 | N14: =IF(CNAM!I42="","",CNAM!I42) -> 6000000 | O14: =IF(OR(L14="",N14=""),"",IFERROR(N14/L14,"")) -> 0.33333333 | P14: P2 | Q14: Relancer la direction financière CNAM pour le solde (facture jointe) | R14: 46357 | S14: Facturation trimestrielle de 4,5 M : 13,5 M encaissés, solde 4,5 M (compta). | T14: Support et gestion des services IT / licences | U14: → CNAM | V14: Direction : DG : Karim Bamba (confirmé) · DGA : Ahmed Tidiane Diomandé (confirmé)
B15: 7 | C15: Client existant | D15: CNAM | E15: Renouvellement licences ManageEngine 2027 | F15: ManageEngine — modules et licences exacts à confirmer | G15: ManageEngine | H15: Commercial IAT | I15: Récurrent | J15: M3 – Offre en préparation | L15: =IF(CNAM!G50="","",CNAM!G50) -> 66309707 | M15: =IF(OR(L15="",K15=""),"",L15*K15) | O15: =IF(OR(L15="",N15=""),"",IFERROR(N15/L15,"")) | P15: P2 | Q15: Préparer l’offre de renouvellement avant la relance J-90 | R15: 46355 | S15: Échéance 27/02/2027 · relance J-90 le 29/11/2026. Montant de base = dernière facturation. | T15: Support et gestion des services IT / licences | U15: → CNAM | V15: Direction : DG : Karim Bamba (confirmé) · DGA : Ahmed Tidiane Diomandé (confirmé)
B16: 8 | C16: Client existant | D16: CNPS | E16: Renouvellement licences ManageEngine 2026 | F16: ManageEngine — modules et licences exacts à confirmer | G16: ManageEngine | H16: Commercial IAT | I16: Récurrent | J16: M5 – Négociation / signature | L16: =IF(CNPS!G50="","",CNPS!G50) -> 22700000 | M16: =IF(OR(L16="",K16=""),"",L16*K16) | O16: =IF(OR(L16="",N16=""),"",IFERROR(N16/L16,"")) | P16: P1 | Q16: Relance commerciale + rendez-vous avec la DSI CNPS pour obtenir la décision | R16: 46318 | S16: Échu depuis le 10/02/2026 ; offre envoyée, attente client (compta). 22,7 M = montant évoqué en réunion, non chiffré dans le point comptable. Base 2025 : 21 578 849. | T16: Support et gestion des services IT / licences | U16: → CNPS | V16: Direction : DG : Denis Charles Kouassi (confirmé) · DGA chargé de l’exploitation : Idriss Traoré (à confirmer) · DSI : Thierry Bahi (à confirmer) Gballet BEUGRE — Directeur du Système d'Information (DSI) · Cel:(225)08305255 · g.beugre@cnps.ci (+7 autres dans l’onglet Contacts)
B17: 9 | C17: Client existant | D17: CNPS | E17: Offre ≈ 59 M envoyée — non encore validée | F17: À préciser | G17: Client existant | H17: Commercial IAT | J17: M4 – Offre remise | L17: =IF(CNPS!G51="","",CNPS!G51) -> 59000000 | M17: =IF(OR(L17="",K17=""),"",L17*K17) | O17: =IF(OR(L17="",N17=""),"",IFERROR(N17/L17,"")) | P17: P1 | Q17: Récupérer l’offre · fixer une date de décision | S17: Offre absente du point transmis par Désiré (réunion du 13/10). Objet et date d’envoi à compléter. Rattachement à la CNPS à confirmer (transcription « CNTS / CNT »). | U17: → CNPS | V17: Direction : DG : Denis Charles Kouassi (confirmé) · DGA chargé de l’exploitation : Idriss Traoré (à confirmer) · DSI : Thierry Bahi (à confirmer) Gballet BEUGRE — Directeur du Système d'Information (DSI) · Cel:(225)08305255 · g.beugre@cnps.ci (+7 autres dans l’onglet Contacts)
B18: 10 | C18: Client existant | D18: FER (Fond d'entretien Routier) | E18: Licences ManageEngine 2026 | F18: ManageEngine — produit et périmètre à confirmer | G18: ManageEngine | H18: Commercial IAT | I18: Récurrent | J18: M6 – Gagné | K18: 1 | L18: =IF(FER!G34="","",FER!G34) -> 28766400 | M18: =IF(OR(L18="",K18=""),"",L18*K18) -> 28766400 | O18: =IF(OR(L18="",N18=""),"",IFERROR(N18/L18,"")) | P18: P3 | Q18: Point de satisfaction avant la relance J-90 (26/03/2027) | S18: Nouveau client 2026 : facturé 28 766 400 le 24/06/2026, soldé (compta). Renouvellement le 24/06/2027. | T18: Licences et gestion des services IT | U18: → FER | V18: Direction : Directrice générale : Annick Tohé Lasmel (confirmé) · Directeur financier et comptable : Moussa Diarra (à confirmer)
B19: 11 | C19: Client existant | D19: FER (Fond d'entretien Routier) | E19: Sécurisation boîtes mails | F19: ManageEngine | G19: ManageEngine | H19: Commercial IAT | I19: Ponctuel | J19: M5 – Négociation / signature | K19: =IF(FER!H43="","",FER!H43) -> 0.9 | L19: =IF(FER!G43="","",FER!G43) -> 4500000 | M19: =IF(OR(L19="",K19=""),"",L19*K19) -> 4050000 | N19: 0 | O19: =IF(OR(L19="",N19=""),"",IFERROR(N19/L19,"")) -> 0 | P19: P1 | Q19: Vérifier avec la compta · planifier la formation prévue | S19: Ligne du pipeline d’origine (coût des ventes 1 065 000) non retrouvée dans la facturation transmise par la compta : vérifier si elle est incluse dans les 28,8 M ou reste à facturer. | T19: Licences et gestion des services IT | U19: → FER | V19: Direction : Directrice générale : Annick Tohé Lasmel (confirmé) · Directeur financier et comptable : Moussa Diarra (à confirmer)
B20: 12 | C20: Client existant | D20: NSIA (Assurances / Assurances Vie) | E20: Renouvellement licences ManageEngine 2026 | F20: ManageEngine | G20: Client existant | H20: Commercial IAT | I20: Récurrent | J20: M6 – Gagné | K20: 1 | L20: =IF(NSIA!G45="","",NSIA!G45) -> 1610068 | M20: =IF(OR(L20="",K20=""),"",L20*K20) -> 1610068 | O20: =IF(OR(L20="",N20=""),"",IFERROR(N20/L20,"")) | P20: P3 | Q20: Prochaine échéance 18/09/2027 | S20: Client depuis 2024 (compta) : 1,0 M (2024) · 1,0 M (2025) · 1,6 M (2026). Renouvelle chaque année en septembre. | T20: Support et gestion des services IT / licences | U20: → NSIA | V20: Direction : DG : Sonia Nadège Seka (à confirmer) · DGA : Gérard Gilles Akou (confirmé) · Directeur du réseau des particuliers : Jacques Avenie (à confirmer) NSIA PARTICIPATION : Gabriel COMOE-EDANOU — Directeur Des Opérations et de la Technologies Groupe · 0749595963 · gabriel.comoe-edanou@groupensia.com (+2 autres dans l’onglet Contacts) NSIA Banque : AMANGOUA Alexandre · 07 88 86 46 22 · alexandre.armangouah@groupensia.com (+3 autres dans l’onglet Contacts)
B21: 13 | C21: Partenaire / apporteur | D21: NEURONES | E21: Renouvellement licence WithSecure 2026 | F21: WithSecure | G21: WithSecure | H21: Commercial IAT | I21: Récurrent | J21: M3 – Offre en préparation | L21: =IF(NEURONES!G44="","",NEURONES!G44) | M21: =IF(OR(L21="",K21=""),"",L21*K21) | O21: =IF(OR(L21="",N21=""),"",IFERROR(N21/L21,"")) | P21: P1 | Q21: Relancer le fournisseur pour la cotation, puis émettre l’offre client | R21: 46309 | S21: Échu depuis le 21/08/2026 : blocage côté fournisseur, attente de cotation (compta). Base 2025 : 7 383 000 (soldé). | T21: Licences de sécurité des postes (endpoint) | U21: → NEURONES | V21: Direction : PDG : Luc de Chammard (confirmé) · DG délégué : Bertrand Ducurtil (à confirmer) · Directeur marketing et communication : Matthieu Vautier (à confirmer)
B22: 14 | C22: Prospect | D22: GIZ | E22: À COMPLÉTER — intitulé de l’affaire à préciser | H22: À confirmer | J22: M0 – À qualifier | M22: =IF(OR(L22="",K22=""),"",L22*K22) | O22: =IF(OR(L22="",N22=""),"",IFERROR(N22/L22,"")) | P22: P3 | S22: Aucune donnée dans le fichier d’origine.
B23: 15 | C23: Appel d’offres | D23: Le Médiateur de la République de Côte d'Ivoire (à valider) | E23: Plateforme e-Médiation (via OC²S) | F23: Plateforme e-Médiation via OC²S — rôle, solution et périmètre à confirmer | G23: Appel d'offres public (à valider) | H23: À confirmer | J23: M0 – À qualifier | M23: =IF(OR(L23="",K23=""),"",L23*K23) | O23: =IF(OR(L23="",N23=""),"",IFERROR(N23/L23,"")) | P23: P2 | Q23: Compléter la fiche : entité porteuse, montant, calendrier de l'AO, pièces attendues · Confirmer le rôle d'OC²S (mandataire / sous-traitant) et formaliser l'accord de groupement · Verrouiller le rétroplanning de dépôt | S23: En cours de montage (à valider) — données non renseignées dans le fichier source | M0 - À qualifier | Ligne présente dans le fichier sous l'intitulé « OCCS EMEDIATION » sans aucune donnée. Pré-renseignée ici sur la base du contexte connu : À VALIDER avant diffusion. | T23: Plateforme de e-médiation et intégration applicative — à valider | U23: → Appels d’offres
B24: 16 | C24: Prospect | D24: AGITECH (AG Tech Afrik) | E24: Solution MDM — Mobile Device Management (40 terminaux) | F24: Solution MDM à sélectionner; ManageEngine Endpoint Central à évaluer, sans engagement à ce stade | G24: Demande de cotation — affaire indirecte (client final via AGITECH) | H24: Commercial IAT | I24: Ponctuel | J24: M1 – Besoin identifié | M24: =IF(OR(L24="",K24=""),"",L24*K24) | O24: =IF(OR(L24="",N24=""),"",IFERROR(N24/L24,"")) | P24: P1 | Q24: QUICK WIN : produire la cotation sous 5 jours ouvrés · Sélectionner l'éditeur MDM et obtenir le prix partenaire · Clarifier l'identité du client final et le potentiel d'extension du parc | S24: Demande de cotation reçue — offre non remise | M1 - Besoin identifié / demande d'étude | Faible montant mais forte valeur d'entrée : porte d'accès au client final et à un partenaire prescripteur. | T24: Gestion des terminaux mobiles (MDM) — cotation
B25: 17 | C25: Prospect | D25: SIFCA | E25: Transformation digitale et pilotage des processus métiers | F25: Odoo Community / Microsoft Power Platform ou BI — à valider selon architecture existante | G25: Prospection directe (à initier) | H25: Commercial IAT | J25: M0 – À qualifier | M25: =IF(OR(L25="",K25=""),"",L25*K25) | O25: =IF(OR(L25="",N25=""),"",IFERROR(N25/L25,"")) | P25: P3 | Q25: Identifier DSI / finance / opérations · Obtenir un rendez-vous de découverte · Vérifier les systèmes en place et les achats en cours | S25: Approche grands comptes : cartographier les filiales et identifier un besoin métier prioritaire; ne pas présumer d’un remplacement ERP. | M0 - À qualifier | Prospect nouveau : besoin, budget, décideur et calendrier non confirmés. | T25: Transformation des processus, ERP et reporting
B26: 18 | C26: Prospect | D26: PALMCI | E26: Pilotage opérationnel, stocks et maintenance | F26: Odoo / outil de gestion des interventions / Microsoft BI — choix à confirmer après cadrage | G26: Prospection directe (à initier) | H26: Commercial IAT | J26: M0 – À qualifier | M26: =IF(OR(L26="",K26=""),"",L26*K26) | O26: =IF(OR(L26="",N26=""),"",IFERROR(N26/L26,"")) | P26: P3 | Q26: Contacter DSI et direction industrielle · Identifier un processus pilote · Confirmer contraintes sites et intégrations | S26: Hypothèse de besoin à valider; éviter toute proposition de remplacement du système industriel sans audit. | M0 - À qualifier | Prospect nouveau : besoin, budget, décideur et calendrier non confirmés. | T26: Gestion opérationnelle, maintenance et reporting
B27: 19 | C27: Prospect | D27: Olam Cocoa Processing Abidjan | E27: Pilotage des flux et automatisation des processus support | F27: Microsoft Power Platform / outils BI / intégration API — à confirmer après découverte | G27: Prospection directe (à initier) | H27: Commercial IAT | J27: M0 – À qualifier | M27: =IF(OR(L27="",K27=""),"",L27*K27) | O27: =IF(OR(L27="",N27=""),"",IFERROR(N27/L27,"")) | P27: P3 | Q27: Identifier IT / supply chain / opérations · Qualifier le processus cible et le décideur · Vérifier fournisseurs en place | S27: Prospecter un processus périphérique et mesurable plutôt que les systèmes industriels critiques. | M0 - À qualifier | Prospect nouveau : besoin, budget, décideur et calendrier non confirmés. | T27: Automatisation, intégration et reporting | V27: Alain MOGO — DSI Groupe · 05 06 72 72 82 (+1 autre dans l’onglet Contacts)
B28: 20 | C28: Prospect | D28: PROSUMA | E28: Automatisation, gestion documentaire et reporting | F28: Microsoft 365 / Power Automate / Power BI — licences et architecture à vérifier | G28: Prospection directe (à initier) | H28: Commercial IAT | J28: M0 – À qualifier | M28: =IF(OR(L28="",K28=""),"",L28*K28) | O28: =IF(OR(L28="",N28=""),"",IFERROR(N28/L28,"")) | P28: P3 | Q28: Identifier DSI / finance / opérations · Proposer un atelier de découverte · Quantifier le processus manuel ciblé | S28: Chercher un cas d’usage transversal et borné; ne pas présumer d’un besoin de refonte globale. | M0 - À qualifier | Prospect nouveau : besoin, budget, décideur et calendrier non confirmés. | T28: Automatisation des processus et pilotage décisionnel | V28: Direction : Dirigeants (DG / PDG) : Abou Kassam et Karim Fakhry (confirmé) · DSI : Moussa Touré (à confirmer) Moussa TOURE — DSI · D : (+225) 27 21 25 34 16 / 07 57 25 79 54 · Moussa.Toure@prosuma.ci (+3 autres dans l’onglet Contacts)
B29: 21 | C29: Prospect | D29: Africa Global Logistics Côte d’Ivoire (AGL) | E29: Automatisation des workflows et services IT complémentaires | F29: Microsoft 365 / Power Platform / cloud partenaire — à confirmer selon exigences client | G29: Prospection directe (à initier) | H29: Commercial IAT | J29: M0 – À qualifier | M29: =IF(OR(L29="",K29=""),"",L29*K29) | O29: =IF(OR(L29="",N29=""),"",IFERROR(N29/L29,"")) | P29: P3 | Q29: Identifier DSI / opérations · Rechercher un lot complémentaire · Qualifier exigences de sécurité et références requises | S29: Cibler les fonctions support ou un lot externalisable sans intervenir d’emblée sur les systèmes logistiques critiques. | M0 - À qualifier | Prospect nouveau : besoin, budget, décideur et calendrier non confirmés. | T29: Workflows, intégration applicative et services d’infrastructure | V29: Dimitri ADON — Chef de Département Infrastructure et Technique · 07 59 92 72 42 / 07 47 72 63 44 · Dimitri.ADON@bollore.com
B30: 22 | C30: Prospect | D30: SODECI | E30: Digitalisation des processus support et maintenance IT | F30: ManageEngine / Microsoft Power Platform — modules à confirmer | G30: Prospection directe (à initier) | H30: Commercial IAT | J30: M0 – À qualifier | M30: =IF(OR(L30="",K30=""),"",L30*K30) | O30: =IF(OR(L30="",N30=""),"",IFERROR(N30/L30,"")) | P30: P3 | Q30: Identifier DSI / achats / moyens généraux · Vérifier procédure de référencement fournisseur · Proposer un atelier de cadrage | S30: Approche ciblée; qualifier procédures d’achat, exigences de sécurité et contrats existants. | M0 - À qualifier | Prospect nouveau : besoin, budget, décideur et calendrier non confirmés. | T30: Automatisation, gestion des services IT et reporting | V30: Hermann N'ganza — DTI · 0506323236 · hermann.nganza@gs2e.ci (+6 autres dans l’onglet Contacts)
B31: 23 | C31: Prospect | D31: CIE | E31: Automatisation des workflows et résilience IT | F31: ManageEngine / Microsoft / partenaire cybersécurité — périmètre à confirmer | G31: Prospection directe (à initier) | H31: Commercial IAT | J31: M0 – À qualifier | M31: =IF(OR(L31="",K31=""),"",L31*K31) | O31: =IF(OR(L31="",N31=""),"",IFERROR(N31/L31,"")) | P31: P3 | Q31: Identifier DSI / opérations / achats · Qualifier le périmètre non critique · Vérifier exigences et procédure de consultation | S31: Ne pas proposer de changement sur systèmes critiques sans références et validation technique appropriées. | M0 - À qualifier | Prospect nouveau : besoin, budget, décideur et calendrier non confirmés. | T31: Services IT, continuité d’activité et automatisation | V31: CIE : Tanoh Hermann · 0709332615 · batanoh@cie.ci GS2E : Hermann N'ganza — DTI · 0506323236 · hermann.nganza@gs2e.ci (+6 autres dans l’onglet Contacts)
B32: 24 | C32: Prospect | D32: Air Côte d’Ivoire | E32: Services IT complémentaires, gestion documentaire et résilience | F32: Microsoft 365 / outils de workflow / partenaire cybersécurité — à valider | G32: Prospection directe (à initier) | H32: Commercial IAT | J32: M0 – À qualifier | M32: =IF(OR(L32="",K32=""),"",L32*K32) | O32: =IF(OR(L32="",N32=""),"",IFERROR(N32/L32,"")) | P32: P3 | Q32: Identifier DSI / sécurité / achats · Confirmer les lots accessibles et références exigées · Évaluer calendrier d’achat | S32: Cibler un besoin périphérique au SI aéronautique; qualification de sécurité obligatoire. | M0 - À qualifier | Prospect nouveau : besoin, budget, décideur et calendrier non confirmés. | T32: Automatisation, gestion documentaire et résilience IT | V32: Martial DIABATE — RSI · 07 69 55 95 70 · ma.diabate@aircotedivoire.com (+3 autres dans l’onglet Contacts)
B33: 25 | C33: Prospect | D33: GIG (Groupement d’Industries Générales) | E33: Gestion des stocks, achats et opérations | F33: Odoo Community — uniquement si adéquation confirmée après audit | G33: Prospection directe (à initier) | H33: Commercial IAT | J33: M0 – À qualifier | M33: =IF(OR(L33="",K33=""),"",L33*K33) | O33: =IF(OR(L33="",N33=""),"",IFERROR(N33/L33,"")) | P33: P3 | Q33: Vérifier l’identité et le périmètre de l’entreprise · Identifier dirigeant / finance / opérations · Proposer entretien découverte | S33: Prospect à qualifier; confirmer l’entité exacte, les activités et le système existant avant proposition. | M0 - À qualifier | Prospect nouveau : besoin, budget, décideur et calendrier non confirmés. | T33: ERP et transformation des processus
B34: 26 | C34: Prospect | D34: Banian Group | E34: Gestion interfiliales, CRM et tableaux de bord | F34: Odoo CRM / Microsoft Power Platform / BI — à définir après cadrage | G34: Prospection directe (à initier) | H34: Commercial IAT | J34: M0 – À qualifier | M34: =IF(OR(L34="",K34=""),"",L34*K34) | O34: =IF(OR(L34="",N34=""),"",IFERROR(N34/L34,"")) | P34: P3 | Q34: Cartographier les filiales et décideurs · Identifier un pilote · Vérifier systèmes et priorités budgétaires | S34: Approche groupe, mais qualification filiale par filiale et décisionnaire par décisionnaire. | M0 - À qualifier | Prospect nouveau : besoin, budget, décideur et calendrier non confirmés. | T34: CRM, workflows et pilotage multi-entités
B35: 27 | C35: Prospect | D35: CDC-CI (Caisse des Dépôts et Consignations de Côte d’Ivoire) | E35: Digitalisation des processus et gestion documentaire | F35: Microsoft 365 / Power Platform / GED partenaire — conformité et périmètre à confirmer | G35: Prospection directe (à initier) | H35: Commercial IAT | J35: M0 – À qualifier | M35: =IF(OR(L35="",K35=""),"",L35*K35) | O35: =IF(OR(L35="",N35=""),"",IFERROR(N35/L35,"")) | P35: P3 | Q35: Surveiller les avis et manifestations d’intérêt · Vérifier critères d’éligibilité et références · Identifier le service demandeur | S35: Veille sur les consultations officielles; aucune opportunité d’appel d’offres présumée ouverte. | M0 - À qualifier | Prospect nouveau : besoin, budget, décideur et calendrier non confirmés. | T35: Gestion documentaire, automatisation et reporting
B36: 28 | C36: Prospect | D36: MTN Côte d’Ivoire | E36: Automatisation métiers et solutions numériques complémentaires | F36: Microsoft / API / plateforme IA sécurisée — technologie à sélectionner après qualification | G36: Prospection directe (à initier) | H36: Commercial IAT | J36: M0 – À qualifier | M36: =IF(OR(L36="",K36=""),"",L36*K36) | O36: =IF(OR(L36="",N36=""),"",IFERROR(N36/L36,"")) | P36: P3 | Q36: Identifier direction IT / innovation / opérations · Cartographier contrats et partenaires en place · Qualifier un cas d’usage | S36: Compte stratégique avec écosystème technologique mature; chercher un besoin précis et une porte d’entrée partenaire. | M0 - À qualifier | Prospect nouveau : besoin, budget, décideur et calendrier non confirmés. | T36: Automatisation, intégration applicative et IA métier | V36: MTN : Corinne N’TAPKE — Manager Technology Process · 22505238080 · Corinne.n’tapke@mtn.com (+10 autres dans l’onglet Contacts) MTN BUSINESS : Hervé ZANDO · 22505044448 · Herve.Zando@mtn.com (+3 autres dans l’onglet Contacts)
B37: 29 | C37: Client existant | D37: Orange Business — E-Agri | E37: Plateforme E-Agri (commercialisation de produits vivriers) | F37: Développement plateforme — partenaires | G37: Orange Business | H37: À confirmer | I37: Récurrent | J37: M6 – Gagné | M37: =IF(OR(L37="",K37=""),"",L37*K37) | O37: =IF(OR(L37="",N37=""),"",IFERROR(N37/L37,"")) | P37: P2 | Q37: Faire le point sur l’avancement du développement par les partenaires | S37: Contrat de réalisation + revenue sharing avec Orange en exploitation (réunion du 13/10). Montant et avancement à compléter ; aucune facturation dans le point comptable. | T37: Développement de plateforme numérique | U37: → Orange Business | V37: Mame DIOP — DSI · 22507799662 · mame.diopba@orange.com (+7 autres dans l’onglet Contacts)
B38: 30 | C38: Prospect | D38: Client à préciser (projet digitalisation) | E38: Digitalisation du pôle opérationnel | F38: Développement sur mesure (à transformer en produit) | G38: Approche directe | H38: À confirmer | I38: Récurrent | J38: M5 – Négociation / signature | L38: 36000000 | M38: =IF(OR(L38="",K38=""),"",L38*K38) | O38: =IF(OR(L38="",N38=""),"",IFERROR(N38/L38,"")) | P38: P1 | Q38: RDV du 19/10 pour finaliser le cahier des charges | R38: 46314 | S38: Accord de principe donné. 36 M payés 1 M / mois sur 3 ans. Cahier des charges presque finalisé. Hypothèse : client = groupe PROSUMA (le « grand frère Aboukassar » cité en réunion ≈ Abou Kassam, codirigeant de PROSUMA ; entrepôts sec / frais cohérents avec la distribution) — à confirmer. | T38: Digitalisation des processus
B39: 31 | C39: Prospect | D39: Client à préciser (projet digitalisation) | E39: Prisme + portail (complément) | F39: Développement sur mesure | G39: Approche directe | H39: À confirmer | I39: Récurrent | J39: M3 – Offre en préparation | L39: 72000000 | M39: =IF(OR(L39="",K39=""),"",L39*K39) | O39: =IF(OR(L39="",N39=""),"",IFERROR(N39/L39,"")) | P39: P1 | Q39: Finaliser la cotation · la valider ensemble · l’émettre sur papier à en-tête Infinity | S39: Hypothèse : ≈ 3 M / mois sur 24 mois (option paiement comptant à chiffrer). Argument : remplace la saisie manuelle de ≈ 20 comptables juniors. | T39: Digitalisation des processus
B40: 32 | C40: Prospect | D40: Client à préciser (projet digitalisation) | E40: Projets entrepôts (sec / frais) | F40: À définir | G40: Approche directe | H40: À confirmer | J40: M0 – À qualifier | M40: =IF(OR(L40="",K40=""),"",L40*K40) | O40: =IF(OR(L40="",N40=""),"",IFERROR(N40/L40,"")) | P40: P3 | Q40: Qualifier après le lancement du projet de digitalisation | S40: Évoqué par le client comme projet suivant.
B41: 33 | C41: Prospect | D41: Ministère des Transports | E41: Gestion de flotte automobile | F41: Éditeur partenaire (boîtier + 4G + plateforme) | G41: Prospection directe | H41: À confirmer | J41: M1 – Besoin identifié | M41: =IF(OR(L41="",K41=""),"",L41*K41) | O41: =IF(OR(L41="",N41=""),"",IFERROR(N41/L41,"")) | P41: P2 | Q41: Obtenir des tests sur les véhicules de l’entreprise avant de se positionner | S41: Solution à challenger techniquement ; cible : grands parcs automobiles (PND). | T41: Gestion de flotte
B42: 34 | C42: Prospect | D42: SGI (BOA, BNI…) | E42: Plateforme d’investissement Wari+ (marque blanche) | F42: Wari+ — partenariat à signer | G42: Via le partenaire éditeur | H42: À confirmer | J42: M1 – Besoin identifié | M42: =IF(OR(L42="",K42=""),"",L42*K42) | O42: =IF(OR(L42="",N42=""),"",IFERROR(N42/L42,"")) | P42: P1 | Q42: Signer le partenariat · préparer la démo du salon | R42: 46317 | S42: Prix plancher éditeur 45 M, revenue sharing au-delà. Démo interactive prévue au Salon de l’Épargne (22-23/10). | T42: Plateforme front-office d’investissement | V42: BOA BANK CI : johnson YAPI — DSI GROUPE · 221 07 77 482 0450 · jyapi@boaholding.com (+7 autres dans l’onglet Contacts) BNI : Noufe — DSI · 07 07620719 · anoufe@bni.ci (+6 autres dans l’onglet Contacts)
B43: 35 | C43: Prospect | D43: Mutuelle Nationale de Madagascar | E43: Création d’une plateforme | F43: À définir | G43: Réseau (Madagascar) | H43: Maoula | J43: M1 – Besoin identifié | M43: =IF(OR(L43="",K43=""),"",L43*K43) | O43: =IF(OR(L43="",N43=""),"",IFERROR(N43/L43,"")) | P43: P3 | Q43: Faire le point avec Maoula | S43: Demande de proposition transmise par Maoula ; suivi à reprendre.
B44: 36 | C44: Prospect | D44: Deals B2B Direction — Huawei | E44: À compléter | F44: Huawei | G44: Direction générale | H44: Direction générale | J44: M0 – À qualifier | M44: =IF(OR(L44="",K44=""),"",L44*K44) | O44: =IF(OR(L44="",N44=""),"",IFERROR(N44/L44,"")) | P44: P2 | Q44: Compléter avec la Direction | S44: Deals gérés par la Direction : à faire figurer pour le suivi même si IAT n’est pas lead.
B45: 37 | C45: Prospect | D45: Deals B2B Direction — DGF | E45: À compléter | F45: À préciser | G45: Direction générale | H45: Direction générale | J45: M0 – À qualifier | M45: =IF(OR(L45="",K45=""),"",L45*K45) | O45: =IF(OR(L45="",N45=""),"",IFERROR(N45/L45,"")) | P45: P2 | Q45: Compléter avec la Direction | S45: Deals gérés par la Direction : à faire figurer pour le suivi même si IAT n’est pas lead.
B46: =IF(D46="","",ROW()-8) | M46: =IF(OR(L46="",K46=""),"",L46*K46) | O46: =IFERROR(N46/L46,"")
B47: =IF(D47="","",ROW()-8) | M47: =IF(OR(L47="",K47=""),"",L47*K47) | O47: =IFERROR(N47/L47,"")
B48: =IF(D48="","",ROW()-8) | M48: =IF(OR(L48="",K48=""),"",L48*K48) | O48: =IFERROR(N48/L48,"")
B49: =IF(D49="","",ROW()-8) | M49: =IF(OR(L49="",K49=""),"",L49*K49) | O49: =IFERROR(N49/L49,"")
B50: =IF(D50="","",ROW()-8) | M50: =IF(OR(L50="",K50=""),"",L50*K50) | O50: =IFERROR(N50/L50,"")
B51: ="TOTAL IAT ("&COUNTA(D9:D50)&" affaires)" -> TOTAL IAT (37 affaires) | L51: =SUM(L9:L50) -> 453330882 | M51: =SUM(M9:M50) -> 171217175 | N51: =SUM(N9:N50) -> 39000000 | O51: =IFERROR(N51/L51,"") -> 0.086029877

Sheet Renouvellements
B2: IAT — Renouvellements
B3: Contrats récurrents (licences et maintenance) · Source : point comptable du 13/10/2026 · Montants en FCFA
B4: Prochaine échéance = dernière facturation + 12 mois · Jaune pâle = à renseigner · Vert = repris d’une fiche client · colonnes calculées : échéance, jours, relances, alerte
B5: ← Retour à la synthèse
B7: CALENDRIER ET SUIVI DES RELANCES DE RENOUVELLEMENT
B8: N° | C8: Client | D8: Contrat / produit | E8: Dernière facturation | F8: Dernier montant facturé | G8: Historique facturé | H8: Prochaine échéance | I8: Jours restants | J8: Relance J-90 | K8: Relance J-30 | L8: Alerte | M8: Statut du renouvellement | N8: Porteur | O8: Date dernière relance | P8: Prochaine action | Q8: Commentaire | R8: Fiche
B9: 1 | C9: CNPS | D9: Licences ManageEngine | E9: =IF(ISNUMBER(CNPS!F41),CNPS!F41,"N/A") -> 45698 | F9: =IF(CNPS!G41="","",CNPS!G41) -> 21578849 | G9: 2025 : 21,6 M | H9: =IF(ISNUMBER(E9),EDATE(E9,12),"") -> 46063 | I9: =IF(ISNUMBER(H9),H9-TODAY(),"") -> -251 | J9: =IF(ISNUMBER(H9),H9-90,"") -> 45973 | K9: =IF(ISNUMBER(H9),H9-30,"") -> 46033 | L9: =IF(C9="","",IF(M9="Renouvelé","Renouvelé",IF(M9="Perdu","Perdu",IF(NOT(ISNUMBER(H9)),"Date à confirmer",IF(H9<TODAY(),"Échu - urgent",IF(H9-TODAY()<=90,"À relancer (≤ 90 j)","À venir")))))) -> Échu - urgent | M9: Offre envoyée | P9: Relance commerciale + rendez-vous avec la DSI CNPS pour obtenir la décision | Q9: Offre 2026 en attente de retour CNPS. Échéance dépassée. | R9: → CNPS
B10: 2 | C10: NEURONES | D10: Licence WithSecure | E10: =IF(ISNUMBER(NEURONES!F35),NEURONES!F35,"N/A") -> 45890 | F10: =IF(NEURONES!G35="","",NEURONES!G35) -> 7383000 | G10: 2025 : 7,4 M | H10: =IF(ISNUMBER(E10),EDATE(E10,12),"") -> 46255 | I10: =IF(ISNUMBER(H10),H10-TODAY(),"") -> -59 | J10: =IF(ISNUMBER(H10),H10-90,"") -> 46165 | K10: =IF(ISNUMBER(H10),H10-30,"") -> 46225 | L10: =IF(C10="","",IF(M10="Renouvelé","Renouvelé",IF(M10="Perdu","Perdu",IF(NOT(ISNUMBER(H10)),"Date à confirmer",IF(H10<TODAY(),"Échu - urgent",IF(H10-TODAY()<=90,"À relancer (≤ 90 j)","À venir")))))) -> Échu - urgent | M10: Attente cotation fournisseur | P10: Relancer le fournisseur pour la cotation, puis émettre l’offre | Q10: Blocage côté fournisseur. Échéance dépassée. | R10: → NEURONES
B11: 3 | C11: CNAM | D11: Licences ManageEngine | E11: =IF(ISNUMBER(CNAM!F41),CNAM!F41,"N/A") -> 46080 | F11: =IF(CNAM!G41="","",CNAM!G41) -> 66309707 | G11: 2024 : 69,8 M · 2025 : 66,3 M · 2026 : 66,3 M | H11: =IF(ISNUMBER(E11),EDATE(E11,12),"") -> 46445 | I11: =IF(ISNUMBER(H11),H11-TODAY(),"") -> 131 | J11: =IF(ISNUMBER(H11),H11-90,"") -> 46355 | K11: =IF(ISNUMBER(H11),H11-30,"") -> 46415 | L11: =IF(C11="","",IF(M11="Renouvelé","Renouvelé",IF(M11="Perdu","Perdu",IF(NOT(ISNUMBER(H11)),"Date à confirmer",IF(H11<TODAY(),"Échu - urgent",IF(H11-TODAY()<=90,"À relancer (≤ 90 j)","À venir")))))) -> À venir | M11: Non démarré | P11: Préparer l’offre de renouvellement 2027 avant la relance J-90 | Q11: Premier contrat : 46 % du montant récurrent annuel. | R11: → CNAM
B12: 4 | C12: FER | D12: Licences ManageEngine | E12: =IF(ISNUMBER(FER!F34),FER!F34,"N/A") -> 46197 | F12: =IF(FER!G34="","",FER!G34) -> 28766400 | G12: 2026 : 28,8 M (nouveau client) | H12: =IF(ISNUMBER(E12),EDATE(E12,12),"") -> 46562 | I12: =IF(ISNUMBER(H12),H12-TODAY(),"") -> 248 | J12: =IF(ISNUMBER(H12),H12-90,"") -> 46472 | K12: =IF(ISNUMBER(H12),H12-30,"") -> 46532 | L12: =IF(C12="","",IF(M12="Renouvelé","Renouvelé",IF(M12="Perdu","Perdu",IF(NOT(ISNUMBER(H12)),"Date à confirmer",IF(H12<TODAY(),"Échu - urgent",IF(H12-TODAY()<=90,"À relancer (≤ 90 j)","À venir")))))) -> À venir | M12: Non démarré | P12: Point de satisfaction client avant la relance J-90 | R12: → FER
B13: 5 | C13: NSIA | D13: Licences ManageEngine | E13: =IF(ISNUMBER(NSIA!F45),NSIA!F45,"N/A") -> 46283 | F13: =IF(NSIA!G45="","",NSIA!G45) -> 1610068 | G13: 2024 : 1,0 M · 2025 : 1,0 M · 2026 : 1,6 M | H13: =IF(ISNUMBER(E13),EDATE(E13,12),"") -> 46648 | I13: =IF(ISNUMBER(H13),H13-TODAY(),"") -> 334 | J13: =IF(ISNUMBER(H13),H13-90,"") -> 46558 | K13: =IF(ISNUMBER(H13),H13-30,"") -> 46618 | L13: =IF(C13="","",IF(M13="Renouvelé","Renouvelé",IF(M13="Perdu","Perdu",IF(NOT(ISNUMBER(H13)),"Date à confirmer",IF(H13<TODAY(),"Échu - urgent",IF(H13-TODAY()<=90,"À relancer (≤ 90 j)","À venir")))))) -> À venir | M13: Non démarré | Q13: Renouvelle chaque année en septembre. | R13: → NSIA
B14: 6 | C14: CNAM | D14: Contrat de maintenance ManageEngine | E14: =IF(ISNUMBER(CNAM!F42),CNAM!F42,"N/A") -> N/A | F14: =IF(CNAM!G42="","",CNAM!G42) -> 18000000 | G14: 2025 : 18 M · 2026 : 18 M | I14: =IF(ISNUMBER(H14),H14-TODAY(),"") | J14: =IF(ISNUMBER(H14),H14-90,"") | K14: =IF(ISNUMBER(H14),H14-30,"") | L14: =IF(C14="","",IF(M14="Renouvelé","Renouvelé",IF(M14="Perdu","Perdu",IF(NOT(ISNUMBER(H14)),"Date à confirmer",IF(H14<TODAY(),"Échu - urgent",IF(H14-TODAY()<=90,"À relancer (≤ 90 j)","À venir")))))) -> Date à confirmer | M14: Non démarré | P14: Renseigner la date de facturation / d’échéance du contrat | Q14: Date de facturation « N/A » dans le point comptable : saisir l’échéance en colonne H. Solde 2026 de 4,5 M encore à encaisser. | R14: → CNAM
B15: =IF(C15="","",ROW()-8) | H15: =IF(ISNUMBER(E15),EDATE(E15,12),"") | I15: =IF(ISNUMBER(H15),H15-TODAY(),"") | J15: =IF(ISNUMBER(H15),H15-90,"") | K15: =IF(ISNUMBER(H15),H15-30,"") | L15: =IF(C15="","",IF(M15="Renouvelé","Renouvelé",IF(M15="Perdu","Perdu",IF(NOT(ISNUMBER(H15)),"Date à confirmer",IF(H15<TODAY(),"Échu - urgent",IF(H15-TODAY()<=90,"À relancer (≤ 90 j)","À venir"))))))
B16: =IF(C16="","",ROW()-8) | H16: =IF(ISNUMBER(E16),EDATE(E16,12),"") | I16: =IF(ISNUMBER(H16),H16-TODAY(),"") | J16: =IF(ISNUMBER(H16),H16-90,"") | K16: =IF(ISNUMBER(H16),H16-30,"") | L16: =IF(C16="","",IF(M16="Renouvelé","Renouvelé",IF(M16="Perdu","Perdu",IF(NOT(ISNUMBER(H16)),"Date à confirmer",IF(H16<TODAY(),"Échu - urgent",IF(H16-TODAY()<=90,"À relancer (≤ 90 j)","À venir"))))))
B17: =IF(C17="","",ROW()-8) | H17: =IF(ISNUMBER(E17),EDATE(E17,12),"") | I17: =IF(ISNUMBER(H17),H17-TODAY(),"") | J17: =IF(ISNUMBER(H17),H17-90,"") | K17: =IF(ISNUMBER(H17),H17-30,"") | L17: =IF(C17="","",IF(M17="Renouvelé","Renouvelé",IF(M17="Perdu","Perdu",IF(NOT(ISNUMBER(H17)),"Date à confirmer",IF(H17<TODAY(),"Échu - urgent",IF(H17-TODAY()<=90,"À relancer (≤ 90 j)","À venir"))))))
B18: =IF(C18="","",ROW()-8) | H18: =IF(ISNUMBER(E18),EDATE(E18,12),"") | I18: =IF(ISNUMBER(H18),H18-TODAY(),"") | J18: =IF(ISNUMBER(H18),H18-90,"") | K18: =IF(ISNUMBER(H18),H18-30,"") | L18: =IF(C18="","",IF(M18="Renouvelé","Renouvelé",IF(M18="Perdu","Perdu",IF(NOT(ISNUMBER(H18)),"Date à confirmer",IF(H18<TODAY(),"Échu - urgent",IF(H18-TODAY()<=90,"À relancer (≤ 90 j)","À venir"))))))
B19: =IF(C19="","",ROW()-8) | H19: =IF(ISNUMBER(E19),EDATE(E19,12),"") | I19: =IF(ISNUMBER(H19),H19-TODAY(),"") | J19: =IF(ISNUMBER(H19),H19-90,"") | K19: =IF(ISNUMBER(H19),H19-30,"") | L19: =IF(C19="","",IF(M19="Renouvelé","Renouvelé",IF(M19="Perdu","Perdu",IF(NOT(ISNUMBER(H19)),"Date à confirmer",IF(H19<TODAY(),"Échu - urgent",IF(H19-TODAY()<=90,"À relancer (≤ 90 j)","À venir"))))))
B20: =IF(C20="","",ROW()-8) | H20: =IF(ISNUMBER(E20),EDATE(E20,12),"") | I20: =IF(ISNUMBER(H20),H20-TODAY(),"") | J20: =IF(ISNUMBER(H20),H20-90,"") | K20: =IF(ISNUMBER(H20),H20-30,"") | L20: =IF(C20="","",IF(M20="Renouvelé","Renouvelé",IF(M20="Perdu","Perdu",IF(NOT(ISNUMBER(H20)),"Date à confirmer",IF(H20<TODAY(),"Échu - urgent",IF(H20-TODAY()<=90,"À relancer (≤ 90 j)","À venir"))))))
B21: TOTAL — montant récurrent annuel (base dernière facturation) | F21: =SUM(F9:F20) -> 143648024

Sheet CNAM
B2: CNAM — Fiche compte
B3: Client existant IAT | Montants en FCFA | Facturation et encaissements : point comptabilité au 13/10/2026
B4: Cellules jaune pâle = information à compléter · Texte vert = valeur reprise d’un autre onglet
B5: ← Retour à la synthèse
B7: 1. FICHE COMPTE
B8: Secteur | C8: Protection sociale / assurance maladie
B9: Direction générale (recherche du 15/10/2026) | C9: DG : Karim Bamba (confirmé) · DGA : Ahmed Tidiane Diomandé (confirmé)
B10: Interlocuteur direction (nom / fonction) | C10: Ismael Djiré / Directeur du système d'information
B11: Interlocuteur opérationnel (nom / fonction) | C11: Souleymane Cisse / Ingénieur système service administrateur
B12: Responsable IAT (lead commercial) | C12: Fadel Koloma / Salim Kone
B13: Relation haut niveau gérée par | C13: Mahoula
B14: État de santé du compte | C14: Bon
B15: Taux de satisfaction (1 à 5) | C15: 4
B16: Dernier contact
B17: Prochain point prévu | C17: Présentation et formation sur les solutions de la CNAM endpoint central et services deskplus
B18: Notes (réunion du 13/10/2026 et comptabilité) | C18: Premier client IAT : 46 % du montant récurrent annuel (compta). Contrats récurrents : licences ManageEngine (renouvellement annuel, prochaine échéance 27/02/2027) + contrat de maintenance facturé 4,5 M par trimestre. Un nouveau directeur est arrivé sur un compte suivi en haut par Maoula : le prendre en charge côté opérationnel (rattachement à la CNAM à confirmer).
B20: DIRIGEANTS — CNAM (Côte d’Ivoire) (recherche web + LinkedIn, données au 15/10/2026)
B21: Fonction | C21: Nom | E21: Fiabilité | F21: Source / remarque
B22: DG | C22: Karim Bamba | E22: Confirmé | F22: Site officiel (ipscnam.ci) ; pas de profil LinkedIn trouvé.
B23: DGA | C23: Ahmed Tidiane Diomandé | E23: Confirmé | F23: LinkedIn : Directeur Général Adjoint.
B24: DSI | C24: Ismael Djiré | E24: Confirmé | F24: directeur du système d'information et chef de service sécurité et infrastructure
B25: Directeur commercial | C25: — | E25: Non trouvé
B27: CONTACTS — BASE CLIENTS CI (aucun contact trouvé)
B28: Nom | C28: Fonction | E28: Profil | G28: Téléphone | I28: Email | L28: Commentaire
B29: Karim Bamba | C29: Directeur Général Adjoint | E29: Direction Générale
B30: Ahmed Tidiane Diomandé | C30: Directeur Général Adjoint | E30: Direction Générale
B31: Ismael Djiré | C31: Directeur du système d'information | E31: DirectionSI
B32: Souleymane Cisse | C32: Ingénieur système service administrateur | E32: Exploitation / infra | G32: +225 0555252468
B33: Malick Coulibaly | C33: Chef de service Projet | E33: Direction SI
B34: Naby Ouattara | C34: Chef cde service Helpdesk | E34: Direction SI | G34: +225 0758543513
B36: 2. CE QUI A DÉJÀ ÉTÉ VENDU ET FACTURÉ (historique, encaissements, récurrent / ponctuel)
B37: Produit / service | C37: Partenaire / éditeur | D37: Récurrent / ponctuel | E37: Exercice | F37: Date de facturation | G37: Montant facturé | H37: Coût des ventes | I37: Commission | J37: CA net | K37: Marge | L37: Encaissé | M37: Solde à encaisser | N37: Commentaires
B38: Licences ManageEngine (déploiement) | C38: ManageEngine | D38: Récurrent | E38: 2024 | F38: 45595 | G38: 69799690 | J38: =IF(G38="","",G38-N(I38)) -> 69799690 | K38: =IF(G38="","",J38-N(H38)) -> 69799690 | L38: 69799690 | M38: =IF(G38="","",G38-N(L38)) -> 0 | N38: Encaissé le 05/02/2025 (chèque 5770692).
B39: Licences ManageEngine | C39: ManageEngine | D39: Récurrent | E39: 2025 | F39: 45898 | G39: 66309706 | J39: =IF(G39="","",G39-N(I39)) -> 66309706 | K39: =IF(G39="","",J39-N(H39)) -> 66309706 | L39: 66309706 | M39: =IF(G39="","",G39-N(L39)) -> 0 | N39: Encaissé le 01/12/2025.
B40: Contrat de maintenance ManageEngine | C40: ManageEngine | D40: Récurrent | E40: 2025 | F40: N/A | G40: 18000000 | J40: =IF(G40="","",G40-N(I40)) -> 18000000 | K40: =IF(G40="","",J40-N(H40)) -> 18000000 | L40: 18000000 | M40: =IF(G40="","",G40-N(L40)) -> 0 | N40: Date de facturation non renseignée (N/A). Encaissé en déc. 2025 (9 M + 4,5 M + 4,5 M).
B41: Licences ManageEngine (renouvellement) | C41: ManageEngine | D41: Récurrent | E41: 2026 | F41: 46080 | G41: 66309707 | H41: 0 | I41: 33000000 | J41: =IF(G41="","",G41-N(I41)) -> 33309707 | K41: =IF(G41="","",J41-N(H41)) -> 33309707 | L41: 66309707 | M41: =IF(G41="","",G41-N(L41)) -> 0 | N41: Soldé. Coût des ventes et commission repris du pipeline d’origine.
B42: Contrat de maintenance ManageEngine | C42: ManageEngine | D42: Récurrent | E42: 2026 | F42: N/A | G42: 18000000 | H42: 500000 | I42: 6000000 | J42: =IF(G42="","",G42-N(I42)) -> 12000000 | K42: =IF(G42="","",J42-N(H42)) -> 11500000 | L42: 13500000 | M42: =IF(G42="","",G42-N(L42)) -> 4500000 | N42: Facturation trimestrielle de 4,5 M. Solde de 4,5 M à relancer auprès de la direction financière (échéance 01/12/2026). Date de facturation à renseigner.
J43: =IF(G43="","",G43-N(I43)) | K43: =IF(G43="","",J43-N(H43)) | M43: =IF(G43="","",G43-N(L43))
J44: =IF(G44="","",G44-N(I44)) | K44: =IF(G44="","",J44-N(H44)) | M44: =IF(G44="","",G44-N(L44))
B45: TOTAL FACTURÉ (tous exercices) | G45: =SUM(G38:G44) -> 238419103 | H45: =SUM(H38:H44) -> 500000 | I45: =SUM(I38:I44) -> 39000000 | J45: =SUM(J38:J44) -> 199419103 | K45: =SUM(K38:K44) -> 198919103 | L45: =SUM(L38:L44) -> 233919103 | M45: =SUM(M38:M44) -> 4500000
B46: dont exercice 2026 | G46: =SUMIFS(G38:G44,$E$38:$E$44,2026) -> 84309707 | I46: =SUMIFS(I38:I44,$E$38:$E$44,2026) -> 39000000 | K46: =SUMIFS(K38:K44,$E$38:$E$44,2026) -> 44809707 | L46: =SUMIFS(L38:L44,$E$38:$E$44,2026) -> 79809707 | M46: =SUMIFS(M38:M44,$E$38:$E$44,2026) -> 4500000
B48: 3. OFFRES EN COURS / À SUIVRE (envoyées, non encore validées, renouvellements)
B49: Offre / affaire | C49: Partenaire / éditeur | D49: Étape | E49: Date d’envoi | F49: Échéance décision | G49: Montant | H49: Closing | I49: Montant pondéré | J49: Responsable | K49: Prochaine étape | N49: Commentaires
B50: Renouvellement licences ManageEngine 2027 | C50: ManageEngine | D50: M3 – Offre en préparation | F50: 46355 | G50: =IF(CNAM!G41="","",CNAM!G41) -> 66309707 | I50: =IF(OR(G50="",H50=""),"",G50*H50) | J50: Commercial IAT | K50: Préparer l’offre de renouvellement avant la relance J-90 (29/11/2026). | N50: Échéance du contrat : 27/02/2027. Montant de base = dernière facturation.
I51: =IF(OR(G51="",H51=""),"",G51*H51)
I52: =IF(OR(G52="",H52=""),"",G52*H52)
I53: =IF(OR(G53="",H53=""),"",G53*H53)
B54: TOTAL OFFRES EN COURS | G54: =SUM(G50:G53) -> 66309707 | I54: =SUM(I50:I53) -> 0
B56: 4. STRATÉGIE DE CONTINUITÉ ET DE DÉVELOPPEMENT (vente croisée, renouvellement)
B57: Opportunité | C57: Solution / partenaire | D57: Priorité | E57: Échéance | F57: Responsable | G57: Valeur pour le client / action à mener | N57: Commentaires
B58: Étendre la couverture ManageEngine (autres modules) | C58: ManageEngine | D58: P2 | F58: Commercial IAT | G58: Présentation de l’offre complète ManageEngine (avec Salim / Kade) et cartographie des modules non encore vendus.
B59: Mesurer la satisfaction et sécuriser le renouvellement 2027 | C59: Licences + maintenance | D59: P1 | E59: 46355 | F59: Commercial IAT | G59: Point de satisfaction avec l’équipe opérationnelle avant la relance J-90 ; encaisser le solde de maintenance avant de renégocier.

Sheet CNPS
B2: CNPS — Fiche compte
B3: Client existant IAT | Montants en FCFA | Facturation et encaissements : point comptabilité au 13/10/2026
B4: Cellules jaune pâle = information à compléter · Texte vert = valeur reprise d’un autre onglet
B5: ← Retour à la synthèse
B7: 1. FICHE COMPTE
B8: Secteur | C8: Protection sociale
B9: Direction générale (recherche du 15/10/2026) | C9: DG : Denis Charles Kouassi (confirmé) · DGA chargé de l’exploitation : Idriss Traoré (à confirmer) · DSI : Thierry Bahi (à confirmer)
B10: Interlocuteur direction (nom / fonction) | C10: Gballet BEUGRE — Directeur du Système d'Information (DSI) (base clients — coordonnées ci-dessous)
B11: Interlocuteur opérationnel (nom / fonction) | C11: Innocent YAPI — RSSI ; Amadou DIOMANDOU — Chef de Departement Infrastructure et Exploitation ; Daouda COULIBALY — Chef du Service Système Réseau et NTIC (base clients)
B12: Achats / marchés | C12: Nomel Lorgn Florent — Acheteur ; Mme YASSI Née DIALLO — Resp Chargés des Marchés (base clients)
B13: Responsable IAT (lead commercial) | C13: Fadel Koloma / Salim Kone
B14: Relation haut niveau gérée par
B15: État de santé du compte
B16: Taux de satisfaction (1 à 5)
B17: Dernier contact
B18: Prochain point prévu
B19: Notes (réunion du 13/10/2026 et comptabilité) | C19: Renouvellement des licences échu depuis le 10/02/2026 : offre 2026 envoyée, en attente de retour (compta). La réunion du 13/10 évoque un contrat de 22 700 000 envoyé à la signature et une autre offre d’environ 59 M non validée. Le montant du renouvellement n’est pas chiffré dans le point comptable : à rapprocher.
B21: DIRIGEANTS — CNPS (Côte d’Ivoire) (recherche web + LinkedIn, données au 15/10/2026)
B22: Fonction | C22: Nom | E22: Fiabilité | F22: Source / remarque
B23: DG | C23: Denis Charles Kouassi | E23: Confirmé | F23: LinkedIn + presse.
B24: DGA chargé de l’exploitation | C24: Idriss Traoré | E24: À confirmer | F24: Profil LinkedIn en lecture limitée.
B25: DSI | C25: Thierry Bahi | E25: À confirmer | F25: Cité en déc. 2023, introuvable sur LinkedIn. ⚠ La base clients CI indique Gballet BEUGRE comme DSI : à trancher.
B26: Directeur commercial | C26: — | E26: Non trouvé
B28: CONTACTS — BASE CLIENTS CI (CNPS)
B29: Nom | C29: Fonction | E29: Profil | G29: Téléphone | I29: Email | L29: Commentaire
B30: Gballet BEUGRE | C30: Directeur du Système d'Information (DSI) | E30: Direction SI / digital | G30: Cel:(225)08305255 | I30: g.beugre@cnps.ci | L30: La recherche web du 15/10/2026 cite Thierry Bahi comme DSI (à confirmer) : vérifier qui est en poste.
B31: Innocent YAPI | C31: RSSI | E31: Sécurité SI | G31: 08 30 57 79 | I31: i.yapi@cnps.ci | L31: Numéro au format à 8 chiffres (avant 2021) : à mettre à jour
B32: Amadou DIOMANDOU | C32: Chef de Departement Infrastructure et Exploitation | E32: Infrastructure / réseaux | G32: 0779 42 41 00 / 014307744 | I32: a.diomande@cnps.ci
B33: Daouda COULIBALY | C33: Chef du Service Système Réseau et NTIC | E33: Infrastructure / réseaux | G33: CEL: +225 57887371 | I33: d.coulibaly@cnps.ci | L33: Numéro au format à 8 chiffres (avant 2021) : à mettre à jour
B34: Nomel Lorgn Florent | C34: Acheteur | E34: Achats / marchés | G34: 07 57 45 52 82 | I34: f.nomel@cnps.ci
B35: Mme YASSI Née DIALLO | C35: Resp Chargés des Marchés | E35: Achats / marchés | I35: k.diallo@cnps.ci
B36: DRAME | C36: Resp Sce Formation | E36: Commercial / autre | G36: 07 65 38 98 | I36: y.drame@cnps.ci | L36: Numéro au format à 8 chiffres (avant 2021) : à mettre à jour
B37: POLL Hermann SEKA SEKA | E37: Non renseigné | G37: 07 59 34 55 44 | I37: p.seka@cnps.ci
B39: 2. CE QUI A DÉJÀ ÉTÉ VENDU ET FACTURÉ (historique, encaissements, récurrent / ponctuel)
B40: Produit / service | C40: Partenaire / éditeur | D40: Récurrent / ponctuel | E40: Exercice | F40: Date de facturation | G40: Montant facturé | H40: Coût des ventes | I40: Commission | J40: CA net | K40: Marge | L40: Encaissé | M40: Solde à encaisser | N40: Commentaires
B41: Licences ManageEngine | C41: ManageEngine | D41: Récurrent | E41: 2025 | F41: 45698 | G41: 21578849 | J41: =IF(G41="","",G41-N(I41)) -> 21578849 | K41: =IF(G41="","",J41-N(H41)) -> 21578849 | L41: 21578849 | M41: =IF(G41="","",G41-N(L41)) -> 0 | N41: Encaissé le 18/03/2025.
J42: =IF(G42="","",G42-N(I42)) | K42: =IF(G42="","",J42-N(H42)) | M42: =IF(G42="","",G42-N(L42))
J43: =IF(G43="","",G43-N(I43)) | K43: =IF(G43="","",J43-N(H43)) | M43: =IF(G43="","",G43-N(L43))
J44: =IF(G44="","",G44-N(I44)) | K44: =IF(G44="","",J44-N(H44)) | M44: =IF(G44="","",G44-N(L44))
B45: TOTAL FACTURÉ (tous exercices) | G45: =SUM(G41:G44) -> 21578849 | H45: =SUM(H41:H44) -> 0 | I45: =SUM(I41:I44) -> 0 | J45: =SUM(J41:J44) -> 21578849 | K45: =SUM(K41:K44) -> 21578849 | L45: =SUM(L41:L44) -> 21578849 | M45: =SUM(M41:M44) -> 0
B46: dont exercice 2026 | G46: =SUMIFS(G41:G44,$E$41:$E$44,2026) -> 0 | I46: =SUMIFS(I41:I44,$E$41:$E$44,2026) -> 0 | K46: =SUMIFS(K41:K44,$E$41:$E$44,2026) -> 0 | L46: =SUMIFS(L41:L44,$E$41:$E$44,2026) -> 0 | M46: =SUMIFS(M41:M44,$E$41:$E$44,2026) -> 0
B48: 3. OFFRES EN COURS / À SUIVRE (envoyées, non encore validées, renouvellements)
B49: Offre / affaire | C49: Partenaire / éditeur | D49: Étape | E49: Date d’envoi | F49: Échéance décision | G49: Montant | H49: Closing | I49: Montant pondéré | J49: Responsable | K49: Prochaine étape | N49: Commentaires
B50: Renouvellement licences ManageEngine 2026 | C50: ManageEngine | D50: M5 – Négociation / signature | F50: 46318 | G50: 22700000 | I50: =IF(OR(G50="",H50=""),"",G50*H50) | J50: Commercial IAT | K50: Relance commerciale + rendez-vous avec la DSI CNPS pour obtenir la décision. | N50: Échéance dépassée (10/02/2026). 22,7 M = montant évoqué en réunion ; non chiffré dans le point comptable. Base 2025 : 21 578 849.
B51: Offre ≈ 59 M (envoyée, non validée) | D51: M4 – Offre remise | G51: 59000000 | I51: =IF(OR(G51="",H51=""),"",G51*H51) | J51: Commercial IAT | K51: Récupérer l’offre (absente du point transmis par Désiré) et fixer une date de décision. | N51: Objet et date d’envoi à compléter. Rattachement à la CNPS à confirmer (transcription « CNTS / CNT »).
I52: =IF(OR(G52="",H52=""),"",G52*H52)
I53: =IF(OR(G53="",H53=""),"",G53*H53)
B54: TOTAL OFFRES EN COURS | G54: =SUM(G50:G53) -> 81700000 | I54: =SUM(I50:I53) -> 0
B56: 4. STRATÉGIE DE CONTINUITÉ ET DE DÉVELOPPEMENT (vente croisée, renouvellement)
B57: Opportunité | C57: Solution / partenaire | D57: Priorité | E57: Échéance | F57: Responsable | G57: Valeur pour le client / action à mener | N57: Commentaires
B58: Vente croisée sur la base installée ManageEngine | C58: ManageEngine | D58: P2 | F58: Commercial IAT | G58: Une fois le renouvellement signé : identifier les besoins IT non couverts et proposer les modules complémentaires.

Sheet FER
B2: FER — Fiche compte
B3: Client existant IAT | Montants en FCFA | Facturation et encaissements : point comptabilité au 13/10/2026
B4: Cellules jaune pâle = information à compléter · Texte vert = valeur reprise d’un autre onglet
B5: ← Retour à la synthèse
B7: 1. FICHE COMPTE
B8: Secteur | C8: Administration / infrastructures routières (Fonds d’entretien routier)
B9: Direction générale (recherche du 15/10/2026) | C9: Directrice générale : Annick Tohé Lasmel (confirmé) · Directeur financier et comptable : Moussa Diarra (à confirmer)
B10: Interlocuteur direction (nom / fonction)
B11: Interlocuteur opérationnel (nom / fonction)
B12: Responsable IAT (lead commercial) | C12: Commercial IAT
B13: Relation haut niveau gérée par
B14: État de santé du compte
B15: Taux de satisfaction (1 à 5)
B16: Dernier contact
B17: Prochain point prévu
B18: Notes (réunion du 13/10/2026 et comptabilité) | C18: Nouveau client 2026 (compta) : licences ManageEngine facturées 28 766 400 le 24/06/2026, soldées. Prochaine échéance 24/06/2027. La sécurisation des boîtes mail était le produit d’entrée ; une formation sur la solution était prévue.
B20: DIRIGEANTS — FER (Côte d’Ivoire) (recherche web + LinkedIn, données au 15/10/2026)
B21: Fonction | C21: Nom | E21: Fiabilité | F21: Source / remarque
B22: Directrice générale | C22: Annick Tohé Lasmel | E22: Confirmé | F22: Site officiel du FER (actif juillet 2026) ; dirige le FER depuis 2022 ; pas de profil LinkedIn.
B23: Directeur financier et comptable | C23: Moussa Diarra | E23: À confirmer | F23: Information complémentaire de la recherche.
B24: DGA | C24: — | E24: Non trouvé
B25: DSI | C25: — | E25: Non trouvé | F25: Aucun DSI trouvé : à identifier (porte d’entrée naturelle pour ManageEngine).
B26: Directeur commercial | C26: — | E26: Non trouvé
B28: CONTACTS — BASE CLIENTS CI (aucun contact trouvé)
B29: Nom | C29: Fonction | E29: Profil | G29: Téléphone | I29: Email | L29: Commentaire
B30: Aucun contact dans la base clients CI : à compléter
B32: 2. CE QUI A DÉJÀ ÉTÉ VENDU ET FACTURÉ (historique, encaissements, récurrent / ponctuel)
B33: Produit / service | C33: Partenaire / éditeur | D33: Récurrent / ponctuel | E33: Exercice | F33: Date de facturation | G33: Montant facturé | H33: Coût des ventes | I33: Commission | J33: CA net | K33: Marge | L33: Encaissé | M33: Solde à encaisser | N33: Commentaires
B34: Licences ManageEngine | C34: ManageEngine | D34: Récurrent | E34: 2026 | F34: 46197 | G34: 28766400 | J34: =IF(G34="","",G34-N(I34)) -> 28766400 | K34: =IF(G34="","",J34-N(H34)) -> 28766400 | L34: 28766400 | M34: =IF(G34="","",G34-N(L34)) -> 0 | N34: Soldé. Nouveau client 2026.
J35: =IF(G35="","",G35-N(I35)) | K35: =IF(G35="","",J35-N(H35)) | M35: =IF(G35="","",G35-N(L35))
J36: =IF(G36="","",G36-N(I36)) | K36: =IF(G36="","",J36-N(H36)) | M36: =IF(G36="","",G36-N(L36))
J37: =IF(G37="","",G37-N(I37)) | K37: =IF(G37="","",J37-N(H37)) | M37: =IF(G37="","",G37-N(L37))
B38: TOTAL FACTURÉ (tous exercices) | G38: =SUM(G34:G37) -> 28766400 | H38: =SUM(H34:H37) -> 0 | I38: =SUM(I34:I37) -> 0 | J38: =SUM(J34:J37) -> 28766400 | K38: =SUM(K34:K37) -> 28766400 | L38: =SUM(L34:L37) -> 28766400 | M38: =SUM(M34:M37) -> 0
B39: dont exercice 2026 | G39: =SUMIFS(G34:G37,$E$34:$E$37,2026) -> 28766400 | I39: =SUMIFS(I34:I37,$E$34:$E$37,2026) -> 0 | K39: =SUMIFS(K34:K37,$E$34:$E$37,2026) -> 28766400 | L39: =SUMIFS(L34:L37,$E$34:$E$37,2026) -> 28766400 | M39: =SUMIFS(M34:M37,$E$34:$E$37,2026) -> 0
B41: 3. OFFRES EN COURS / À SUIVRE (envoyées, non encore validées, renouvellements)
B42: Offre / affaire | C42: Partenaire / éditeur | D42: Étape | E42: Date d’envoi | F42: Échéance décision | G42: Montant | H42: Closing | I42: Montant pondéré | J42: Responsable | K42: Prochaine étape | N42: Commentaires
B43: Sécurisation des boîtes mail | C43: ManageEngine | D43: M5 – Négociation / signature | G43: 4500000 | H43: 0.9 | I43: =IF(OR(G43="",H43=""),"",G43*H43) -> 4050000 | J43: Commercial IAT | K43: Vérifier avec la compta si ce montant est inclus dans les 28,8 M facturés ou reste à facturer. | N43: Ligne du pipeline d’origine (fiabilité 90 %, coût des ventes 1 065 000, commission 0) non retrouvée dans la facturation transmise.
B44: Formation sur la solution de sécurisation mail | C44: ManageEngine | D44: M3 – Offre en préparation | I44: =IF(OR(G44="",H44=""),"",G44*H44) | J44: Commercial IAT | K44: Planifier la formation et l’utiliser pour détecter d’autres besoins.
I45: =IF(OR(G45="",H45=""),"",G45*H45)
I46: =IF(OR(G46="",H46=""),"",G46*H46)
B47: TOTAL OFFRES EN COURS | G47: =SUM(G43:G46) -> 4500000 | I47: =SUM(I43:I46) -> 4050000
B49: 4. STRATÉGIE DE CONTINUITÉ ET DE DÉVELOPPEMENT (vente croisée, renouvellement)
B50: Opportunité | C50: Solution / partenaire | D50: Priorité | E50: Échéance | F50: Responsable | G50: Valeur pour le client / action à mener | N50: Commentaires
B51: Vente croisée après le produit d’entrée | C51: ManageEngine / WithSecure / Hornetsecurity | D51: P1 | F51: Commercial IAT | G51: Cartographier l’environnement IT du FER et proposer gestion des services IT, sécurité des postes ou sauvegarde.
B52: Sécuriser le renouvellement 2027 | C52: Licences ManageEngine | D52: P3 | E52: 46472 | F52: Commercial IAT | G52: Point de satisfaction client avant la relance J-90 (26/03/2027).

Sheet NSIA
A1: 0
B2: NSIA — Fiche compte
B3: Client existant IAT | Montants en FCFA | Facturation et encaissements : point comptabilité au 13/10/2026
B4: Cellules jaune pâle = information à compléter · Texte vert = valeur reprise d’un autre onglet
B5: ← Retour à la synthèse
B7: 1. FICHE COMPTE
B8: Secteur | C8: Assurance
B9: Direction générale (recherche du 15/10/2026) | C9: DG : Sonia Nadège Seka (à confirmer) · DGA : Gérard Gilles Akou (confirmé) · Directeur du réseau des particuliers : Jacques Avenie (à confirmer)
B10: Interlocuteur direction (nom / fonction) | C10: Gabriel COMOE-EDANOU — Directeur Des Opérations et de la Technologies Groupe (base clients — coordonnées ci-dessous)
B11: Interlocuteur opérationnel (nom / fonction) | C11: Tyao Basile N'GUESSSAN — Ingénieur Projet ; AMANGOUA Alexandre ; Elvis Adou (base clients)
B12: Achats / marchés
B13: Responsable IAT (lead commercial) | C13: Commercial IAT
B14: Relation haut niveau gérée par
B15: État de santé du compte
B16: Taux de satisfaction (1 à 5)
B17: Dernier contact
B18: Prochain point prévu
B19: Notes (réunion du 13/10/2026 et comptabilité) | C19: Client récurrent depuis 2024 (compta), renouvelle chaque année en septembre. Raisons sociales facturées : NSIA Assurances (2024-2025) puis NSIA Assurances Vie (2026). Figurait comme prospect « NSIA VIE » dans l’ancien pipeline.
B21: DIRIGEANTS — NSIA Vie (Côte d’Ivoire) (recherche web + LinkedIn, données au 15/10/2026)
B22: Fonction | C22: Nom | E22: Fiabilité | F22: Source / remarque
B23: DG | C23: Sonia Nadège Seka | E23: À confirmer | F23: Profil LinkedIn limité, filiale non certifiée : à recouper.
B24: DGA | C24: Gérard Gilles Akou | E24: Confirmé | F24: LinkedIn : DGA NSIA Vie CI (n’est plus directeur commercial).
B25: Directeur du réseau des particuliers | C25: Jacques Avenie | E25: À confirmer | F25: Équivalent le plus proche d’un directeur commercial.
B26: Directeur financier | C26: Richmond Fabrice N’Doua | E26: À confirmer
B27: Directeur études, réassurance et actuariat | C27: Konan Manassé Yao | E27: À confirmer | F27: Interlocuteur clé pour le pitch Credolab Assurance (atelier avec les équipes actuarielles).
B28: DG NSIA Holding Assurances (groupe) | C28: Mansan Dominique Diagou-Ehilé | E28: À confirmer | F28: N’est plus DG de NSIA Vie CI.
B29: DSI | C29: — | E29: Non trouvé | F29: Ancien DSI : Edna Adou Tehia (poste précédent) ; Mohamed Coulibaly n’apparaît plus.
B31: CONTACTS — BASE CLIENTS CI (NSIA Banque, NSIA PARTICIPATION)
B32: Nom | C32: Fonction | E32: Profil | G32: Téléphone | I32: Email | L32: Commentaire
B33: Gabriel COMOE-EDANOU | C33: Directeur Des Opérations et de la Technologies Groupe | E33: Direction SI / digital | G33: 0749595963 | I33: gabriel.comoe-edanou@groupensia.com
B34: Tyao Basile N'GUESSSAN | C34: Ingénieur Projet | E34: Informatique / projets | G34: 0505 89 35 46 | I34: basile.nguessan@groupensia.com
B35: AMANGOUA Alexandre | E35: Non renseigné | G35: 07 88 86 46 22 | I35: alexandre.armangouah@groupensia.com
B36: Elvis Adou | E36: Non renseigné | G36: 0709243281 | I36: elvis.adou@nsiabanque.com
B37: Eric AHUI | E37: Non renseigné | G37: 07 69 28 66 02 | I37: eric.ahui@nsiabanque.com
B38: Francis gnakoury | E38: Non renseigné | G38: 0787530619 | I38: francis.gnakouri@nsiabanque.com
B39: Prosper Yao | E39: Non renseigné | G39: 0708013119 | I39: prosper.yao@groupensia.com
B41: 2. CE QUI A DÉJÀ ÉTÉ VENDU ET FACTURÉ (historique, encaissements, récurrent / ponctuel)
B42: Produit / service | C42: Partenaire / éditeur | D42: Récurrent / ponctuel | E42: Exercice | F42: Date de facturation | G42: Montant facturé | H42: Coût des ventes | I42: Commission | J42: CA net | K42: Marge | L42: Encaissé | M42: Solde à encaisser | N42: Commentaires
B43: Licences ManageEngine | C43: ManageEngine | D43: Récurrent | E43: 2024 | F43: 45560 | G43: 1003000 | J43: =IF(G43="","",G43-N(I43)) -> 1003000 | K43: =IF(G43="","",J43-N(H43)) -> 1003000 | L43: 1003000 | M43: =IF(G43="","",G43-N(L43)) -> 0 | N43: NSIA ASSURANCES — soldé.
B44: Licences ManageEngine | C44: ManageEngine | D44: Récurrent | E44: 2025 | F44: 45905 | G44: 982940 | J44: =IF(G44="","",G44-N(I44)) -> 982940 | K44: =IF(G44="","",J44-N(H44)) -> 982940 | L44: 982940 | M44: =IF(G44="","",G44-N(L44)) -> 0 | N44: Encaissé le 24/09/2025.
B45: Licences ManageEngine (renouvellement) | C45: ManageEngine | D45: Récurrent | E45: 2026 | F45: 46283 | G45: 1610068 | J45: =IF(G45="","",G45-N(I45)) -> 1610068 | K45: =IF(G45="","",J45-N(H45)) -> 1610068 | L45: 1610068 | M45: =IF(G45="","",G45-N(L45)) -> 0 | N45: NSIA ASSURANCES VIE — soldé.
J46: =IF(G46="","",G46-N(I46)) | K46: =IF(G46="","",J46-N(H46)) | M46: =IF(G46="","",G46-N(L46))
J47: =IF(G47="","",G47-N(I47)) | K47: =IF(G47="","",J47-N(H47)) | M47: =IF(G47="","",G47-N(L47))
B48: TOTAL FACTURÉ (tous exercices) | G48: =SUM(G43:G47) -> 3596008 | H48: =SUM(H43:H47) -> 0 | I48: =SUM(I43:I47) -> 0 | J48: =SUM(J43:J47) -> 3596008 | K48: =SUM(K43:K47) -> 3596008 | L48: =SUM(L43:L47) -> 3596008 | M48: =SUM(M43:M47) -> 0
B49: dont exercice 2026 | G49: =SUMIFS(G43:G47,$E$43:$E$47,2026) -> 1610068 | I49: =SUMIFS(I43:I47,$E$43:$E$47,2026) -> 0 | K49: =SUMIFS(K43:K47,$E$43:$E$47,2026) -> 1610068 | L49: =SUMIFS(L43:L47,$E$43:$E$47,2026) -> 1610068 | M49: =SUMIFS(M43:M47,$E$43:$E$47,2026) -> 0
B51: 3. OFFRES EN COURS / À SUIVRE (envoyées, non encore validées, renouvellements)
B52: Offre / affaire | C52: Partenaire / éditeur | D52: Étape | E52: Date d’envoi | F52: Échéance décision | G52: Montant | H52: Closing | I52: Montant pondéré | J52: Responsable | K52: Prochaine étape | N52: Commentaires
I53: =IF(OR(G53="",H53=""),"",G53*H53)
I54: =IF(OR(G54="",H54=""),"",G54*H54)
I55: =IF(OR(G55="",H55=""),"",G55*H55)
I56: =IF(OR(G56="",H56=""),"",G56*H56)
B57: TOTAL OFFRES EN COURS | G57: =SUM(G53:G56) -> 0 | I57: =SUM(I53:I56) -> 0
B59: 4. STRATÉGIE DE CONTINUITÉ ET DE DÉVELOPPEMENT (vente croisée, renouvellement)
B60: Opportunité | C60: Solution / partenaire | D60: Priorité | E60: Échéance | F60: Responsable | G60: Valeur pour le client / action à mener | N60: Commentaires
B61: Développer le compte au-delà des licences | C61: ManageEngine / sécurité | D61: P3 | F61: Commercial IAT | G61: Petit compte (1,6 M) mais fidèle : identifier d’autres entités et besoins au sein du groupe NSIA.

Sheet Orange Business
B2: Orange Business — Fiche compte
B3: Client existant IAT | Montants en FCFA
B4: Cellules jaune pâle = information à compléter · Texte vert = valeur reprise d’un autre onglet
B5: ← Retour à la synthèse
B7: 1. FICHE COMPTE
B8: Secteur | C8: Télécoms / intégrateur (apporteur de deals)
B9: Interlocuteur clé | C9: Abdoul Aïdara (orthographe à confirmer) — centralise les demandes
B10: Autres interlocuteurs | C10: TOURE Sidik — Manager Sécurité Opérationnel ; YOH Landry — Responsable étude et Ingénierie ; AGOLY Franck — Senior Manager Exploitation Applications&Plateformes de Services (base clients)
B11: Achats / marchés | C11: GUIGREHI Franck — Direction des Achats et de la Logistique Acheteur (base clients)
B12: Responsable IAT (lead commercial)
B13: Relation haut niveau gérée par
B14: État de santé du compte | C14: À surveiller
B15: Taux de satisfaction (1 à 5)
B16: Dernier contact
B17: Prochain point prévu
B18: Notes (réunion du 13/10/2026) | C18: Orange Business nous envoyait régulièrement des demandes d’offre ; plus rien depuis un moment : il faut reprendre la main. Suivre tous les deals transmis : gagnés, soumis, perdus. Inclure le projet E-Agri (revenue sharing). Aucune facturation Orange dans le point comptable du 13/10/2026.
B20: CONTACTS — BASE CLIENTS CI (ORANGE)
B21: Nom | C21: Fonction | E21: Profil | G21: Téléphone | I21: Email | L21: Commentaire
B22: Mame DIOP | C22: DSI | E22: Direction SI / digital | G22: 22507799662 | I22: mame.diopba@orange.com | L22: Numéro au format à 8 chiffres (avant 2021) : à mettre à jour
B23: TOURE Sidik | C23: Manager Sécurité Opérationnel | E23: Sécurité SI | G23: 0225 07747835 | I23: sidik.toure@orange.com | L23: Prénom « Sidik » cité en réunion du 13/10 : vraisemblablement ce contact (à confirmer).
B24: YOH Landry | C24: Responsable étude et Ingénierie | E24: Informatique / projets | G24: 00225 09506343 | I24: landry.yoh@orange.com | L24: Prénom « Landry » cité en réunion du 13/10 : vraisemblablement ce contact (à confirmer).
B25: AGOLY Franck | C25: Senior Manager Exploitation Applications&Plateformes de Services | E25: Infrastructure / réseaux | G25: 00225 07012368 | I25: franck.agoly@orange.com | L25: Numéro au format à 8 chiffres (avant 2021) : à mettre à jour
B26: KOUASSI Jean Marc | C26: Chef de Département Core | E26: Infrastructure / réseaux | G26: 22507605444 | I26: jean-marc.kouassi@orange.com | L26: Numéro au format à 8 chiffres (avant 2021) : à mettre à jour
B27: LOPOI David | C27: Senior Manager Reseau IP | E27: Infrastructure / réseaux | G27: 0022507019933 | I27: david.lopoi@orange.com | L27: Numéro au format à 8 chiffres (avant 2021) : à mettre à jour
B28: TEKI Saint-François | C28: Manager Réseau Interne | E28: Infrastructure / réseaux | G28: 022507676606 | I28: saint-francois.teki@orange.com
B29: GUIGREHI Franck | C29: Direction des Achats et de la Logistique Acheteur | E29: Achats / marchés | G29: 0225 78638328 / 0225 21214543 | I29: franck.guigrehi@orange.com
B31: 2. AFFAIRES GAGNÉES / EN EXPLOITATION
B32: Produit / service | C32: Partenaire / éditeur | D32: Récurrent / ponctuel | E32: Exercice | F32: Date de facturation | G32: Montant facturé | H32: Coût des ventes | I32: Commission | J32: CA net | K32: Marge | L32: Encaissé | M32: Solde à encaisser | N32: Commentaires
B33: Plateforme E-Agri (commercialisation de produits vivriers) | C33: Partenaires de développement | D33: Récurrent | J33: =IF(G33="","",G33-N(I33)) | K33: =IF(G33="","",J33-N(H33)) | M33: =IF(G33="","",G33-N(L33)) | N33: Contrat de réalisation de la plateforme + revenue sharing avec Orange une fois en exploitation. Montant, facturation et avancement à compléter.
J34: =IF(G34="","",G34-N(I34)) | K34: =IF(G34="","",J34-N(H34)) | M34: =IF(G34="","",G34-N(L34))
J35: =IF(G35="","",G35-N(I35)) | K35: =IF(G35="","",J35-N(H35)) | M35: =IF(G35="","",G35-N(L35))
J36: =IF(G36="","",G36-N(I36)) | K36: =IF(G36="","",J36-N(H36)) | M36: =IF(G36="","",G36-N(L36))
B37: TOTAL FACTURÉ (tous exercices) | G37: =SUM(G33:G36) -> 0 | H37: =SUM(H33:H36) -> 0 | I37: =SUM(I33:I36) -> 0 | J37: =SUM(J33:J36) -> 0 | K37: =SUM(K33:K36) -> 0 | L37: =SUM(L33:L36) -> 0 | M37: =SUM(M33:M36) -> 0
B38: dont exercice 2026 | G38: =SUMIFS(G33:G36,$E$33:$E$36,2026) -> 0 | I38: =SUMIFS(I33:I36,$E$33:$E$36,2026) -> 0 | K38: =SUMIFS(K33:K36,$E$33:$E$36,2026) -> 0 | L38: =SUMIFS(L33:L36,$E$33:$E$36,2026) -> 0 | M38: =SUMIFS(M33:M36,$E$33:$E$36,2026) -> 0
B40: 3. DEALS TRANSMIS PAR ORANGE BUSINESS (en cours, soumis, perdus)
B41: Offre / affaire | C41: Partenaire / éditeur | D41: Étape | E41: Date d’envoi | F41: Échéance décision | G41: Montant | H41: Closing | I41: Montant pondéré | J41: Responsable | K41: Prochaine étape | N41: Commentaires
B42: Orange Burkina — Migration Microsoft Exchange | C42: Microsoft — via OC²S | D42: M5 – Négociation / signature | G42: 41135000 | H42: 0.6 | I42: =IF(OR(G42="",H42=""),"",G42*H42) -> 24681000 | J42: À confirmer | K42: Fixer une date de décision avec Judicaël KOUTOU · identifier le décideur final. | N42: Offre remise depuis plus de 2 mois.
B43: Orange Liberia — Audit SAM | C43: Via OC²S | D43: M5 – Négociation / signature | G43: 23000000 | H43: 0.6 | I43: =IF(OR(G43="",H43=""),"",G43*H43) -> 13800000 | J43: À confirmer | K43: Traiter dans la même séquence de relance que le Burkina. | N43: Affaire jumelle du dossier Orange Burkina.
I44: =IF(OR(G44="",H44=""),"",G44*H44)
I45: =IF(OR(G45="",H45=""),"",G45*H45)
B46: TOTAL OFFRES EN COURS | G46: =SUM(G42:G45) -> 64135000 | I46: =SUM(I42:I45) -> 38481000
B48: 4. STRATÉGIE DE CONTINUITÉ ET DE DÉVELOPPEMENT (vente croisée, renouvellement)
B49: Opportunité | C49: Solution / partenaire | D49: Priorité | E49: Échéance | F49: Responsable | G49: Valeur pour le client / action à mener | N49: Commentaires
B50: Réactiver le flux de demandes d’offres | C50: Toutes solutions | D50: P1 | F50: Commercial IAT | G50: Reprendre contact avec l’interlocuteur clé, faire le point sur les deals en cours et perdus, se repositionner.
B51: Historique des deals perdus | C51: — | D51: P2 | F51: Commercial IAT | G51: Lister les deals soumis puis perdus (étape « Perdu ») pour comprendre les raisons et ajuster les offres.

Sheet NEURONES
B2: NEURONES — Fiche compte
B3: Partenaire revendeur | Montants en FCFA | Facturation et encaissements : point comptabilité au 13/10/2026
B4: Cellules jaune pâle = information à compléter · Texte vert = valeur reprise d’un autre onglet
B5: ← Retour à la synthèse
B7: 1. FICHE COMPTE
B8: Secteur | C8: Intégrateur / ESN (partenaire revendeur)
B9: Direction générale (recherche du 15/10/2026) | C9: PDG : Luc de Chammard (confirmé) · DG délégué : Bertrand Ducurtil (à confirmer) · Directeur marketing et communication : Matthieu Vautier (à confirmer)
B10: Interlocuteur direction (nom / fonction)
B11: Interlocuteur opérationnel (nom / fonction)
B12: Responsable IAT (lead commercial) | C12: Commercial IAT
B13: Relation haut niveau gérée par
B14: État de santé du compte
B15: Taux de satisfaction (1 à 5)
B16: Dernier contact
B17: Prochain point prévu
B18: Notes (réunion du 13/10/2026 et comptabilité) | C18: NEURONES passe par IAT pour vendre WithSecure, car IAT détient la carte partenaire. Renouvellement échu depuis le 21/08/2026 : blocage côté fournisseur (attente de cotation). Pousser aussi la carte en direct, sinon l’éditeur risque de la retirer.
B20: DIRIGEANTS — NEURONES (groupe, France) (recherche web + LinkedIn, données au 15/10/2026)
B21: Fonction | C21: Nom | E21: Fiabilité | F21: Source / remarque
B22: PDG | C22: Luc de Chammard | E22: Confirmé | F22: LinkedIn + AMF.
B23: DG délégué | C23: Bertrand Ducurtil | E23: À confirmer | F23: Déclarations AMF ; non revérifié sur LinkedIn.
B24: Directeur marketing et communication | C24: Matthieu Vautier | E24: À confirmer
B25: DSI | C25: — | E25: Non trouvé
B26: Directeur commercial | C26: — | E26: Non trouvé | F26: Groupe organisé en filiales ayant chacune leur DG.
B27: ⚠ Recherche menée sur le groupe français NEURONES : vérifier que le partenaire revendeur d’Abidjan en fait bien partie (le groupe est organisé en filiales ayant chacune leur DG).
B29: CONTACTS — BASE CLIENTS CI (aucun contact trouvé)
B30: Nom | C30: Fonction | E30: Profil | G30: Téléphone | I30: Email | L30: Commentaire
B31: Aucun contact dans la base clients CI : à compléter
B33: 2. CE QUI A DÉJÀ ÉTÉ VENDU ET FACTURÉ (historique, encaissements, récurrent / ponctuel)
B34: Produit / service | C34: Partenaire / éditeur | D34: Récurrent / ponctuel | E34: Exercice | F34: Date de facturation | G34: Montant facturé | H34: Coût des ventes | I34: Commission | J34: CA net | K34: Marge | L34: Encaissé | M34: Solde à encaisser | N34: Commentaires
B35: Licence WithSecure | C35: WithSecure | D35: Récurrent | E35: 2025 | F35: 45890 | G35: 7383000 | H35: 4578000 | I35: 655000 | J35: =IF(G35="","",G35-N(I35)) -> 6728000 | K35: =IF(G35="","",J35-N(H35)) -> 2150000 | L35: 7383000 | M35: =IF(G35="","",G35-N(L35)) -> 0 | N35: Encaissé en 3 fois (27/08, 14/11, 02/12/2025). Coût des ventes et commission repris du pipeline d’origine.
J36: =IF(G36="","",G36-N(I36)) | K36: =IF(G36="","",J36-N(H36)) | M36: =IF(G36="","",G36-N(L36))
J37: =IF(G37="","",G37-N(I37)) | K37: =IF(G37="","",J37-N(H37)) | M37: =IF(G37="","",G37-N(L37))
J38: =IF(G38="","",G38-N(I38)) | K38: =IF(G38="","",J38-N(H38)) | M38: =IF(G38="","",G38-N(L38))
B39: TOTAL FACTURÉ (tous exercices) | G39: =SUM(G35:G38) -> 7383000 | H39: =SUM(H35:H38) -> 4578000 | I39: =SUM(I35:I38) -> 655000 | J39: =SUM(J35:J38) -> 6728000 | K39: =SUM(K35:K38) -> 2150000 | L39: =SUM(L35:L38) -> 7383000 | M39: =SUM(M35:M38) -> 0
B40: dont exercice 2026 | G40: =SUMIFS(G35:G38,$E$35:$E$38,2026) -> 0 | I40: =SUMIFS(I35:I38,$E$35:$E$38,2026) -> 0 | K40: =SUMIFS(K35:K38,$E$35:$E$38,2026) -> 0 | L40: =SUMIFS(L35:L38,$E$35:$E$38,2026) -> 0 | M40: =SUMIFS(M35:M38,$E$35:$E$38,2026) -> 0
B42: 3. OFFRES EN COURS / À SUIVRE (envoyées, non encore validées, renouvellements)
B43: Offre / affaire | C43: Partenaire / éditeur | D43: Étape | E43: Date d’envoi | F43: Échéance décision | G43: Montant | H43: Closing | I43: Montant pondéré | J43: Responsable | K43: Prochaine étape | N43: Commentaires
B44: Renouvellement licence WithSecure 2026 | C44: WithSecure | D44: M3 – Offre en préparation | F44: 46309 | I44: =IF(OR(G44="",H44=""),"",G44*H44) | J44: Commercial IAT | K44: Relancer le fournisseur pour la cotation, puis émettre l’offre client. | N44: Échéance dépassée (21/08/2026). Montant non chiffré ; base 2025 : 7 383 000.
I45: =IF(OR(G45="",H45=""),"",G45*H45)
I46: =IF(OR(G46="",H46=""),"",G46*H46)
I47: =IF(OR(G47="",H47=""),"",G47*H47)
B48: TOTAL OFFRES EN COURS | G48: =SUM(G44:G47) -> 0 | I48: =SUM(I44:I47) -> 0
B50: 4. STRATÉGIE DE CONTINUITÉ ET DE DÉVELOPPEMENT (vente croisée, renouvellement)
B51: Opportunité | C51: Solution / partenaire | D51: Priorité | E51: Échéance | F51: Responsable | G51: Valeur pour le client / action à mener | N51: Commentaires
B52: Développer le volume WithSecure via NEURONES | C52: WithSecure | D52: P2 | F52: Commercial IAT | G52: Point trimestriel avec NEURONES sur leurs affaires à venir.

Sheet Appels d’offres
B2: IAT — Appels d’offres
B3: Suivi des appels d’offres et consultations | Montants en FCFA
B4: Jours restants calculés automatiquement · rouge = moins de 7 jours
B5: ← Retour à la synthèse
B7: APPELS D’OFFRES EN COURS ET EN VEILLE
B8: N° | C8: Organisme | D8: Objet | E8: Référence AO | F8: Date de publication | G8: Date limite de dépôt | H8: Jours restants | I8: Montant estimé (FCFA) | J8: Mode de réponse | K8: Partenaire(s) | L8: Pièces / exigences | M8: Étape AO | N8: Responsable | O8: Commentaires
B9: 1 | C9: Le Médiateur de la République de Côte d’Ivoire (à valider) | D9: Plateforme e-Médiation | H9: =IF(G9="","",G9-TODAY()) | J9: Groupement / sous-traitance (à confirmer) | K9: OC²S | L9: Entité porteuse, montant, calendrier et pièces attendues à compléter | M9: Go / No-go | N9: À confirmer | O9: Repris du pipeline (ligne « OCCS EMEDIATION » sans données). Confirmer le rôle d’OC²S et formaliser l’accord de groupement.
B10: 2 | C10: CDC-CI (Caisse des Dépôts et Consignations) | D10: Digitalisation des processus et gestion documentaire | H10: =IF(G10="","",G10-TODAY()) | M10: Veille | N10: Commercial IAT | O10: Aucun AO ouvert identifié : surveiller les avis et manifestations d’intérêt, vérifier critères d’éligibilité.
B11: =IF(C11="","",ROW()-8) | H11: =IF(G11="","",G11-TODAY())
B12: =IF(C12="","",ROW()-8) | H12: =IF(G12="","",G12-TODAY())
B13: =IF(C13="","",ROW()-8) | H13: =IF(G13="","",G13-TODAY())
B14: =IF(C14="","",ROW()-8) | H14: =IF(G14="","",G14-TODAY())
B15: =IF(C15="","",ROW()-8) | H15: =IF(G15="","",G15-TODAY())
B16: =IF(C16="","",ROW()-8) | H16: =IF(G16="","",G16-TODAY())
B17: =IF(C17="","",ROW()-8) | H17: =IF(G17="","",G17-TODAY())
B18: =IF(C18="","",ROW()-8) | H18: =IF(G18="","",G18-TODAY())
B19: =IF(C19="","",ROW()-8) | H19: =IF(G19="","",G19-TODAY())
B20: =IF(C20="","",ROW()-8) | H20: =IF(G20="","",G20-TODAY())
B21: TOTAL | I21: =SUM(I9:I20) -> 0

Sheet Solutions & prospects
B2: IAT — Solutions & prospects
B3: Stratégie par produit : ce qu’on vend, à qui, avec quel argument, et la liste des prospects par solution
B4: On ne vend pas ce qu’on ne maîtrise pas : colonne « Maîtrise commerciale » à mettre à jour après chaque formation
B5: ← Retour à la synthèse
B7: 1. CATALOGUE ET STRATÉGIE PAR SOLUTION
B8: Solution | C8: Éditeur / partenaire | D8: Catégorie | E8: Statut du partenariat | F8: Référent / expert interne | G8: Maîtrise commerciale | H8: Cibles sectorielles | I8: Problème adressé / valeur (pitch) | J8: Clients existants | K8: Supports disponibles | L8: Priorité | M8: Prochaine action
B9: Credolab | C9: Credolab (« Infinity powered by Credolab ») | D9: Scoring comportemental / anti-fraude / KYC | E9: Signé (juin 2026) | G9: À former | H9: Banques commerciales, assurance, fintech & télécoms, institutions gouvernementales, microfinance (SFD) — Côte d’Ivoire et Afrique de l’Ouest francophone | I9: Scoring comportemental zéro PII (11 M+ caractéristiques, < 200 ms) · +40 % de pouvoir prédictif · −21,9 % de coût du risque · Gini 92 contre les bots · maîtrise locale IAT (conformité BCEAO / OHADA). Pitchs détaillés par segment en section 3. | J9: Aucun à ce jour | K9: Pitchs ciblés par segment (juillet 2026) · document d’approche · éléments d’Olivier à intégrer | L9: P1 | M9: Lancer le pilote avec Credit Access (candidat idéal) · attaquer un prospect par semaine selon le calendrier (section 2) · revenir sur le dossier du 08/10
B10: Wari+ | C10: Daniel (éditeur) — partenariat à signer | D10: Plateforme front-office d’investissement (marque blanche) | E10: En négociation | G10: À former | H10: SGI, banques (BOA, BNI…) | I10: Produit prêt et déjà utilisé par des SGI ; IAT fournit la technologie, adossée à un acteur agréé. | K10: Démo interactive (sandbox) sur écrans tactiles 27" au Salon de l’Épargne | L10: P1 | M10: Signer un partenariat de commercialisation (revenue sharing, prix plancher 45 M) avant le salon du 22/10
B11: ManageEngine | C11: ManageEngine | D11: Gestion des services IT, endpoint, sécurité | E11: Partenaire signé | F11: Salim, Kade (formés) | G11: À former | H11: Administrations, organismes sociaux, grandes entreprises | I11: Pilotage et sécurisation du parc IT, support, gestion des licences. | J11: CNAM, CNPS, FER | K11: Brochures ManageEngine | L11: P1 | M11: Présentation complète de l’offre au commercial par Salim / Kade · cartographier les ventes croisées
B12: WithSecure | C12: WithSecure | D12: Sécurité des postes (endpoint) | E12: Partenaire (carte détenue par IAT) | G12: À former | H12: Entreprises, intégrateurs | I12: Protection des postes de travail. | J12: NEURONES (revendeur) | K12: Brochure IAT | L12: P2 | M12: Pousser la carte en direct pour ne pas risquer de la perdre
B13: Hornetsecurity | C13: Hornetsecurity | D13: Sécurité messagerie / sauvegarde M365 | E13: Partenaire | G13: À former | H13: Entreprises sous Microsoft 365 | I13: Sécurisation et sauvegarde de la messagerie. | K13: Brochure IAT | L13: P2 | M13: Identifier les personnes clés chez l’éditeur (call avec Maoula)
B14: Fortinet | C14: Fortinet | D14: Sécurité réseau | E14: À confirmer | G14: À former | L14: P3 | M14: Vérifier qui représente Fortinet et qui fait les configurations
B15: Acronis | C15: Acronis | D15: Sauvegarde | E15: Via prestataires externes | G15: À former | L15: P3 | M15: Confirmer le modèle de délivrance
B16: Huawei | C16: Huawei | D16: Infrastructure | E16: Partenaire enregistré | F16: Direction générale | G16: À former | L16: P2 | M16: Faire connaître le partenariat (site web, brochure)
B17: Microsoft 365 / Exchange | C17: Microsoft — via OC²S | D17: Messagerie et collaboration | E17: Via partenaire | G17: À former | H17: Telcos, grandes entreprises | J17: Orange Burkina (en cours) | L17: P2
B18: Odoo | C18: Odoo Community | D18: ERP / CRM | G18: À former | H18: PME, groupes multi-filiales | L18: P3
B19: Gestion de flotte | C19: Éditeur partenaire (nom à préciser) | D19: Télématique (boîtier + 4G + plateforme) | E19: En évaluation | G19: À former | H19: Administrations et entreprises à grand parc automobile | I19: Suivi des véhicules, alertes d’échéances (visite technique, etc.). | L19: P2 | M19: Tests sur les véhicules de l’entreprise avant toute offre
B20: Développement sur mesure / digitalisation | C20: IAT | D20: Digitalisation des processus | E20: — | G20: Maîtrisé | H20: Distribution, groupes | I20: Supprimer la saisie manuelle et fiabiliser les processus. | J20: Projet digitalisation (client à préciser) | L20: P1 | M20: Transformer le développement en produit réutilisable
B22: 2. PROSPECTS PAR SOLUTION (objectif : au moins un prospect attaqué par semaine — calendrier Credolab proposé, à valider)
B23: Solution | C23: Prospect | D23: Secteur | E23: Contact / fonction | F23: Angle d’attaque / besoin | G23: Étape | H23: Semaine d’attaque | I23: Prochaine action | J23: Responsable | K23: Relation IAG (/5) | L23: Dernière action (date) | M23: Commentaires
B24: Credolab | C24: Credit Access | D24: Microfinance (SFD) | F24: La fraude des agents est le premier facteur de perte : passer du scoring manuel au scoring automatisé (−43 % de fraude dans des cas similaires). | G24: M0 – À qualifier | H24: 46314 | I24: Proposer un pilote (preuve de concept) avant extension aux autres SFD. | J24: Commercial IAT | K24: 5 | M24: 8,5 % des crédits du marché, très forte croissance digitale — candidat idéal pour le pilote.
B25: Credolab | C25: BNI | D25: Banque | E25: Noufe — DSI · 07 07620719 · anoufe@bni.ci (+6 autres dans l’onglet Contacts) | F25: Thin-files (bancarisation de 24,3 %) et fraude à l’identité (81 % du secteur) : +40 % de pouvoir prédictif sans changer le process de décision, −21,9 % de coût du risque. | G25: M0 – À qualifier | H25: 46321 | I25: Proposer un pilote sandbox de 4 à 6 semaines sur un segment de portefeuille (crédit PME ou retail). | J25: Commercial IAT | K25: 5 | M25: Banque Nationale d’Investissement — actifs > 700 Mds FCFA, partenaire clé de l’État. À approcher aussi au Salon de l’Épargne (22-23/10).
B26: Credolab | C26: Orange CI / Orange Bank | D26: Fintech / Télécom | E26: Mame DIOP — DSI · 22507799662 · mame.diopba@orange.com (+7 autres dans l’onglet Contacts) | F26: Fraude en temps réel (< 200 ms), Gini 92 contre les bots et fermes d’appareils, intégration SDK/API rapide, modèle de revenus au volume. | G26: M0 – À qualifier | H26: 46328 | I26: Test sandbox SDK/API sur un flux à risque (onboarding, crédit instantané ou paiement). | J26: Commercial IAT | K26: 5 | M26: Opérateur dominant, partenariat existant très fort avec IAG (voir onglet Orange Business).
B27: Credolab | C27: NSIA | D27: Assurance | E27: NSIA PARTICIPATION : Gabriel COMOE-EDANOU — Directeur Des Opérations et de la Technologies Groupe · 0749595963 · gabriel.comoe-edanou@groupensia.com (+2 autres dans l’onglet Contacts) NSIA Banque : AMANGOUA Alexandre · 07 88 86 46 22 · alexandre.armangouah@groupensia.com (+3 autres dans l’onglet Contacts) | F27: Tarifer les assurés sans historique et détecter la fraude à la souscription ou au sinistre. | G27: M0 – À qualifier | H27: 46335 | I27: Atelier de cadrage avec les équipes actuarielles et anti-fraude : 1 à 2 cas d’usage pilotes. | J27: Commercial IAT | M27: Client existant IAT (licences ManageEngine) : vente croisée. Profil et relation à qualifier selon le pitch.
B28: Credolab | C28: AEJ (Agence Emploi Jeunes) | D28: Institution publique | F28: Scoring alternatif de bénéficiaires non bancarisés et détection de la fraude documentaire / d’identité sur de gros volumes ; décisions auditables (BCEAO, OHADA). | G28: M0 – À qualifier | H28: 46342 | I28: Présenter un cas d’usage chiffré sur un programme en cours et proposer un pilote sur une cohorte. | J28: Commercial IAT | K28: 4 | M28: 800 000 bénéficiaires ciblés, budget 606 M USD, micro-crédits entreprises.
B29: Credolab | C29: Ecobank CI | D29: Banque | E29: Désiré OULAI — DSI · + 225 07 09 21 95 · doulai@ecobank.com (+4 autres dans l’onglet Contacts) | F29: Thin-files (bancarisation de 24,3 %) et fraude à l’identité (81 % du secteur) : +40 % de pouvoir prédictif sans changer le process de décision, −21,9 % de coût du risque. | G29: M0 – À qualifier | H29: 46349 | I29: Proposer un pilote sandbox de 4 à 6 semaines sur un segment de portefeuille (crédit PME ou retail). | J29: Commercial IAT | K29: 4 | M29: Actifs > 1 200 Mds FCFA, leader panafricain.
B30: Credolab | C30: Wave | D30: Fintech / Télécom | F30: Fraude en temps réel (< 200 ms), Gini 92 contre les bots et fermes d’appareils, intégration SDK/API rapide, modèle de revenus au volume. | G30: M0 – À qualifier | H30: 46356 | I30: Test sandbox SDK/API sur un flux à risque (onboarding, crédit instantané ou paiement). | J30: Commercial IAT | K30: 4 | M30: Disrupteur du mobile money, expansion rapide vers le crédit.
B31: Credolab | C31: Djamo | D31: Fintech / Télécom | F31: Fraude en temps réel (< 200 ms), Gini 92 contre les bots et fermes d’appareils, intégration SDK/API rapide, modèle de revenus au volume. | G31: M0 – À qualifier | H31: 46363 | I31: Test sandbox SDK/API sur un flux à risque (onboarding, crédit instantané ou paiement). | J31: Commercial IAT | K31: 4 | M31: Néo-banque leader, première fintech avec agrément microfinance BCEAO (2025).
B32: Credolab | C32: Cofina CI | D32: Microfinance (SFD) | E32: Emany kitsoukou — DSI · +225 47639495 · emanny.kitsoukou@cofinacorp.com (+6 autres dans l’onglet Contacts) | F32: La fraude des agents est le premier facteur de perte : passer du scoring manuel au scoring automatisé (−43 % de fraude dans des cas similaires). | G32: M0 – À qualifier | H32: 46370 | I32: Proposer un pilote (preuve de concept) avant extension aux autres SFD. | J32: Commercial IAT | K32: 4 | M32: Leader de la méso-finance (~10 % des crédits), actifs > 87 Mds FCFA. Écrit « Confina CI » dans le pitch.
B33: Credolab | C33: Bridge Bank Group CI | D33: Banque | E33: Mme KOUASSI — Acheteur · 01 40 14 87 03 (+3 autres dans l’onglet Contacts) | F33: Thin-files (bancarisation de 24,3 %) et fraude à l’identité (81 % du secteur) : +40 % de pouvoir prédictif sans changer le process de décision, −21,9 % de coût du risque. | G33: M0 – À qualifier | H33: 46377 | I33: Proposer un pilote sandbox de 4 à 6 semaines sur un segment de portefeuille (crédit PME ou retail). | J33: Commercial IAT | K33: 4 | M33: Actifs > 350 Mds FCFA, focus PME et innovation.
B34: Credolab | C34: Fin’Elle | D34: Microfinance (SFD) | E34: Lolomba KONE — Head of IT · 225 07 87 90 57 84 · lolamba.kone@cofinacorp.com (+1 autre dans l’onglet Contacts) | F34: La fraude des agents est le premier facteur de perte : passer du scoring manuel au scoring automatisé (−43 % de fraude dans des cas similaires). | G34: M0 – À qualifier | H34: 46391 | I34: Proposer un pilote (preuve de concept) avant extension aux autres SFD. | J34: Commercial IAT | K34: 4 | M34: Niche de l’inclusion financière des femmes (alignement avec le FAFCI).
B35: Credolab | C35: BICICI / Afrika Bank CI | D35: Banque | F35: Thin-files (bancarisation de 24,3 %) et fraude à l’identité (81 % du secteur) : +40 % de pouvoir prédictif sans changer le process de décision, −21,9 % de coût du risque. | G35: M0 – À qualifier | H35: 46398 | I35: Proposer un pilote sandbox de 4 à 6 semaines sur un segment de portefeuille (crédit PME ou retail). | J35: Commercial IAT | K35: 4 | M35: Fortes présences corporate et retail.
B36: Credolab | C36: FAFCI | D36: Institution publique | F36: Scoring alternatif de bénéficiaires non bancarisés et détection de la fraude documentaire / d’identité sur de gros volumes ; décisions auditables (BCEAO, OHADA). | G36: M0 – À qualifier | H36: 46405 | I36: Présenter un cas d’usage chiffré sur un programme en cours et proposer un pilote sur une cohorte. | J36: Commercial IAT | K36: 3 | M36: Plus de 420 000 femmes financées, 98 % de remboursement, distribution via SFD.
B37: Credolab | C37: Programme DICEFA | D37: Institution publique | F37: Scoring alternatif de bénéficiaires non bancarisés et détection de la fraude documentaire / d’identité sur de gros volumes ; décisions auditables (BCEAO, OHADA). | G37: M0 – À qualifier | H37: 46412 | I37: Présenter un cas d’usage chiffré sur un programme en cours et proposer un pilote sur une cohorte. | J37: Commercial IAT | K37: 3 | M37: Lancé en septembre 2025 : 28,5 Mds FCFA sur 5 ans. Cas d’usage chiffré à préparer.
B38: Credolab | C38: FIDEN | D38: Institution publique | F38: Scoring alternatif de bénéficiaires non bancarisés et détection de la fraude documentaire / d’identité sur de gros volumes ; décisions auditables (BCEAO, OHADA). | G38: M0 – À qualifier | H38: 46419 | I38: Présenter un cas d’usage chiffré sur un programme en cours et proposer un pilote sur une cohorte. | J38: Commercial IAT | K38: 3 | M38: Fonds d’État pour le financement des PME.
B39: Credolab | C39: Moov Africa / CinetPay | D39: Fintech / Télécom | E39: AGNIN Yao Jules — Chef de Division Ingénierie · 00225 01000914 · yaojules.agnin@moov.com (+2 autres dans l’onglet Contacts) | F39: Fraude en temps réel (< 200 ms), Gini 92 contre les bots et fermes d’appareils, intégration SDK/API rapide, modèle de revenus au volume. | G39: M0 – À qualifier | H39: 46426 | I39: Test sandbox SDK/API sur un flux à risque (onboarding, crédit instantané ou paiement). | J39: Commercial IAT | K39: 3 | M39: Acteurs majeurs des paiements à sécuriser après incidents (cyberattaque CinetPay de 1,2 M€ en 2025).
B40: Credolab | C40: UNACOOPEC-CI / Baobab / Advans | D40: Microfinance (SFD) | E40: BAOBAB : Wilson KOUAKOU — RI · 0554876179 · tkouakou@baobabgroup.com (+2 autres dans l’onglet Contacts) ADVANS : Héloïse TROUILLEZ — Chargée de projets digitaux · 05 45.55.52.47 · htrouillez@advanscotedivoire.com (+4 autres dans l’onglet Contacts) | F40: La fraude des agents est le premier facteur de perte : passer du scoring manuel au scoring automatisé (−43 % de fraude dans des cas similaires). | G40: M0 – À qualifier | H40: 46433 | I40: Proposer un pilote (preuve de concept) avant extension aux autres SFD. | J40: Commercial IAT | K40: 3 | M40: Leaders en volume de clients et d’agences.
B41: Credolab | C41: AXA | D41: Assurance | E41: AMANI BORRO — Resp Informatique · +225 07016476 · amani.borro@axa.ci (+1 autre dans l’onglet Contacts) | F41: Tarifer les assurés sans historique et détecter la fraude à la souscription ou au sinistre. | G41: M0 – À qualifier | H41: 46440 | I41: Atelier de cadrage avec les équipes actuarielles et anti-fraude : 1 à 2 cas d’usage pilotes. | J41: Commercial IAT | M41: Profil et niveau de relation à qualifier.
B42: Credolab | C42: SUNU | D42: Assurance | E42: Felix Adou · 05381644 · felix.adou@sunu-group.com (+2 autres dans l’onglet Contacts) | F42: Tarifer les assurés sans historique et détecter la fraude à la souscription ou au sinistre. | G42: M0 – À qualifier | H42: 46447 | I42: Atelier de cadrage avec les équipes actuarielles et anti-fraude : 1 à 2 cas d’usage pilotes. | J42: Commercial IAT | M42: Profil et niveau de relation à qualifier.
B43: Credolab | C43: GT BANK | D43: Banque | E43: Innocent AKA — IT · 0759495233 · innocent.aka@gtbank.com (+1 autre dans l’onglet Contacts) | F43: Thin-files (bancarisation de 24,3 %) et fraude à l’identité (81 % du secteur) : +40 % de pouvoir prédictif sans changer le process de décision, −21,9 % de coût du risque. | G43: M0 – À qualifier | I43: Proposer un pilote sandbox de 4 à 6 semaines sur un segment de portefeuille (crédit PME ou retail). | J43: Commercial IAT | M43: Cible complémentaire issue de la base clients CI (non citée dans le pitch) — 2 contact(s). À prioriser.
B44: Credolab | C44: SGCI | D44: Banque | E44: DIAKITE-TOURE · 0585000265 · mariethou.diakite-toure@socgen.com (+5 autres dans l’onglet Contacts) | F44: Thin-files (bancarisation de 24,3 %) et fraude à l’identité (81 % du secteur) : +40 % de pouvoir prédictif sans changer le process de décision, −21,9 % de coût du risque. | G44: M0 – À qualifier | I44: Proposer un pilote sandbox de 4 à 6 semaines sur un segment de portefeuille (crédit PME ou retail). | J44: Commercial IAT | M44: Cible complémentaire issue de la base clients CI (non citée dans le pitch) — 6 contact(s). À prioriser.
B45: Credolab | C45: SIB | D45: Banque | E45: Catherine DADY · 07 57 080684 · catherine.dadi@sib.ci (+6 autres dans l’onglet Contacts) | F45: Thin-files (bancarisation de 24,3 %) et fraude à l’identité (81 % du secteur) : +40 % de pouvoir prédictif sans changer le process de décision, −21,9 % de coût du risque. | G45: M0 – À qualifier | I45: Proposer un pilote sandbox de 4 à 6 semaines sur un segment de portefeuille (crédit PME ou retail). | J45: Commercial IAT | M45: Cible complémentaire issue de la base clients CI (non citée dans le pitch) — 7 contact(s). À prioriser.
B46: Credolab | C46: CORIS BANK | D46: Banque | E46: Omar Somtore — DSI · 0546636671 · osomtore@coris-bank.com (+3 autres dans l’onglet Contacts) | F46: Thin-files (bancarisation de 24,3 %) et fraude à l’identité (81 % du secteur) : +40 % de pouvoir prédictif sans changer le process de décision, −21,9 % de coût du risque. | G46: M0 – À qualifier | I46: Proposer un pilote sandbox de 4 à 6 semaines sur un segment de portefeuille (crédit PME ou retail). | J46: Commercial IAT | M46: Cible complémentaire issue de la base clients CI (non citée dans le pitch) — 4 contact(s). À prioriser.
B47: Credolab | C47: BSIC | D47: Banque | E47: Dara Paul · 67 76 61 86 · paul.dara@bsic.ci (+3 autres dans l’onglet Contacts) | F47: Thin-files (bancarisation de 24,3 %) et fraude à l’identité (81 % du secteur) : +40 % de pouvoir prédictif sans changer le process de décision, −21,9 % de coût du risque. | G47: M0 – À qualifier | I47: Proposer un pilote sandbox de 4 à 6 semaines sur un segment de portefeuille (crédit PME ou retail). | J47: Commercial IAT | M47: Cible complémentaire issue de la base clients CI (non citée dans le pitch) — 4 contact(s). À prioriser.
B48: Credolab | C48: VERSUS BANK | D48: Banque | E48: EDDY ESSO — DSI · 0708088791 / 0151716092 · edi.esso@versusbank.com (+4 autres dans l’onglet Contacts) | F48: Thin-files (bancarisation de 24,3 %) et fraude à l’identité (81 % du secteur) : +40 % de pouvoir prédictif sans changer le process de décision, −21,9 % de coût du risque. | G48: M0 – À qualifier | I48: Proposer un pilote sandbox de 4 à 6 semaines sur un segment de portefeuille (crédit PME ou retail). | J48: Commercial IAT | M48: Cible complémentaire issue de la base clients CI (non citée dans le pitch) — 5 contact(s). À prioriser.
B49: Credolab | C49: ORABANK CI | D49: Banque | E49: SANOGO OUSMANE · 05 75 75 98 75 · ousmane.sanogo@orabank.net (+1 autre dans l’onglet Contacts) | F49: Thin-files (bancarisation de 24,3 %) et fraude à l’identité (81 % du secteur) : +40 % de pouvoir prédictif sans changer le process de décision, −21,9 % de coût du risque. | G49: M0 – À qualifier | I49: Proposer un pilote sandbox de 4 à 6 semaines sur un segment de portefeuille (crédit PME ou retail). | J49: Commercial IAT | M49: Cible complémentaire issue de la base clients CI (non citée dans le pitch) — 2 contact(s). À prioriser.
B50: Credolab | C50: MANSA BANK | D50: Banque | E50: Fabrice Hauhouot · 47930350 · fabrice.hauhouot@mansabank.com (+2 autres dans l’onglet Contacts) | F50: Thin-files (bancarisation de 24,3 %) et fraude à l’identité (81 % du secteur) : +40 % de pouvoir prédictif sans changer le process de décision, −21,9 % de coût du risque. | G50: M0 – À qualifier | I50: Proposer un pilote sandbox de 4 à 6 semaines sur un segment de portefeuille (crédit PME ou retail). | J50: Commercial IAT | M50: Cible complémentaire issue de la base clients CI (non citée dans le pitch) — 3 contact(s). À prioriser.
B51: Credolab | C51: BGFI BANK CI | D51: Banque | E51: Moussa TOURE · 07 58 51 30 12 · m.toure@bgfigroupe.com (+1 autre dans l’onglet Contacts) | F51: Thin-files (bancarisation de 24,3 %) et fraude à l’identité (81 % du secteur) : +40 % de pouvoir prédictif sans changer le process de décision, −21,9 % de coût du risque. | G51: M0 – À qualifier | I51: Proposer un pilote sandbox de 4 à 6 semaines sur un segment de portefeuille (crédit PME ou retail). | J51: Commercial IAT | M51: Cible complémentaire issue de la base clients CI (non citée dans le pitch) — 2 contact(s). À prioriser.
B52: Credolab | C52: ABI & banque Atlantique | D52: Banque | E52: Miloud — DSSI ABI · +225 03 70 70 71 · miloud.chennaoui@banqueatlantique.net (+6 autres dans l’onglet Contacts) | F52: Thin-files (bancarisation de 24,3 %) et fraude à l’identité (81 % du secteur) : +40 % de pouvoir prédictif sans changer le process de décision, −21,9 % de coût du risque. | G52: M0 – À qualifier | I52: Proposer un pilote sandbox de 4 à 6 semaines sur un segment de portefeuille (crédit PME ou retail). | J52: Commercial IAT | M52: Cible complémentaire issue de la base clients CI (non citée dans le pitch) — 7 contact(s). À prioriser.
B53: Credolab | C53: BANQUE POPULAIRE | D53: Banque | E53: Dominique Mensah — DSI · 0709220000 · dmensah@banquepopulaire.ci (+3 autres dans l’onglet Contacts) | F53: Thin-files (bancarisation de 24,3 %) et fraude à l’identité (81 % du secteur) : +40 % de pouvoir prédictif sans changer le process de décision, −21,9 % de coût du risque. | G53: M0 – À qualifier | I53: Proposer un pilote sandbox de 4 à 6 semaines sur un segment de portefeuille (crédit PME ou retail). | J53: Commercial IAT | M53: Cible complémentaire issue de la base clients CI (non citée dans le pitch) — 4 contact(s). À prioriser.
B54: Credolab | C54: BHCI | D54: Banque | E54: Diby Constant — RSSI · 2250102000081 · cydiby@bhci.ci (+5 autres dans l’onglet Contacts) | F54: Thin-files (bancarisation de 24,3 %) et fraude à l’identité (81 % du secteur) : +40 % de pouvoir prédictif sans changer le process de décision, −21,9 % de coût du risque. | G54: M0 – À qualifier | I54: Proposer un pilote sandbox de 4 à 6 semaines sur un segment de portefeuille (crédit PME ou retail). | J54: Commercial IAT | M54: Cible complémentaire issue de la base clients CI (non citée dans le pitch) — 6 contact(s). À prioriser.
... B66: Credolab | C66: ECROCRED | D66: Microfinance (SFD) | E66: Jean Claude ZOGBE — Resp Systèmes D'Informations · 0789629904 · jean-claude.zogbe@wittifinances.com | F66: La fraude des agents est le premier facteur de perte : passer du scoring manuel au scoring automatisé (−43 % de fraude dans des cas similaires). | G66: M0 – À qualifier | I66: Proposer un pilote (preuve de concept) avant extension aux autres SFD. | J66: Commercial IAT | M66: Cible complémentaire issue de la base clients CI (non citée dans le pitch) — 1 contact(s). À prioriser.
B67: Wari+ | C67: BOA (SGI) | D67: Banque / SGI | E67: johnson YAPI — DSI GROUPE · 221 07 77 482 0450 · jyapi@boaholding.com (+7 autres dans l’onglet Contacts)
B68: Wari+ | C68: BNI (SGI) | D68: Banque / SGI | E68: Noufe — DSI · 07 07620719 · anoufe@bni.ci (+6 autres dans l’onglet Contacts)
B69: Wari+ | C69: Phoenix Capital (SGI) | D69: SGI | E69: Lydie Nguessan · 0707967513 · lnguessan@phoenixafricaholding.com
B70: Wari+ | C70: Bridge Securities (SGI) | D70: SGI
B71: Wari+ | C71: BRVM (connexion au marché) | D71: Bourse régionale | E71: alain coulibaly · 0709535324 · acoulibaly@brvm.org (+2 autres dans l’onglet Contacts)
B72: ManageEngine | C72: CNPS (vente croisée) | D72: Protection sociale | E72: Gballet BEUGRE — Directeur du Système d'Information (DSI) · Cel:(225)08305255 · g.beugre@cnps.ci (+7 autres dans l’onglet Contacts)
B73: ManageEngine | C73: FER (vente croisée) | D73: Administration
B74: ManageEngine
B75: WithSecure
B76: Hornetsecurity
B77: Gestion de flotte | C77: Ministère des Transports | D77: Administration
B79: 3. PITCHS CREDOLAB PAR SEGMENT — « Infinity powered by Credolab » (source : pitchs ciblés, juillet 2026)
B80: Segment | C80: Promesse | D80: Enjeu pour la cible | F80: Ce que nous apportons | I80: Accroche d’ouverture | J80: Appel à l’action | L80: Cibles prioritaires
B81: Socle commun (tous segments) | C81: Trois piliers | D81: Quel que soit le segment, le pitch repose sur une technologie mondiale, une maîtrise locale et des résultats chiffrés. | F81: 1) Scoring comportemental mondial : zéro PII, plus de 11 millions de caractéristiques analysées, réponse en moins de 200 ms. 2) Maîtrise locale totale du marché ivoirien et ouest-africain par IAT (réglementaire, technique, commercial). 3) Résultats démontrés : +40 % de pouvoir prédictif, −21,9 % de coût du risque, Gini de 92 sur les attaques de bots et fermes d’appareils. | I81: Parler valeur et résultats, pas nom de l’éditeur. | J81: Adapter le socle à l’enjeu du segment (lignes ci-dessous). | L81: —
B82: Banques commerciales | C82: « Transformez vos thin-files en clients notés, sans changer votre process de décision. » | D82: Bancarisation de 24,3 % en Côte d’Ivoire : un marché massif de candidats sans historique de crédit. Fraude à l’identité : 81 % du secteur (GIM-UEMOA, 2024). | F82: +40 % de pouvoir prédictif sans remplacer l’existant · −21,9 % de coût du risque · Gini 92 contre les bots · intégration SDK/API (Core Banking, mobile) en quelques semaines · conformité BCEAO, OHADA et protection des données gérée par IAT. | I82: « Sur un marché où seulement 1 Ivoirien sur 4 a un historique de crédit exploitable, chaque candidat rejeté à tort est un client perdu — et chaque fraude non détectée est une perte évitable. Notre technologie transforme les données comportementales de vos clients en score de risque actionnable, en moins de 200 millisecondes, sans jamais toucher à leurs données personnelles. » | J82: Pilote sandbox de 4 à 6 semaines sur un segment de portefeuille ciblé (crédit PME ou retail), avec mesure d’impact avant déploiement. | L82: BNI (5/5) · Ecobank CI (4/5) · Bridge Bank Group CI (4/5) · BICICI / Afrika Bank CI (4/5)
B83: Assurance | C83: « Évaluez le risque de vos assurés sans historique, et détectez la fraude avant le sinistre. » | D83: Une large part de la population cible n’a pas d’historique documentaire structuré ; cas d’usage en tarification du risque et en détection de fraude (souscription, sinistre). | F83: Scoring comportemental complémentaire aux données actuarielles · détection de fraude à la souscription (technologie anti-bot, Gini 92) · tableaux de bord et workflows de décision sur mesure · conformité gérée par IAT. | I83: « Vous tarifez aujourd’hui un risque avec des données parcellaires. Nous vous apportons une couche d’intelligence comportementale supplémentaire — la même que celle qui réduit de 21,9 % le coût du risque dans le secteur bancaire — pour mieux évaluer vos assurés et détecter la fraude avant qu’elle ne coûte cher. » | J83: Atelier de cadrage avec les équipes actuarielles et anti-fraude pour identifier 1 à 2 cas d’usage pilotes (tarification ou anti-fraude sinistre). | L83: AXA · SUNU · NSIA (profils et relations à qualifier)
B84: Fintech & Télécoms | C84: « Protégez un écosystème digital de 1,1 milliard de comptes mobiles, un compte à la fois. » | D84: 1,1 milliard de comptes mobiles en Afrique subsaharienne, un écosystème exposé (cyberattaque de 1,2 M€ chez CinetPay en septembre 2025). | F84: Détection de fraude en temps réel (< 200 ms) · Gini 92 contre les bots et fermes d’appareils · intégration SDK/API rapide · modèle de revenus au volume, frais généraux minimes. | I84: « CinetPay a perdu 1,2 million d’euros dans une cyberattaque en 2025. Votre volume de transactions est votre force et votre vulnérabilité. Notre moteur détecte les attaques de bots et les fermes d’appareils avec un score de Gini de 92, en temps réel, sans ajouter de friction à l’expérience utilisateur. » | J84: Test sandbox SDK/API ciblé sur un flux à risque (onboarding, crédit instantané ou paiement), avec mesure du taux de détection sur incidents réels. | L84: Orange CI / Orange Bank (5/5) · Wave (4/5) · Djamo (4/5) · Moov Africa / CinetPay (3/5)
B85: Institutions gouvernementales | C85: « Financez à grande échelle, avec un contrôle de fraude à la hauteur du volume. » | D85: Volumes massifs de micro-crédits pour des populations non bancarisées, fort risque de fraude documentaire et d’identité (AEJ : 800 000 bénéficiaires, 606 M USD ; FAFCI : 420 000 femmes ; DICEFA : 28,5 Mds FCFA sur 5 ans). | F85: Scoring alternatif sans historique bancaire · détection de fraude documentaire et d’identité à grande échelle · conformité BCEAO / OHADA et auditabilité · formation et conduite du changement en français. | I85: « Vous devez décaisser des centaines de milliers de micro-crédits à des bénéficiaires sans dossier bancaire, tout en protégeant les fonds publics contre la fraude documentaire. Notre technologie évalue le risque et détecte la fraude d’identité au moment de l’instruction du dossier, à l’échelle de vos volumes. » | J85: Présenter un cas d’usage chiffré adapté à un programme en cours (ex. DICEFA) et proposer une phase pilote sur une cohorte de bénéficiaires. | L85: AEJ (4/5) · FAFCI (3/5) · Programme DICEFA (3/5) · FIDEN (3/5)
B86: Microfinance (SFD) | C86: « La fraude des agents est votre premier facteur de perte. Passez du scoring manuel au scoring automatisé. » | D86: 2,5 millions de clients répartis sur 45 SFD ; la fraude des agents et employés est le premier facteur de perte, avec un scoring encore majoritairement manuel. | F86: −43 % de fraude dans des cas similaires · scoring automatisé et comportemental, moins dépendant du jugement des agents · −21,9 % de coût du risque · formation francophone des analystes crédit et risk managers. | I86: « Votre premier facteur de perte n’est pas l’emprunteur, c’est l’agent. Un scoring comportemental automatisé réduit de 43 % la fraude observée dans des cas similaires au vôtre, sans ralentir votre cycle d’octroi de crédit. » | J86: Lancer le pilote avec Credit Access (relation 5/5, candidat idéal) comme preuve de concept avant extension aux autres SFD. | L86: Credit Access (5/5) · Confina CI (4/5) · Fin’Elle (4/5) · UNACOOPEC-CI / Baobab / Advans (3/5)

Sheet Plan d’actions
B2: IAT — Plan d’actions
B3: Check-list des actions décidées en réunion du 13/10/2026 · gaps à traiter en priorité
B4: Échéance dépassée et action non faite = rouge · Responsables et dates proposés, à valider
B5: ← Retour à la synthèse
B7: ACTIONS
B8: N° | C8: Action | D8: Lié à | E8: Responsable | F8: Échéance | G8: Priorité | H8: Statut | I8: Commentaires
B9: 1 | C9: Compléter chaque fiche client : interlocuteurs, état de santé, satisfaction, coûts des ventes et commissions manquants | D9: CNAM, CNPS, FER, NSIA, Orange Business, NEURONES | E9: Commercial IAT | F9: 46315 | G9: P1 | H9: À faire | I9: La facturation et les encaissements 2024-2026 sont intégrés (point comptable du 13/10/2026)
B10: 2 | C10: CNPS : renouvellement échu depuis le 10/02/2026 — relance commerciale + rendez-vous avec la DSI pour obtenir la décision | D10: CNPS | E10: Commercial IAT | F10: 46318 | G10: P1 | H10: À faire | I10: Source : comptabilité
B11: 3 | C11: CNPS : rapprocher le montant du renouvellement (22,7 M évoqué en réunion, non chiffré dans le point comptable) | D11: CNPS | E11: Commercial IAT | F11: 46315 | G11: P1 | H11: À faire
B12: 4 | C12: NEURONES : relancer le fournisseur pour la cotation WithSecure, puis émettre l’offre de renouvellement | D12: NEURONES | E12: Commercial IAT | F12: 46309 | G12: P1 | H12: À faire | I12: Échu depuis le 21/08/2026 · source : comptabilité
B13: 5 | C13: FER : vérifier avec la compta si la sécurisation mail (4,5 M) est incluse dans les 28,8 M facturés ou reste à facturer | D13: FER | E13: Commercial IAT | F13: 46315 | G13: P1 | H13: À faire
B14: 6 | C14: CNAM : relancer la direction financière pour le solde de 4,5 M du contrat de maintenance (facture jointe) | D14: CNAM | E14: Commercial IAT | F14: 46357 | G14: P2 | H14: À faire | I14: Source : comptabilité
B15: 7 | C15: CNAM : renseigner la date de facturation et l’échéance du contrat de maintenance | D15: CNAM / Renouvellements | E15: Commercial IAT | F15: 46318 | G15: P2 | H15: À faire | I15: Date « N/A » dans le point comptable
B16: 8 | C16: CNAM : préparer l’offre de renouvellement des licences 2027 avant la relance J-90 | D16: CNAM | E16: Commercial IAT | F16: 46355 | G16: P2 | H16: À faire | I16: Échéance du contrat : 27/02/2027
B17: 9 | C17: FER : point de satisfaction client avant la relance J-90 du renouvellement | D17: FER | E17: Commercial IAT | F17: 46472 | G17: P3 | H17: À faire | I17: Échéance du contrat : 24/06/2027
B18: 10 | C18: Récupérer toutes les offres et cotations déjà envoyées et les intégrer au pipeline (ex. offre CNPS ≈ 59 M) | D18: Pipeline global | E18: Commercial IAT | F18: 46312 | G18: P1 | H18: À faire | I18: Avec Désiré et Maoula
B19: 11 | C19: Reprendre la main sur Orange Business : relancer l’interlocuteur clé et lister les deals gagnés / soumis / perdus | D19: Orange Business | E19: Commercial IAT | F19: 46318 | G19: P1 | H19: À faire
B20: 12 | C20: Call (tripartite si besoin) avec Maoula : partenaires technologiques, personnes clés, qui pousse quoi | D20: Solutions & prospects | E20: Commercial IAT | F20: 46316 | G20: P1 | H20: À faire
B21: 13 | C21: Se faire présenter toute l’offre ManageEngine par Salim et Kade (brochures à l’appui) | D21: ManageEngine | E21: Commercial IAT | F21: 46318 | G21: P2 | H21: À faire
B22: 14 | C22: Credolab : proposer le pilote à Credit Access (SFD, relation 5/5, candidat idéal identifié dans le pitch) | D22: Credolab | E22: Commercial IAT | F22: 46318 | G22: P1 | H22: À faire | I22: Semaine du 19/10 dans le calendrier d’attaque
B23: 15 | C23: Credolab : attaquer au moins un prospect par semaine selon le calendrier proposé (19 cibles issues des pitchs par segment) | D23: Solutions & prospects | E23: Commercial IAT | F23: 46314 | G23: P1 | H23: À faire | I23: Signé en juin, aucune action depuis : sujet évoqué par le partenaire. Calendrier à valider
B24: 16 | C24: Credolab : compléter les contacts métier (risque, crédit, digital) des cibles — la base clients fournit surtout des contacts IT ; trouver les contacts manquants (Credit Access, Wave, Djamo, BICICI, AEJ, FAFCI, DICEFA, FIDEN) | D24: Solutions & prospects | E24: Commercial IAT | F24: 46325 | G24: P2 | H24: À faire | I24: Contacts IT de la base clients CI déjà rattachés (19/10/2026)
B25: 17 | C25: Credolab : qualifier les cibles complémentaires issues de la base clients (banques, assureurs, SFD non cités dans le pitch) | D25: Solutions & prospects | E25: Commercial IAT | F25: 46332 | G25: P2 | H25: À faire
B26: 18 | C26: Mettre à jour les numéros au format à 8 chiffres (antérieur à 2021) dans l’onglet Contacts, en commençant par les contacts rattachés au pipeline | D26: Contacts | E26: Commercial IAT | F26: 46325 | G26: P3 | H26: À faire
B27: 19 | C27: Orange : confirmer que « Sidik » et « Landry » cités en réunion sont Sidik TOURE et Landry YOH (Orange CI) | D27: Orange Business | E27: Commercial IAT | F27: 46318 | G27: P3 | H27: À faire
B28: 20 | C28: Confirmer si le client du projet de digitalisation est le groupe PROSUMA (« Aboukassar » ≈ Abou Kassam, codirigeant) | D28: Pipeline global / PROSUMA | E28: Commercial IAT | F28: 46314 | G28: P1 | H28: À faire | I28: Recoupement réunion du 13/10 × recherche dirigeants du 15/10
B29: 21 | C29: CNPS : trancher qui est le DSI actuel (Gballet BEUGRE selon la base clients, Thierry Bahi selon la recherche web) | D29: CNPS | E29: Commercial IAT | F29: 46318 | G29: P1 | H29: À faire | I29: À faire avant la relance du renouvellement (RDV DSI)
B30: 22 | C30: Identifier les DSI de la CNAM, du FER et de NSIA Vie (non trouvés par la recherche) | D30: CNAM, FER, NSIA | E30: Commercial IAT | F30: 46325 | G30: P2 | H30: À faire
B31: 23 | C31: NSIA : recouper le nom de la DG de NSIA Vie CI (Sonia Nadège Seka, à confirmer) et préparer l’approche Credolab avec Konan Manassé Yao (actuariat) | D31: NSIA / Credolab | E31: Commercial IAT | F31: 46332 | G31: P2 | H31: À faire
B32: 24 | C32: NEURONES : vérifier que le revendeur d’Abidjan appartient au groupe français NEURONES (recherche menée sur le groupe) | D32: NEURONES | E32: Commercial IAT | F32: 46325 | G32: P3 | H32: À faire
B33: 25 | C33: Revenir sur le dossier Credolab reçu le 08/10 et intégrer les éléments d’Olivier dans les pitchs | D33: Credolab | E33: Commercial IAT | F33: 46311 | G33: P1 | H33: À faire | I33: Délai de 24-48 h déjà dépassé
B34: 26 | C34: Rédiger les pitchs sectoriels (banques : KYC, onboarding, cybersécurité, scoring, audit de conformité ; telcos) | D34: Solutions & prospects | E34: Commercial IAT | F34: 46315 | G34: P1 | H34: À faire
B35: 27 | C35: Définir une stratégie par produit et des offres sectorielles | D35: Solutions & prospects | E35: Commercial IAT | F35: 46326 | G35: P2 | H35: À faire
B36: 28 | C36: Revoir la brochure (trop généraliste) et produire des one-pagers concrets pour le salon | D36: Salon de l’Épargne | E36: Commercial IAT | F36: 46315 | G36: P1 | H36: À faire | I36: Pour Credolab : s’appuyer sur les pitchs Banques et Microfinance (onglet Solutions & prospects)
B37: 29 | C37: Salon de l’Épargne (22-23/10) : démo interactive Wari+ sur écrans tactiles 27" | D37: Wari+ | E37: À confirmer | F37: 46316 | G37: P1 | H37: À faire
B38: 30 | C38: Signer le partenariat de commercialisation Wari+ (revenue sharing, prix plancher 45 M) | D38: Wari+ | E38: Direction générale | F38: 46316 | G38: P1 | H38: À faire
B39: 31 | C39: Finaliser le cahier des charges de la digitalisation du pôle opérationnel | D39: Client à préciser (projet digitalisation) | E39: À confirmer | F39: 46314 | G39: P1 | H39: À faire
B40: 32 | C40: Valider ensemble la cotation Prisme / portail et l’émettre sur papier à en-tête Infinity | D40: Client à préciser (projet digitalisation) | E40: À confirmer | F40: 46311 | G40: P1 | H40: À faire
B41: 33 | C41: Gestion de flotte : obtenir des tests sur les véhicules de l’entreprise | D41: Ministère des Transports | E41: À confirmer | F41: 46325 | G41: P2 | H41: À faire
B42: 34 | C42: Prendre en charge le nouveau directeur sur le compte suivi en haut par Maoula | D42: CNAM (à confirmer) | E42: Commercial IAT | F42: 46318 | G42: P2 | H42: À faire
B43: 35 | C43: KAYDAN : qualifier l’affaire ou la sortir du portefeuille | D43: Pipeline global | E43: Commercial IAT | F43: 46318 | G43: P2 | H43: À faire
B44: 36 | C44: Profiter de la période budgétaire pour relancer les prospects (signature possible pour 2027) | D44: Pipeline global | E44: Commercial IAT | F44: 46326 | G44: P2 | H44: À faire
B45: 37 | C45: Faire figurer les deals B2B de la Direction (Huawei, DGF…) dans le pipeline | D45: Pipeline global | E45: Direction générale | F45: 46318 | G45: P2 | H45: À faire
B46: 38 | C46: Communiquer sur le partenariat Huawei (site web, brochure) | D46: Huawei | E46: À confirmer | F46: 46326 | G46: P3 | H46: À faire
B47: =IF(C47="","",ROW()-8)
B48: =IF(C48="","",ROW()-8)
B49: =IF(C49="","",ROW()-8)
B50: =IF(C50="","",ROW()-8)
B51: =IF(C51="","",ROW()-8)

Sheet Contacts
B2: IAT — Contacts
B3: Base clients Côte d’Ivoire (BD_CLIENTS_CI.xlsx) + dirigeants identifiés par recherche web / LinkedIn (15/10/2026) · contacts dédoublonnés, profilés et rattachés au pipeline
B4: Profil déduit de la fonction · « Lien avec le pipeline » = compte, prospect ou cible concerné · Statut « Coordonnées à vérifier » = numéro à 8 chiffres (format antérieur à 2021)
B5: ← Retour à la synthèse
B7: CONTACTS (420 lignes) — filtrer par entreprise, secteur, profil, source ou lien avec le pipeline
B8: N° | C8: Entreprise | D8: Secteur (base) | E8: Nom | F8: Fonction | G8: Profil | H8: Téléphone | I8: Email | J8: Lien avec le pipeline IAT | K8: Statut du contact | L8: Dernier contact | M8: Commentaires | N8: Source
B9: 1 | C9: CNAM (Côte d’Ivoire) | D9: Dirigeants (recherche) | E9: Karim Bamba | F9: DG | G9: Direction générale / métier | J9: Client — fiche CNAM | K9: À contacter | M9: Confirmé. Site officiel (ipscnam.ci) ; pas de profil LinkedIn trouvé. | N9: Recherche dirigeants (web + LinkedIn, 15/10/2026)
B10: 2 | C10: CNAM (Côte d’Ivoire) | D10: Dirigeants (recherche) | E10: Ahmed Tidiane Diomandé | F10: DGA | G10: Direction générale / métier | J10: Client — fiche CNAM | K10: À contacter | M10: Confirmé. LinkedIn : Directeur Général Adjoint. | N10: Recherche dirigeants (web + LinkedIn, 15/10/2026)
B11: 3 | C11: CNPS (Côte d’Ivoire) | D11: Dirigeants (recherche) | E11: Thierry Bahi | F11: DSI | G11: Direction SI / digital | J11: Client — fiche CNPS | K11: À contacter | M11: À confirmer. Cité en déc. 2023, introuvable sur LinkedIn. ⚠ La base clients CI indique Gballet BEUGRE comme DSI : à trancher. | N11: Recherche dirigeants (web + LinkedIn, 15/10/2026)
B12: 4 | C12: CNPS (Côte d’Ivoire) | D12: Dirigeants (recherche) | E12: Denis Charles Kouassi | F12: DG | G12: Direction générale / métier | J12: Client — fiche CNPS | K12: À contacter | M12: Confirmé. LinkedIn + presse. | N12: Recherche dirigeants (web + LinkedIn, 15/10/2026)
B13: 5 | C13: CNPS (Côte d’Ivoire) | D13: Dirigeants (recherche) | E13: Idriss Traoré | F13: DGA chargé de l’exploitation | G13: Direction générale / métier | J13: Client — fiche CNPS | K13: À contacter | M13: À confirmer. Profil LinkedIn en lecture limitée. | N13: Recherche dirigeants (web + LinkedIn, 15/10/2026)
B14: 6 | C14: FER (Côte d’Ivoire) | D14: Dirigeants (recherche) | E14: Annick Tohé Lasmel | F14: Directrice générale | G14: Direction générale / métier | J14: Client — fiche FER | K14: À contacter | M14: Confirmé. Site officiel du FER (actif juillet 2026) ; dirige le FER depuis 2022 ; pas de profil LinkedIn. | N14: Recherche dirigeants (web + LinkedIn, 15/10/2026)
B15: 7 | C15: FER (Côte d’Ivoire) | D15: Dirigeants (recherche) | E15: Moussa Diarra | F15: Directeur financier et comptable | G15: Direction générale / métier | J15: Client — fiche FER | K15: À contacter | M15: À confirmer. Information complémentaire de la recherche. | N15: Recherche dirigeants (web + LinkedIn, 15/10/2026)
B16: 8 | C16: NEURONES (groupe, France) | D16: Dirigeants (recherche) | E16: Luc de Chammard | F16: PDG | G16: Direction générale / métier | J16: Partenaire — fiche NEURONES | K16: À contacter | M16: Confirmé. LinkedIn + AMF. | N16: Recherche dirigeants (web + LinkedIn, 15/10/2026)
B17: 9 | C17: NEURONES (groupe, France) | D17: Dirigeants (recherche) | E17: Bertrand Ducurtil | F17: DG délégué | G17: Direction générale / métier | J17: Partenaire — fiche NEURONES | K17: À contacter | M17: À confirmer. Déclarations AMF ; non revérifié sur LinkedIn. | N17: Recherche dirigeants (web + LinkedIn, 15/10/2026)
B18: 10 | C18: NEURONES (groupe, France) | D18: Dirigeants (recherche) | E18: Matthieu Vautier | F18: Directeur marketing et communication | G18: Direction générale / métier | J18: Partenaire — fiche NEURONES | K18: À contacter | M18: À confirmer. | N18: Recherche dirigeants (web + LinkedIn, 15/10/2026)
B19: 11 | C19: NSIA Vie (Côte d’Ivoire) | D19: Dirigeants (recherche) | E19: Sonia Nadège Seka | F19: DG | G19: Direction générale / métier | J19: Client — fiche NSIA (NSIA Vie) | K19: À contacter | M19: À confirmer. Profil LinkedIn limité, filiale non certifiée : à recouper. | N19: Recherche dirigeants (web + LinkedIn, 15/10/2026)
B20: 12 | C20: NSIA Vie (Côte d’Ivoire) | D20: Dirigeants (recherche) | E20: Gérard Gilles Akou | F20: DGA | G20: Direction générale / métier | J20: Client — fiche NSIA (NSIA Vie) | K20: À contacter | M20: Confirmé. LinkedIn : DGA NSIA Vie CI (n’est plus directeur commercial). | N20: Recherche dirigeants (web + LinkedIn, 15/10/2026)
... B26: 18 | C26: PROSUMA (Côte d’Ivoire) | D26: Dirigeants (recherche) | E26: Abou Kassam et Karim Fakhry | F26: Dirigeants (DG / PDG) | G26: Direction générale / métier | J26: Pipeline — PROSUMA | K26: À contacter | M26: Confirmé. Site officiel du groupe ; pas de profil LinkedIn trouvé. | N26: Recherche dirigeants (web + LinkedIn, 15/10/2026)
B27: 19 | C27: ABI & banque Atlantique | D27: Banques & assurances | E27: Miloud | F27: DSSI ABI | G27: Direction SI / digital | H27: +225 03 70 70 71 | I27: miloud.chennaoui@banqueatlantique.net | J27: Credolab — cible complémentaire (base clients) | K27: Coordonnées à vérifier | N27: Base clients CI
B28: 20 | C28: ABI & banque Atlantique | D28: Banques & assurances | E28: Yaya DAGNOGO | F28: Directeur Infrastructures & Production | G28: Infrastructure / réseaux | H28: 01024465 | I28: yaya.dagnogo@banqueatlantique.net | J28: Credolab — cible complémentaire (base clients) | K28: Coordonnées à vérifier | N28: Base clients CI
B29: 21 | C29: ABI & banque Atlantique | D29: Banques & assurances | E29: Abdellilah | F29: Resp Achat ABI | G29: Achats / marchés | H29: 0102553507 | I29: seydou.toure@banqueatlantique.net | J29: Credolab — cible complémentaire (base clients) | K29: À contacter | N29: Base clients CI
B30: 22 | C30: ABI & banque Atlantique | D30: Banques & assurances | E30: TIDIANE SERE | F30: Acheteur | G30: Achats / marchés | H30: +225 42 42 34 39 | I30: thidian.sere@banqueatlantique.net | J30: Credolab — cible complémentaire (base clients) | K30: Coordonnées à vérifier | N30: Base clients CI
B31: 23 | C31: ABI & banque Atlantique | D31: Banques & assurances | E31: ABOUT KOFFI | F31: Resp Achat BACI | G31: Achats / marchés | H31: +225 40 92 74 07 | J31: Credolab — cible complémentaire (base clients) | K31: Coordonnées à vérifier | N31: Base clients CI
B32: 24 | C32: ABI & banque Atlantique | D32: Banques & assurances | E32: CHERIF BISSIRIOU | G32: Non renseigné | H32: +225 01 33 56 08 | I32: cherif.bissiriou@banqueatlantique.net | J32: Credolab — cible complémentaire (base clients) | K32: Coordonnées à vérifier | N32: Base clients CI
B33: 25 | C33: ABI & banque Atlantique | D33: Banques & assurances | E33: TOURE Seydou | G33: Non renseigné | H33: +225 07 38 29 23 | I33: seydou.toure@banqueatlantique.net | J33: Credolab — cible complémentaire (base clients) | K33: Coordonnées à vérifier | N33: Base clients CI
B34: 26 | C34: ADVANS | D34: Banques & assurances | E34: Héloïse TROUILLEZ | F34: Chargée de projets digitaux | G34: Informatique / projets | H34: 05 45.55.52.47 | I34: htrouillez@advanscotedivoire.com | J34: Credolab — Advans | K34: À contacter | N34: Base clients CI
B35: 27 | C35: ADVANS | D35: Banques & assurances | E35: Jean Claude Amoikon SAMOU | F35: Gestionnaire Achats | G35: Achats / marchés | H35: C: (+225) 75.58.47.13 | I35: jcsamou@advanscotedivoire.com | J35: Credolab — Advans | K35: Coordonnées à vérifier | N35: Base clients CI
B36: 28 | C36: ADVANS | D36: Banques & assurances | E36: ADINGRA KOBENAN | G36: Non renseigné | H36: 0707 38 18 97 / (+225) 75.58.46.46 | I36: bkobenan@advanscotedivoire.com | J36: Credolab — Advans | K36: À contacter | N36: Base clients CI
B37: 29 | C37: ADVANS | D37: Banques & assurances | E37: Franck Lakpa | G37: Non renseigné | H37: +225 75 58 47 36 | I37: flakpa@advanscotedivoire.com | J37: Credolab — Advans | K37: Coordonnées à vérifier | N37: Base clients CI
B38: 30 | C38: ADVANS | D38: Banques & assurances | E38: Christian KACOU | G38: Non renseigné | H38: +225 07 82 00 14 | I38: C.KACOU@cgiar.org | J38: Credolab — Advans | K38: Coordonnées à vérifier | N38: Base clients CI
B39: 31 | C39: AFRICAINES DES ASSURANCES | D39: Banques & assurances | E39: VIRGILE ASSOGBA | F39: Directeur Administratif et Financier | G39: Direction générale / métier | H39: 07 07 18 50 50 | I39: vassogba@africaine-ci.com | J39: Credolab — cible complémentaire (base clients) | K39: À contacter | N39: Base clients CI
B40: 32 | C40: AFRICAINES DES ASSURANCES | D40: Banques & assurances | E40: MIAN AHUI | F40: RI | G40: Informatique / projets | H40: 07 08 11 64 57 | I40: mian.ahui@africaine-ci.ci | J40: Credolab — cible complémentaire (base clients) | K40: À contacter | N40: Base clients CI
B41: 33 | C41: AFRICAINES DES ASSURANCES | D41: Banques & assurances | E41: YVES AMESSAN | G41: Non renseigné | I41: yves.amessan@africaine-ci.com | J41: Credolab — cible complémentaire (base clients) | K41: À contacter | N41: Base clients CI
B42: 34 | C42: AFRILAND FIRST BANK | D42: Banques & assurances | E42: Fulbert ATTOUMO | G42: Non renseigné | H42: 87-310-833/ 06139798 | I42: fulbert.attoumo@afrilandfirstbankgroup.com | J42: Credolab — cible complémentaire (base clients) | K42: Coordonnées à vérifier | N42: Base clients CI
B43: 35 | C43: ALIOS FINANCE | D43: Banques & assurances | E43: Souleymane Soumahoro | F43: RI | G43: Informatique / projets | H43: (225) 27 21 21 07 00 (Fax) / (225) 27 21 21 07 80 (LD) / (225) 05 05 85 16 33 (cel) | I43: souleymane.soumahoro@alios-finance.com | J43: Credolab — cible complémentaire (base clients) | K43: À contacter | N43: Base clients CI
B44: 36 | C44: AMIFA | D44: Banques & assurances | E44: Mohamed ELEMAYE | F44: IT MANAGER | G44: Direction SI / digital | H44: 01 72 50 05 69 | I44: m.elemaye@amifa-ci.net | J44: Credolab — cible complémentaire (base clients) | K44: À contacter | N44: Base clients CI
B45: 37 | C45: AMIFA | D45: Banques & assurances | E45: Masseba Soumahoro | G45: Non renseigné | H45: (225) 27 22 42 67 27 | I45: masseba.soumahoro@amifa-ci.net | J45: Credolab — cible complémentaire (base clients) | K45: À contacter | N45: Base clients CI
B46: 38 | C46: AXA ASSURANCE | D46: Banques & assurances | E46: AMANI BORRO | F46: Resp Informatique | G46: Informatique / projets | H46: +225 07016476 | I46: amani.borro@axa.ci | J46: Credolab — AXA | K46: Coordonnées à vérifier | N46: Base clients CI
B47: 39 | C47: AXA ASSURANCE | D47: Banques & assurances | E47: Junior AKANZA | F47: IT | G47: Informatique / projets | I47: junior.akanza@axa.ci | J47: Credolab — AXA | K47: À contacter | N47: Base clients CI
B48: 40 | C48: BANQUE POPULAIRE | D48: Banques & assurances | E48: Dominique Mensah | F48: DSI | G48: Direction SI / digital | H48: 0709220000 | I48: dmensah@banquepopulaire.ci | J48: Credolab — cible complémentaire (base clients) | K48: À contacter | N48: Base clients CI
B49: 41 | C49: BANQUE POPULAIRE | D49: Banques & assurances | E49: TCHINAH | F49: Directeur Projet | G49: Direction générale / métier | H49: 01 00 00 85 | I49: cthinah@banquepopulaire.ci | J49: Credolab — cible complémentaire (base clients) | K49: Coordonnées à vérifier | N49: Base clients CI
B50: 42 | C50: BANQUE POPULAIRE | D50: Banques & assurances | E50: Williams ACKA | F50: RSSI Groupe | G50: Sécurité SI | H50: 0101826715 | I50: wacka@banquepopulaire.ci | J50: Credolab — cible complémentaire (base clients) | K50: À contacter | N50: Base clients CI
B51: 43 | C51: BANQUE POPULAIRE | D51: Banques & assurances | E51: KONAN Brou Claude Hervé | F51: Dir Achat | G51: Achats / marchés | H51: +225 20 25 53 81 / +225 07 51 93 94 | I51: chkonan@caissepargne.ci | J51: Credolab — cible complémentaire (base clients) | K51: Coordonnées à vérifier | N51: Base clients CI
B52: 44 | C52: BAOBAB | D52: Banques & assurances | E52: Wilson KOUAKOU | F52: RI | G52: Informatique / projets | H52: 0554876179 | I52: tkouakou@baobabgroup.com | J52: Credolab — Baobab | K52: À contacter | N52: Base clients CI
B53: 45 | C53: BAOBAB | D53: Banques & assurances | E53: AminaSAMB | F53: Resp Achat | G53: Achats / marchés | H53: 0584 69 89 80 | I53: asamb@baobabgroup.com | J53: Credolab — Baobab | K53: À contacter | N53: Base clients CI
B54: 46 | C54: BAOBAB | D54: Banques & assurances | E54: SOMBO | F54: Directeur Achat | G54: Achats / marchés | H54: 0575 58 23 40 | I54: psombo@baobabgroup.com | J54: Credolab — Baobab | K54: À contacter | N54: Base clients CI
B55: 47 | C55: BGFI BANK CI | D55: Banques & assurances | E55: Moussa TOURE | G55: Non renseigné | H55: 07 58 51 30 12 | I55: m.toure@bgfigroupe.com | J55: Credolab — cible complémentaire (base clients) | K55: À contacter | N55: Base clients CI
B56: 48 | C56: BGFI BANK CI | D56: Banques & assurances | E56: Paul TANO | G56: Non renseigné | H56: 07 57 20 41 00 | I56: p.tano@bgfigroupe.com | J56: Credolab — cible complémentaire (base clients) | K56: À contacter | N56: Base clients CI
B57: 49 | C57: BHCI | D57: Banques & assurances | E57: MORISSON JEAN -SYLVAIN | F57: Resp Sécurité | G57: Sécurité SI | H57: 07 07 17 71 17 | I57: jmorisson@bhci.ci | J57: Credolab — cible complémentaire (base clients) | K57: À contacter | N57: Base clients CI
B58: 50 | C58: BHCI | D58: Banques & assurances | E58: Richard ZOUGOU | F58: Administrateur Sécurité des Systèmes d’information | G58: Sécurité SI | H58: 07 47 94 68 32 | I58: rzougou@bhci.ci | J58: Credolab — cible complémentaire (base clients) | K58: À contacter | N58: Base clients CI
B59: 51 | C59: BHCI | D59: Banques & assurances | E59: Diby Constant | F59: RSSI | G59: Sécurité SI | H59: 2250102000081 | I59: cydiby@bhci.ci | J59: Credolab — cible complémentaire (base clients) | K59: À contacter | N59: Base clients CI
B60: 52 | C60: BHCI | D60: Banques & assurances | E60: Moussa FOFANA | F60: Chef de Département Infra et Système | G60: Infrastructure / réseaux | H60: 07 57 17 17 17 | I60: mofofana@bhci.ci | J60: Credolab — cible complémentaire (base clients) | K60: À contacter | N60: Base clients CI
B61: 53 | C61: BHCI | D61: Banques & assurances | E61: Sidney TIAKPA | F61: Chef de Service Achat Logistique | G61: Achats / marchés | H61: 0558962471 | I61: stiakpa@bhci.ci | J61: Credolab — cible complémentaire (base clients) | K61: À contacter | N61: Base clients CI
B62: 54 | C62: BHCI | D62: Banques & assurances | E62: Mme PATRICIA N'DRI | G62: Non renseigné | I62: pndri@bhci.ci | J62: Credolab — cible complémentaire (base clients) | K62: À contacter | N62: Base clients CI
B63: 55 | C63: BNI | D63: Banques & assurances | E63: Noufe | F63: DSI | G63: Direction SI / digital | H63: 07 07620719 | I63: anoufe@bni.ci | J63: Credolab — BNI · Wari+ (SGI) | K63: À contacter | N63: Base clients CI
B64: 56 | C64: BNI | D64: Banques & assurances | E64: Coulibaly Zonzerigue | F64: DSSI | G64: Direction SI / digital | H64: 097174713 | I64: zonzerigue.coulibaly@bni.ci | J64: Credolab — BNI · Wari+ (SGI) | K64: À contacter | N64: Base clients CI
B65: 57 | C65: BNI | D65: Banques & assurances | E65: BAMBA | F65: IT Bni Finance | G65: Informatique / projets | H65: 09 63 33 08 | I65: mohamed.bamba@bnifinances.ci | J65: Credolab — BNI · Wari+ (SGI) | K65: Coordonnées à vérifier | N65: Base clients CI
B66: 58 | C66: BNI | D66: Banques & assurances | E66: Serge N'daw | F66: Chef De sce Infra & Rx | G66: Infrastructure / réseaux | H66: 79032284 | I66: serge.ndaw@bni.ci | J66: Credolab — BNI · Wari+ (SGI) | K66: Coordonnées à vérifier | N66: Base clients CI
B67: 59 | C67: BNI | D67: Banques & assurances | E67: Yeo Legnimin | F67: Chef De Départ Infra, Système et base de Données | G67: Infrastructure / réseaux | H67: 0707 733524 | I67: legnimin.yeo@bni.ci | J67: Credolab — BNI · Wari+ (SGI) | K67: À contacter | N67: Base clients CI
B68: 60 | C68: BNI | D68: Banques & assurances | E68: DJABOUET NARCISSE | F68: Resp Sce Achat | G68: Achats / marchés | H68: 0789507158 | I68: narcisse.djabouet@bni.ci | J68: Credolab — BNI · Wari+ (SGI) | K68: À contacter | N68: Base clients CI
B69: 61 | C69: BNI | D69: Banques & assurances | E69: Rachelle URI Ahua | F69: Resp Sce Qualité | G69: Commercial / autre | H69: 88919257 | I69: uri-rachele.ahua@bni.ci | J69: Credolab — BNI · Wari+ (SGI) | K69: Coordonnées à vérifier | N69: Base clients CI
B70: 62 | C70: BNP Paribas | D70: Banques & assurances | E70: Venance KONAN | F70: DSI | G70: Direction SI / digital | H70: 07 35 42 55 | I70: venance.konan@bnpparibas.com | J70: Credolab — cible complémentaire (base clients) | K70: Coordonnées à vérifier | N70: Base clients CI
B71: 63 | C71: BNP Paribas | D71: Banques & assurances | E71: Paul Eric | F71: RSI | G71: Informatique / projets | H71: 89 52 6550 | I71: pauleric.seck@bnpparibas.com | J71: Credolab — cible complémentaire (base clients) | K71: Coordonnées à vérifier | N71: Base clients CI
B72: 64 | C72: BNP Paribas | D72: Banques & assurances | E72: Mme GAYIBOR Amma Laetitia | F72: Chef Departement Achats | G72: Achats / marchés | H72: +225 20 20 17 89 / +225 57 14 78 04 | I72: ammaleatitia.gayibor@bnpparibas.com | J72: Credolab — cible complémentaire (base clients) | K72: Coordonnées à vérifier | N72: Base clients CI
B73: 65 | C73: BOA BANK CI | D73: Banques & assurances | E73: johnson YAPI | F73: DSI GROUPE | G73: Direction SI / digital | H73: 221 07 77 482 0450 | I73: jyapi@boaholding.com | J73: Wari+ — BOA (SGI) | K73: À contacter | N73: Base clients CI
B74: 66 | C74: BOA BANK CI | D74: Banques & assurances | E74: John AYORA | F74: DSSI Groupe | G74: Direction SI / digital | H74: 221 78 101 37 29 | I74: jayora@boaholding.com | J74: Wari+ — BOA (SGI) | K74: À contacter | N74: Base clients CI
... B80: 72 | C80: BOA BANK CI | D80: Banques & assurances | E80: TANON AKA | F80: Resp Achats | G80: Achats / marchés | H80: + 225 04 03 47 37 | I80: taka@boacoteivoire.com | J80: Wari+ — BOA (SGI) | K80: Coordonnées à vérifier | N80: Base clients CI
B81: 73 | C81: BRIDGE BANK GROUP | D81: Banques & assurances | E81: Mme KOUASSI | F81: Acheteur | G81: Achats / marchés | H81: 01 40 14 87 03 | J81: Credolab — Bridge Bank Group CI | K81: À contacter | N81: Base clients CI
B82: 74 | C82: BRIDGE BANK GROUP | D82: Banques & assurances | E82: Delors Doro | G82: Non renseigné | H82: 0556702007 | I82: delors.doro@bridgebankgroup.com | J82: Credolab — Bridge Bank Group CI | K82: À contacter | N82: Base clients CI
B83: 75 | C83: BRIDGE BANK GROUP | D83: Banques & assurances | E83: Brice Bleguin | G83: Non renseigné | H83: 05 05 01 00 15 | I83: brice.bleguin@gmail.com | J83: Credolab — Bridge Bank Group CI | K83: À contacter | N83: Base clients CI
B84: 76 | C84: BRIDGE BANK GROUP | D84: Banques & assurances | E84: Victor KAKOU | G84: Non renseigné | H84: 545411960 | I84: victor.kakou@bridgebankgroup.com | J84: Credolab — Bridge Bank Group CI | K84: À contacter | N84: Base clients CI
B85: 77 | C85: BSIC | D85: Banques & assurances | E85: Dara Paul | G85: Non renseigné | H85: 67 76 61 86 | I85: paul.dara@bsic.ci | J85: Credolab — cible complémentaire (base clients) | K85: Coordonnées à vérifier | N85: Base clients CI
B86: 78 | C86: BSIC | D86: Banques & assurances | E86: SEHI KEVIN | G86: Non renseigné | H86: 07 49 82 50 35 | I86: KEVIN.SEHI@BSIC.CI | J86: Credolab — cible complémentaire (base clients) | K86: À contacter | N86: Base clients CI
B87: 79 | C87: BSIC | D87: Banques & assurances | E87: Fulgence KOUAKOU | G87: Non renseigné | H87: 07 07 70 67 89 | I87: fulgence.kouakou@bsic.ci | J87: Credolab — cible complémentaire (base clients) | K87: À contacter | N87: Base clients CI
B88: 80 | C88: BSIC | D88: Banques & assurances | E88: Salex KRIZA | G88: Non renseigné | H88: 46 01 75 01 | I88: SALEX.KRIZA@BSIC.CI | J88: Credolab — cible complémentaire (base clients) | K88: Coordonnées à vérifier | N88: Base clients CI
B89: 81 | C89: COFINA GROUPE | D89: Banques & assurances | E89: Leonard KOUASSI | F89: Group Head of IT | G89: Direction SI / digital | H89: 07 07 20 32 10 | I89: leonard.kouassi@cofinacorp.com | J89: Credolab — Cofina (« Confina CI » dans le pitch) | K89: À contacter | N89: Base clients CI
B90: 82 | C90: COFINA GROUPE | D90: Banques & assurances | E90: Prosper FAYE | F90: DSI GROUPE | G90: Direction SI / digital | H90: +221 77 333 96 02 | I90: prosper.faye@cofinacorp.com | J90: Credolab — Cofina (« Confina CI » dans le pitch) | K90: À contacter | N90: Base clients CI
B91: 83 | C91: COFINA GROUPE | D91: Banques & assurances | E91: Emany kitsoukou | F91: DSI | G91: Direction SI / digital | H91: +225 47639495 | I91: emanny.kitsoukou@cofinacorp.com | J91: Credolab — Cofina (« Confina CI » dans le pitch) | K91: Coordonnées à vérifier | N91: Base clients CI
B92: 84 | C92: COFINA GROUPE | D92: Banques & assurances | E92: Honorat Fieny KOUAME | F92: Head IT COFINA | G92: Direction SI / digital | H92: 07 77 10 26 84 | I92: honorat.kouame@cofinacorp.com | J92: Credolab — Cofina (« Confina CI » dans le pitch) | K92: À contacter | N92: Base clients CI
B93: 85 | C93: COFINA GROUPE | D93: Banques & assurances | E93: Alexis Loukou N’DRI | F93: RSSI Groupe | G93: Sécurité SI | H93: +225 07 97 94 59 99 | I93: alexis.ndri@cofinacorp.com | J93: Credolab — Cofina (« Confina CI » dans le pitch) | K93: À contacter | N93: Base clients CI
B94: 86 | C94: COFINA GROUPE | D94: Banques & assurances | E94: Anderson OUATTARA | F94: Responsable Moyens Généraux CAC | G94: Achats / marchés | H94: 07 77 27 84 20 | I94: anderson.ouattara@cofinacorp.com | J94: Credolab — Cofina (« Confina CI » dans le pitch) | K94: À contacter | N94: Base clients CI
B95: 87 | C95: COFINA GROUPE | D95: Banques & assurances | E95: Saoudatou DIALLO | F95: Sce Achat DAKAR | G95: Achats / marchés | H95: +221771913088 | I95: saoudatou.diallo@cofinacorp.com | J95: Credolab — Cofina (« Confina CI » dans le pitch) | K95: À contacter | N95: Base clients CI
B96: 88 | C96: COMAR ASSURANCES | D96: Banques & assurances | E96: Mustapha AZAIEZ | F96: DG | G96: Direction générale / métier | H96: Téléphone : +225 20 20 24 55 | I96: mustapha.azaiez@comar.ci | J96: Credolab — cible complémentaire (base clients) | K96: Coordonnées à vérifier | N96: Base clients CI
B97: 89 | C97: CORIS BANK | D97: Banques & assurances | E97: Omar Somtore | F97: DSI | G97: Direction SI / digital | H97: 0546636671 | I97: osomtore@coris-bank.com | J97: Credolab — cible complémentaire (base clients) | K97: À contacter | N97: Base clients CI
B98: 90 | C98: CORIS BANK | D98: Banques & assurances | E98: Attabi LEGRE | F98: Chef De sce | G98: Informatique / projets | H98: 05 66 47 33 07 | I98: rlegre@coris-bank.com | J98: Credolab — cible complémentaire (base clients) | K98: À contacter | N98: Base clients CI
B99: 91 | C99: CORIS BANK | D99: Banques & assurances | E99: Laurent COULIBALY | F99: Chef de Sce | G99: Informatique / projets | H99: 05 85 63 62 00 | I99: flcoulibaly@coris-bank.com | J99: Credolab — cible complémentaire (base clients) | K99: À contacter | N99: Base clients CI
B100: 92 | C100: CORIS BANK | D100: Banques & assurances | E100: Anderson KOFFI YAO | F100: Resp Achats | G100: Achats / marchés | H100: 05 04 12 75 52 | I100: kyao@coris-bank.com | J100: Credolab — cible complémentaire (base clients) | K100: À contacter | N100: Base clients CI
... B102: 94 | C102: ECOBANK CI | D102: Banques & assurances | E102: Anderson SERI | F102: RSI | G102: Informatique / projets | H102: 07 57 1514 71 23 | I102: aseri@ecobank.com | J102: Credolab — Ecobank CI | K102: À contacter | N102: Base clients CI
B103: 95 | C103: ECOBANK CI | D103: Banques & assurances | E103: André COULIBALY | G103: Non renseigné | H103: + 225 08 08 61 68 | I103: acoulibaly@ecobank.com | J103: Credolab — Ecobank CI | K103: Coordonnées à vérifier | N103: Base clients CI
B104: 96 | C104: ECOBANK CI | D104: Banques & assurances | E104: Mockey | G104: Non renseigné | H104: + 225 07 02 25 28 | I104: gmockey@ecobank.com | J104: Credolab — Ecobank CI | K104: Coordonnées à vérifier | N104: Base clients CI
B105: 97 | C105: ECOBANK CI | D105: Banques & assurances | E105: EDOUKOU | G105: Non renseigné | H105: + 225 07 01 11 03 | J105: Credolab — Ecobank CI | K105: Coordonnées à vérifier | N105: Base clients CI
B106: 98 | C106: ECROCRED | D106: Banques & assurances | E106: Jean Claude ZOGBE | F106: Resp Systèmes D'Informations | G106: Commercial / autre | H106: 0789629904 | I106: jean-claude.zogbe@wittifinances.com | J106: Credolab — cible complémentaire (base clients) | K106: À contacter | N106: Base clients CI
B107: 99 | C107: FIDRA | D107: Banques & assurances | E107: Françis YAO | F107: DSI | G107: Direction SI / digital | H107: 0709666018 | I107: FYAO@fidra.ci | J107: Credolab — cible complémentaire (base clients) | K107: À contacter | N107: Base clients CI
B108: 100 | C108: FIDRA | D108: Banques & assurances | E108: ISSA DIALLO | F108: RI | G108: Informatique / projets | H108: 0708519114 | J108: Credolab — cible complémentaire (base clients) | K108: À contacter | N108: Base clients CI
B109: 101 | C109: FIDRA | D109: Banques & assurances | E109: GUIBILA | F109: DIR ACHAT | G109: Achats / marchés | H109: 07 07 01 17 31 | I109: ANICET.GUIBILA@fidra.ci | J109: Credolab — cible complémentaire (base clients) | K109: À contacter | N109: Base clients CI
B110: 102 | C110: FIN'ELLE | D110: Banques & assurances | E110: Lolomba KONE | F110: Head of IT | G110: Direction SI / digital | H110: 225 07 87 90 57 84 | I110: lolamba.kone@cofinacorp.com | J110: Credolab — Fin’Elle | K110: À contacter | N110: Base clients CI
B111: 103 | C111: FIN'ELLE | D111: Banques & assurances | E111: Moussa SYLLA | F111: IT Department | G111: Informatique / projets | H111: 225 07 58 33 26 34 | I111: m.sylla@cofinacorp.com | J111: Credolab — Fin’Elle | K111: À contacter | N111: Base clients CI
B112: 104 | C112: FINELLE | D112: Banques & assurances | E112: Moussa Sylla Finelle | F112: IT ASSISTANT | G112: Informatique / projets | H112: 225 07 58 33 26 34 | I112: m.sylla@cofinacorp.com | J112: Credolab — Fin’Elle | K112: À contacter | N112: Base clients CI
B113: 105 | C113: GNA ASSURANCE | D113: Banques & assurances | E113: siriki tiene | G113: Non renseigné | H113: 0708110116 | I113: siriki.tiene@gna-ci.com | J113: Credolab — cible complémentaire (base clients) | K113: À contacter | N113: Base clients CI
...

Sheet Listes
A1: Etapes | B1: Types | C1: Leads | D1: Recur | E1: Prio | F1: OuiNon | G1: Sante | H1: Statut | I1: EtapesAO | J1: Maitrise | K1: StatRen | L1: StatCont
A2: M0 – À qualifier | B2: Client existant | C2: Commercial IAT | D2: Récurrent | E2: P1 | F2: Oui | G2: Bon | H2: À faire | I2: Veille | J2: À former | K2: Non démarré | L2: À contacter
A3: M1 – Besoin identifié | B3: Prospect | C3: Maoula | D3: Ponctuel | E3: P2 | F3: Non | G3: À surveiller | H3: En cours | I3: Go / No-go | J3: En cours | K3: Attente cotation fournisseur | L3: Contacté
A4: M2 – Cadrage / découverte | B4: Appel d’offres | C4: Direction générale | D4: Mixte | E4: P3 | F4: Partiel | G4: À risque | H4: Fait | I4: En préparation | J4: Maîtrisé | K4: Offre envoyée | L4: RDV obtenu
A5: M3 – Offre en préparation | B5: Partenaire / apporteur | C5: Fadel Koloma / Salim Kone | H5: Bloqué | I5: Déposé | K5: Accord client | L5: Coordonnées à vérifier
A6: M4 – Offre remise | C6: À confirmer | I6: Gagné | K6: Renouvelé | L6: Ne plus contacter
A7: M5 – Négociation / signature | I7: Perdu | K7: Perdu
A8: M6 – Gagné | I8: Abandonné
A9: Perdu
A10: Clôturé / en cessation
